{"GHUMARWIN": {"BAROTA": {"BAROTA": ["BAROTA", "CHHATTER", "GHAT", "KUDI", "KUDSAI", "SUSNAL", "TAKRERA"], "GATOR": ["GATOR"], "KAROT": ["KAROT"]}, "BHAPRAL": {"BANI BHAPARALIYA": ["BANI BHAPRALIYAN"], "BANI BRAHMNNA": ["BANI BRAHMNA"], "BARAUN": ["BARAUN"], "BAROG": ["BAROG"], "BHAPRAL": ["BHAPRAL", "BURFRI", "DABRANI", "DHON", "SATHANI"], "LANJHTA": ["BELA", "DHADWARA", "LANJTA", "REHRU"]}, "BHARARI": {"BADSAI": ["BADSAI"], "LAHOT": ["DALOTA", "KHIL", "KUHADRA", "LAHOUT"], "SAMWARI": ["SUMARI"]}, "BHULSWAI": {"BHULSWAI": ["BAG", "BALH", "BHULSAI", "BURAL", "MARDI", "TASALI", "VINDALI"], "CHANOG": ["CHALOG", "CHALOG JHIWARAN"], "PAPROLA": ["PAPROLA"]}, "BUM": {"BAM": ["BARMALI", "BUM", "GALAH", "KARANGHI", "TANDA", "THANA"], "KOTLU": ["KOTLU"]}, "DABHLA": {"DABHLA": ["DABHLA", "GODI", "KOLKU"], "DARI": ["DARI"], "GALASIN": ["GALASIN", "GALASIN-IST", "GALASIN -2ND"], "GATOL": ["BAGHAL", "GATOL", "NERI"], "KURNARHI": ["KUNADI-IST", "KURNADI"], "RANDOH": ["BALH", "RANDOH", "THATHAL"], "RO": ["RAO"]}, "DADHOL": {"BHEL": ["BHEL"], "CHHANDOH": ["CHHANDOH"], "DADHOL KALAN": ["BALLU", "DADHOL BALH", "DADHOL KALLAN"], "DADHOL KHURD": ["DADHOL KHURD", "KUHAR", "MACHHYANI"], "JASWANI": ["JASWANI"], "MARIANI": ["MARIANI"]}, "DANGAR": {"CHOKHNA": ["CHOKHANA"], "DAKHIOT NICHLA": ["DAKHUIT NICHLA"], "DAKHIOT UPERLA": ["DAKUIT UPPERLA"], "DANGAR": ["DANGAR", "RANG", "ROPARI"], "HARI TALYANGAR": ["BHOLA", "HARI BANGLA", "HARI TALYANGER", "RIRU"], "PATTA MALAUTRA": ["CHOUGLA", "PATTA MALAUTRA"]}, "GAHAR": {"BAH": ["BAH"], "BHATER": ["BHATER"], "CHUDHANI": ["CHUDHANI"], "DARAHAL": ["DARAHAL"], "DEHLWIN": ["DEHLWIN", "DEHLWIN-2ND"], "GAHAR": ["GAHAR"], "JARORA": ["JARORA", "UNDA"], "KET": ["KAT"], "KHASWIN": ["KHASWIN"], "MUHANA": ["MUHANA"], "PADDORI": ["LENGERI", "PADDORI"], "PADHIAN": ["PADHIAN"], "SAWARA": ["SAWARA"]}, "GATWAR": {"BHADSIN": ["BHADSIN"], "CHAKRANA": ["CHAKRANA"], "GATWAR": ["GATWAR"], "LADHYANI": ["KANGRI", "LADHYANI", "LADHYANI JOLE", "RADDA", "ROPPERI"], "LEDHWIN": ["LETHWIN"], "THANDDORA": ["THANDOHRA"]}, "GHANDALWIN": {"BALOTA": ["BALOTA"], "BAPYAR": ["BAPYAR"], "BARICHAUK": ["BARI CHOWK"], "BHARDWAN": ["BHARDWAN"], "DHANGWAN": ["DHANGWAN"], "GHANDALWIN": ["BALH", "BANGAL", "BATIAL", "GHANDALWIN", "PACHRANI", "SUWADI"], "KAMLI": ["KAMALI"], "KOTHI": ["KOTHI"], "SAMLAH": ["SAMLAH"]}, "GHUMARWIN": {"AWDHANNI": ["AWDHANI", "SOGHI-IIND", "SOGHI-IST"], "CHUWADI": ["BHUWAI", "CHUWARI", "DARA"], "DAKRI": ["GALLIAN", "GALYANA"], "KIARI": ["CHATTROUR", "KIARI", "LAHRA"], "KULAHRU": ["BAHANI", "KULARU"], "MARHOL": ["CHANGER", "MARHOL"], "TAKREHARA": ["CHOO", "CHOWKI", "GEHRI", "HAWANI", "KHIL", "KHOLI", "PHATE", "TEKREHRA"], "TARONTARA": ["DHANERA", "GAHRU", "KOLKU", "TARONTRA", "TARONTRA-2ND"]}, "HAMBOT": {"BANIPANDTAN": ["BANI PANDITN"], "HAMBOT": ["HAMBOT"], "JANDOT": ["JANDOT"]}, "HARLOG": {"CHALELI": ["BALH", "CHALELI", "CHOWKI", "KANDUEE", "KHARI GEHRI", "KHILLAN-RA-DOHRA"], "HARLOG": ["PAWAL"], "PALTI": ["CHATOKHAR", "CHHUI GHAT", "PALTI"]}, "HATWAR": {"DIPPUR": ["DIPPUR"], "HATWAR": ["DEHRA", "DEHRA TANDA", "DEHRA UPPER", "DIARA", "HATWAR", "HATWAR HARIJAN", "KATHALEG", "MARKOTA"]}, "KASARU": {"BABHELI": ["BABHELI"], "CHHANJIAR": ["CHHANJIAR"], "JANDEHR": ["JANDEHR"], "KALOH": ["KALOH"], "KARYALAG": ["KARYALAG"], "KASARU": ["KASARU"], "KATHALAG": ["KATHALAG"]}, "KOOH MAJWAR": {"DHARAT": ["GHATTU"], "PALELA": ["LAHRA"]}, "KOT": {"BAHLILAWANA": ["BAHLI LABANA"], "KANGRI": ["KANGRI"], "KANJYANA": ["KANJIYANA"], "KOT": ["BHAL", "GARNI TAWAN", "KOT", "KOT HARROV", "KOT KASMALU", "KOT THAI", "MEHRA", "RADHIA"]}, "KOTHI": {"BADHU": ["BADHU"], "JANGAL TIUN KHAS": ["JANGAL TUIN KHAS"], "KOTHI": ["KOTHI"], "PALSOTI": ["PALSOTI- IST", "PALSOTI-2ND"], "PANIALA": ["PANIYALA", "PANIYALA-II", "PANIYALA LOWER"], "ROPARHI": ["ROPARHI"], "SOI": ["KALLAR", "SOI", "SOI-II", "TALAO"], "TIUN KHAS": ["FAYURI", "GHARWASRA", "KARNUE", "KEMB", "TUIN KHAS", "TUIN NICHALI"]}, "KUTHERA": {"BHAGOT": ["BHAGOT", "TAUNG"], "BHAWANNA": ["BHAWANNU"], "BHEL": ["BHEL", "DHARBHIYAN"], "GHALVANN": ["GHULAN"], "GHLYANNA": ["GHALYANA"], "JOL PALAKHIN": ["GAT", "GHAMARAD", "JOLE PLAKHIN", "KHATERA CHO", "KURNRDA", "KUWAL"], "KUTHERA": ["KUTEHRA"], "MALOH": ["MALOH"], "MASAUR": ["BHIYU", "MASOUR", "MASOUR JANGAL", "MASOUR UPPER"], "SARAG": ["JOLE", "SARG"], "TIHRI": ["TIHRI"]}, "LADDA": {"HALWARI": ["HALWARI"], "KHANSARA": ["KHANSARA"], "LADDA": ["LADDA"], "SALWAN": ["SALWAN"]}, "LEHRI SARAIL": {"DAMEHR": ["DOMEHRA", "LENDY", "WARI"], "GAGWAL": ["GAGWAL"], "LEHRI SARAIL": ["BALARA", "BEHRA", "BEPAR", "GHORI DA-BALH", "HARI DEVI", "JOLE", "KARAN", "LEHRI SARAIL", "SAMSAI", "SUPAD"]}, "MALYOUR": {"CHHUJALA": ["RIRI"], "JUNGLE MALYOUR": ["JANGLE MALYOUR"], "MALYOUR.": ["BAH-DHAWAR.", "PADSOLA.", "SANOTI."]}, "MARHANA": {"BHATWARA": ["BHATWARA"], "MARHANA": ["BARA DA GHAT", "BARRGARH", "BASBOD", "BHADRET", "BHEOL", "BUGG", "JHANJWAIN", "KUTHERA", "MAKRIAH", "MALOT", "MANJOTI", "MARHANA", "PAPLAH", "ROPPARI"], "MIHARA": ["CHANGAR", "GALYAT", "MIHARA", "UNDA"], "NALOG": ["NARLOG"], "PALMI": ["PALLMI"], "THANDOH": ["THANDOH"], "TIKRI": ["TIKKARI"], "TUNSU": ["TUNSU"]}, "MEHRI KATHLA": {"CHHAPROH": ["CHHAPROH", "LUHANU", "RANGARU"], "KULARI": ["DOG", "DUGALI", "KULARI"], "MAIHARAN": ["KATHLA", "KHANARI", "MEHRIN"], "NALTI": ["NALTI"], "PALIYAN": ["PALLIAN"], "PARNAL": ["JAGERI", "PARNAL"]}, "MOR SINGHI": {"BACHHRI": ["BACHHARIN", "LAHARA", "SURHAN"], "BHATOLI": ["BHATOLI"], "DIHR": ["DIHAR"], "GAIHRI PANJAIL": ["GAIHIRI PANJAIL"], "GIANA": ["GAINA", "MAR"], "KASOHAL": ["BALH LOWER", "BALH MEDAL", "BALH UPPER", "BELA", "KANJEEN", "KASOL"], "MASDHAN": ["MASDHAN"], "MOR SINGHI": ["MORSINGHI"], "SEDI": ["SEDI"]}, "NANWANA": {"GOWAL MUTHANI.": ["BALORA.", "DHAR-I.", "DHAR-II.", "GOWAL MUTHANI.", "KANGRI.", "LUSSAN.", "MUTHANI."]}, "PADYALAG": {"BARI KALAN": ["BARI KALAN"], "BARI KHURD": ["BARI KHURD"], "BHAGARWAN": ["BHAGARWAN"], "CHHAJOLI": ["CHHAGOLI", "MALEHARI"], "DAHRU": ["DOHRU"], "JANGAL PADYALAG": ["JANGAL PADYALAG"], "PADYALAG": ["PADYALAG"], "PANJAILA": ["PANJAILA"], "PANYALI": ["PANYALI"]}, "PANTEHRA": {"BALAUNNI": ["BALAUNNI"], "CHHIYANVI": ["CHHIYANVI"], "KURNAHRI": ["KURNAHRI"], "PANDTEHRA": ["BENDEHA", "DERDEHRA", "KHUBAN", "PANTEHRA", "THULA"], "PATTA RANNAUNTA": ["PATTA RANAUTAN"], "PHAGAT": ["PHAGAT"], "SONKHAR": ["SONKHAR"]}, "PATER": {"BAH RANAUTAN": ["BAH RANAUTAN"], "BAKEL": ["BAG", "BEKAL"], "BHUNDAL": ["BHUNDAL"], "KOT JHIWRAN": ["KOT JHIRRAN"], "LADHER": ["LADHER"], "MATIAL": ["MATIAL"], "PATER": ["PATER"], "REHANGLI": ["REHANGLI"], "TIKKAR KASOLIYAN": ["TIKKAR KASHOLIAN"]}, "PATTA": {"BADHU": ["BADHU", "BADHU-2ND", "BADU NAUHAL"], "BALOH": ["BALOH"], "BARI MAJHERWAN": ["BAG", "BALH-2ND", "BALH-IST", "BARI-2ND", "BARI DHAR", "BARI MAJERWON", "CHIKER", "CHURA", "KHANGER", "MAJER", "PLASI", "PRAHOO", "RAHAT", "SOHAL", "THOLTU"], "BHABBA": ["BHABA", "BHABA-2ND", "GEHERI", "KIYAR"], "GODHAN": ["GODHAN"], "JANGAL SADYAR": ["JANGAL SADYAR-2ND", "JANGAL SADYAR-IST"], "KALRI": ["KALRI"], "KARANGORHA": ["KANGRORA", "KANGRORA-2ND", "KANGRORA LOWER"], "KOTLA": ["KOTLA", "SOHANI DEVI"], "KUTHAKAR": ["KUTHAKAR"], "NAGAO": ["NAGRAO"], "PATTA": ["PATTA", "PATTA HARIJAN"], "SANAUR": ["SANOUR"], "SASAN": ["SASAN"], "SOHAL": ["SOHAL"]}, "SALAON UPARLI": {"BAUNI DHALYANI": ["BANI DHALYANI"], "KHATOT": ["KHATOT"], "MAKRI": ["MAKRI"], "SALAON UPARLI": ["SALON UPPERLI"], "SALAWONBHAPARALIYAN": ["SALON BHAPARALIN"]}, "SEU": {"BHADROG": ["BHADROG", "DELAG"], "CHERI": ["CHERI"], "JAHRI": ["JAHRI"], "JANGAL BHADAGHAT": ["JANGAL BADAGHAT"], "NASWAL": ["NASWAL", "NASWAL HARIZAN"], "RUDHANNI": ["RUDHANI"], "SEYO": ["SEO"]}, "TALWARA": {"CHHARAL": ["CHHARAL", "DALOLI"], "DHAR BARA": ["DHARWARA"], "DHATOH": ["DATOH"], "TALWARA": ["KOTLA", "TALWARA"]}, "TAROUN": {"TARAUN": ["DIBLO", "RARA", "ROPARI", "TARAUN", "TARGHEL"]}}, "JHANDUTTA": {"AMARPUR": {"AMARPUR": ["AMARPUR", "CHAPPARI", "CHAUGAN", "DAKHETER", "DEOD BASTI", "GUJAR BASTI", "LAMBE JOLE", "REWAL TAL", "RIHRI", "SUKLA BASTI", "SUKRI"], "DARIANA": ["BIAYANA", "DARIANA", "PLAY"], "JANGAL OUSAL": ["DHABYANI", "DHAD", "JAMAN TIKER", "JANGAL OUSAL"], "PANOL": ["BAG", "HADSAR", "JEORA KHUNGAR", "KANGER", "KHARALA", "KURLAG", "PANOL", "TAL"]}, "AUHAR": {"AUHAR": ["AUHER", "AUHER-IV", "FATLIYAN", "KATHINGAL"], "DARIYANA": ["DARIYANA", "GHERA", "RAHIYAN"], "KASEH": ["KASEH"], "ROHIN": ["BHAYATER", "BHIGATA", "BURHAL", "JOLE", "JUNG DOHRA", "ROHIN", "TARGAMAT"]}, "BADGAON": {"BADGOAN": ["BADGON", "BALH", "BANGARIAN", "BHIRA", "GATTE", "HAWANI", "KARLOTEY", "KDUKHAR", "KHIL", "UNDA"], "FATOH": ["FATOH", "KHANETI"], "JHARERI": ["BALH", "JHARERI"], "RAROH": ["RADOH"], "RI": ["REE"], "TIHRA": ["TIHRA"]}, "BADOL": {"BADOL": ["BADOL", "RIDI"], "JAMLI": ["GULANI", "JABBLU", "JAMLI", "KOKKAR"], "JOAHA": ["JUHA", "TARERI"], "POLI": ["NASHAN", "PANJEEN", "PLOT", "POLI"], "TANIOR": ["TANUR"], "THORAHAN": ["DHANATHER", "THURAN"]}, "BAKROA": {"BAGTEHRU": ["BAG", "BAGTHERU", "BAGTHERU-II", "BAGTHERU-IV", "GALYANU", "SUGALTI", "TAL", "THERU"], "BAKROA": ["BAKROA", "BGHER-2ND", "BHAGER-1", "CHAIR"], "BALHU KARIALAN": ["BALHU- KARIALAN", "BALLU-2ND", "BANI", "KHARYALA"], "GHUMANI": ["GHUMANI-IST-UPPER", "GHUMANI-NICHLI", "GHUMANI-V"], "KHURARI": ["KHURARI-III"], "MAJHAUN": ["KOT", "MAJHAUN", "MAJHAUN (HB)"], "PEHRWIN": ["PEHERWIN", "PEHERWIN II"]}, "BALGHAR": {"AMROHA": ["AMROA", "HARIJAN BASTI BALI"], "BALGHAR": ["BAL JOLE REHALA", "BALGHAR", "BHAKHRA", "GEHRI", "JABAL", "KHURJHAIL", "KOLKA", "MANDWAN", "MATERI", "PAPLAH"], "DHARAR": ["DHARAR", "KAMERTA", "KHUBAN"], "JANGAL KHURJAL": ["JANGAL KHUJRAL"], "JANGAL MATERI": ["JANGAL MATERI"], "PARAHU": ["BANI", "KABRETA", "KUT", "PARHOO"], "THAPPAR": ["ANAND GHAT", "BALHU", "GUHAN", "THAPER"]}, "BALH SEENA": {"BALH SEENA": ["BALSHSEENA", "BANYAL BALH", "KULTH BANI", "LEHRI", "SAIN BALH", "TARELLU"], "GUJRERA": ["BUMBLU", "GUJREHRA", "THANDA", "TIBBA"], "JANGAL DHOLI KHALA": ["JUNGLE DHOLI KHALA"], "KATHIUN": ["JATTI SIDH", "KATHUINE", "KUND"]}, "BALOH": {"BALOH": ["BALHI", "BALLU", "BALOH"], "BHALU": ["BHALLU", "HARIZEN BASTI BHALLU"], "DOL LASAWA": ["DOL HARIZEN BASTI", "DOL LASWA"], "FAGOG": ["BUNJEHLI", "FAGOG", "JOHAD", "RIDDOH", "ROPPRI"], "KHAROTA": ["BEHAN", "GADHERU", "KHAROONI", "KHAROTA", "RAPPER"], "RIANA": ["RIYANA"], "SINGASIWIN": ["BANDEHRA", "SANGASWIN", "SANGASWIN LOWER"]}, "BARGAON GALU": {"BADGAON": ["BADGAON", "BADGAON-2ND"], "BUKHAR": ["BUKHAR"], "DUHAK": ["AMLIAN", "DUHAK"], "JANGAL GHARWASRA": ["JANGAL GHARWASAR"], "JANGAL GHATARWASAN": ["JANGAL GHATARWASAN"], "UP MOHAL DOMEHRA": ["NIHANI", "UP MOHAL DOMEHRA"]}, "BEHNA BRAHMNA": {"BAHNAN BRAHMANA": ["BEHNA BERHMNA", "KATHER", "KATHER BHANI", "LOWER BEHNA"], "BALA": ["BADI WALAY", "BALA", "BALA CHANGER", "GWANTLU", "LOWER BALA", "MATOLI", "PUDH", "RIHRI"], "BEHRAN": ["BADER", "BEHRAN", "JANGLA", "JHARERI", "KHAKRE", "KHILU", "KOHLI", "KOTLU", "THIDU", "TIKKERI"]}, "BEHNA JATAN": {"BAIHNA JATAN": ["BARI HAR", "BARWAR", "BEHNA JATTA", "DODRU", "DOL", "JARAD", "NALYAR", "SEERU", "SMORI"], "BERI DAROLA": ["BEHRI DALON"], "KALAR": ["KALLER"], "KOTHI": ["KOTHI", "SAPAREHLU"], "LADHERA": ["LADEHRA"], "SOPTA": ["SOPTA"]}, "BERI MIAN": {"BAIRIMIYAN": ["BERI MAIN"], "BARSANDH": ["BARSAND"], "JAJJAR": ["JAJJAR"]}, "BERTHIN": {"BARTHIN": ["BERTHIN", "KANDIYANA", "KHAWARU", "SERGAL CHOWK"], "BHATAULI": ["BHATOLI", "LAHARA"], "DHAROTI": ["DHAROTI", "KOTLA"], "GUAON": ["GUOAN", "JOLE", "KHAN"], "MAUHIN": ["MOHIN"], "SARGAL": ["CHIKANSHA", "SERGAL"], "TIHRI": ["BALH", "MUNDKHAR", "TEHRI"]}, "BHAROLI  KALAN": {"BHAROLI KALAN": ["BAG", "BAYIN", "BHAROLI KALLAN", "KUTLA TIKKER", "PLAOUN"], "BHAROLI KHURD": ["BAGROO", "BEHRA", "BHAROLI KHURD", "CHANNO", "GATHRIAN", "GHERYANI", "KENDUTH", "MATKHAN"], "BHATER KALAN": ["BHATER KALLAN", "CHELIAN", "KUHARA", "LEHDA", "TIKKER"], "JANGAL BHAROLI KALAN": ["JANGAL BHAROLI KALLAN"]}, "CHHAT": {"CHHAT": ["CHANJIARA", "CHAROL", "CHATT", "JOLE", "LAREH", "MANDYAL", "SAMLOHAL"], "LURHANI": ["ARTIAN", "LAROO", "LURHANI"], "SANDYAR": ["ANDROLI", "BARAD", "JARAL", "KACHUIT", "PANETA", "SANDYAR", "THAPER"], "SIYOTHA": ["BHERAGHAT", "PANERAD", "SEOTHA"]}, "DAHAD": {"DAFER": ["BAHLI", "BHOLI", "DAFER"], "DAHAD": ["BANGERA", "BHUD", "CHOWKI", "DAHAD", "DARA", "KADHERA", "UPPER DAHAD"], "DEHAN": ["DEHAN"], "DEHLWIN": ["DEHLWIN", "KHIL", "PARLA DEHLWIN"], "KUTHERA": ["KUTHERA"], "SANGH": ["SANGH"], "TIKRI": ["CHOR BAIN", "TANGLOH", "TIKKRI"]}, "DAMLI": {"BEHLAG": ["BEHLAG"], "BHATER": ["BHATER"], "CHHAT": ["CHHAT"], "DHAMLI": ["DAMLI", "RISHIKESH"], "DHRASANI": ["BARTA", "DHANETA", "DHARARSANI", "GOALI", "KAPARE", "SEHAL"], "JANGAL GHANIRI": ["JANGAL GHINIRI"], "KOHNA": ["KOHINA"], "MAROHIAN": ["MAROWIAN"], "PATTA": ["PATTA"], "SAMLETA": ["DOON", "SAMLETA"]}, "DHANI": {"BAHL": ["BEHL", "JODDA", "LEDDA"], "DHANI": ["BIHAR", "DHANI", "KATHLI", "TIHRU", "TIKKER"], "DHANOLA": ["DHANOLLA", "GARWALI", "TIBA"], "JANGAL SASOTA DHANOLA": ["JANGAL SASOTA DHANOLA"], "KHARLI": ["BATURA", "JAMANWALI", "KATHLI", "KHARLI", "KOKRU", "NICHLI"], "PAKHAR": ["HARIZAN BASTI", "PAKHAR"], "PARLI": ["NOLLA", "PARLI"], "SASOTA": ["GARHU", "KAKRU", "NOLLA", "PAREDA", "SASOTA", "THANKAR"]}, "DHARI BHARI": {"DHARI BHARI": ["BHARI", "DAL", "DARI"], "KHARWIN": ["KAHARWIN"], "KULAHAN": ["KULAHAN"], "RACHHERA": ["BADHOG", "CHANGER", "CHAPPRA", "PUNGLIAN", "RACHERA", "RIHDI"], "SAMLETU": ["SAMLETU"]}, "DUDIAN": {"DHOLAG CHAKNAR": ["BANYEN", "CHAKNAL", "CHERHED", "CHHIR", "DHOLAK CHAKNAR", "GEHRIAN", "KANGOALI", "SASHAL"], "DUDHIAN": ["DUDIAN", "NICHLI SATH", "TAL"], "JANGAL DHOLAG CHAKNAR": ["JANGAL TOLAG CHAKNAR"], "JANGAL JHUNJNU": ["JANGAL JUNJNU"], "JANGAL LADEH": ["JANGAL LODH"], "JHUNJNU": ["DOLE", "DORA", "JHUNJANU"], "JOHAR KALSAN": ["JOHARKALSAN"], "JOHR SUNDRI": ["JOHR SUNDRI"]}, "DUSHLEHRA": {"DASLEHRA": ["DUSLEHRA"], "GOCHAR": ["GOCHER"], "JANGAL CHALAILEE": ["JANGAL CHALAILEE"], "JANGAL GOCHAR": ["JANGAL GOCHAR"], "JHAMRARIARN": ["BIBBI  SATH", "JHAMRARIN", "RAKKAR"]}, "FATOH": {"CHHIBRIN": ["CHHIBRIN", "CHHLOG"], "FATOH": ["BALH", "DHARARI", "FATOH", "FATOH-2ND", "KALRI"], "NALTI": ["DUGLI-1", "DUGLI-II", "DUGLI-III", "DUGLI-IV", "NALTI", "NALTI-II", "NALTI-III", "NALTI-IV", "NALTI-V", "NALTI-VI", "NALTI-VII"], "PANOH": ["PANOH", "TARED", "UNDH"], "ROPA": ["BORAY CHHRAD", "BUDHAG", "ROOPA"], "SANUR": ["BADOG", "SANAUR", "TIKKARI"], "SARTI": ["SARTI", "SARTI- 2ND"]}, "GALIAN": {"BAROHA": ["BAG BAROHA", "BAROHA", "LOWER BAROHA", "THEDA"], "GALIAN": ["GALLIAN", "GALLIAN BAZAR", "GALLIAN GORKA"], "SER": ["CHAEHAR", "NUKHRAL", "RIDI", "SER", "SER CHANGAR"], "TUNGRI": ["BUJRAIN", "TUNGRE"]}, "GEHRWIN": {"GEHRWIN": ["BADIAL", "BINDWIN", "CHUMAN", "GEHRWIN", "GUGA GEHRWIN", "KAMAL BALH", "KHARA GOHAR", "LEHRI BADIAL", "SERWA-I", "SERWA -II"], "JANGAL BAGRA": ["JANGAL BAGRA"], "JANGAL JAMOTHI": ["JANGAL JAMOTHI"]}, "GHANDIR": {"MALARI": ["GEHRA", "KARLATA", "MALARI", "UPPER TARELLU"]}, "GHARAN": {"BAONGRI": ["BONGRI"], "GHARAHAN": ["GHARAN", "JUNGLE GHARAN"], "GHUMARPUR": ["GHUMARPUR"], "JANGAL GANGLOH": ["JANGAL GANGLOH"], "JANGAL GHRANN": ["JANGAL GHARAN"], "JANGAL KHAMERA KHURD": ["JANGAL KHAMERA KHURD"], "JANGAL MAJHER": ["JANGAL MAJHER"], "JAROT": ["JAROT"], "JOL": ["JOL"], "JUNGLE MEHJUJA MEHDUDA": ["JUNGLE MEHJUJA MEHDUDA"], "KHAMERA KALAN": ["KHAMERA KALAN"], "MAJHER": ["MANJHER"]}, "HIRAPUR": {"BAROA": ["BAROA"], "BHAJWANI": ["BHAJWANI", "ROPA"], "HIRAPUR": ["HIRAPUR"], "KHIRSI": ["KASEH"]}, "JANGLA": {"GHANIAR": ["GHANIAR"], "JAMOI": ["JAMOI"], "JANGAL SERY SALASI": ["JANGLE SERI SALASI"], "JANGLA": ["BALH", "BALRA", "CHATYAL BALH", "CHAUMB", "DABBER", "JANGLA", "KHERA", "SHITLA"], "KHIRSHI": ["KHIRSHI"], "KHUDAI": ["KHUDAI"], "MEKHWIN": ["MEHKHWIN"], "SALASI": ["SALASI"], "SANDRU": ["SUNDRU"]}, "JEJWIN": {"BAITHRIN": ["BATHRIN", "GHARANWALI", "GUGAWALI", "LADDHA"], "BALHI MRETA": ["BALHI MARETA", "JANGAL MARETA", "JOLE", "KHALA", "MALHI", "SAPPER"], "BHADOL": ["BHADOL"], "CHAJOTI": ["CHHANJOTI", "LOWER CHHANJOTI", "NAND", "TIB", "TIKKER", "UPPER CHHANJOTI"], "CHALAWA": ["CHALAWA"], "DAROH": ["DROH", "TIKKER", "UPPER DAROH"], "DOHG": ["DOHAG", "JABBLI", "TINDI", "UPPER DOHAG"], "DURGHAT": ["DURGHAT", "GADERE", "LOWER DURGHAT", "TARKHOL", "TIKKER", "UPPER DURGHAT"], "JANGAL CHALAWA": ["JANGAL CHALAWA"], "JANGAL DURGHAT": ["JANGAL DURGHAT"], "JANGAL TARKHOLA": ["JANGAL TERKHOLA"], "JEJWIN": ["GEHRI", "JEJWIN"], "KARLATA": ["KARLATA"], "KATHERAN": ["KUTHERAN"], "KATHYUN": ["KATTYUN"], "KHAROHL": ["KHAROL"], "KHERI": ["KHERI", "LOWER KHERI", "TIBBIWALI"], "MAKRI": ["BASOWALI", "KHARLI", "LOWER MAKARI", "MAKARI"], "RETI": ["RATI"], "SILH": ["GEHRI", "MIHRA", "SILH"], "SILLVIN": ["NERI", "RIHALA", "RIHALI", "SILLWIN", "TIKKER"], "SOH": ["LOWER SOH", "SOH"]}, "JHABOLA": {"JHABOLA": ["CHAWLH", "GUGA SATH", "HAWANI", "JAROR", "JHABOLA", "KHUBAN", "RIYALI", "TAMBRI"]}, "JHANDUTTA": {"JHANDUTA DOAM": ["JAKHA RA FAT", "JHANDUTTA DOAM (BADDI BILLLOUR", "LATHYANI", "PIROG", "ROPPERI", "TAGOH"], "JHANDUTA SOAM": ["BADWAR BADI", "BIJLU KA HAR", "CHOTI BADWAR", "JATHWIN", "JHANDUTTA SOAM (CHOTI BILOUR)", "MATYANA", "WANDA"], "JHANDUTTA": ["DHONI", "JHANDU", "JHANDUTTA ABBAL", "LAHARY", "MUKRANA"]}, "KALOL": {"BAGLA": ["BAGLA", "DALIAN"], "BAKAIN": ["BAKAIN", "LEDERA", "PIPALIBANDA", "UHANI", "UPPER BAKAIN"], "JANGAL JHANGWAN": ["JUNGLE JHANGWAN"], "JANGAL JHARERI": ["JUNGLE JHARERI"], "JANGAL KALOL": ["JANGAL KALOL"], "JANGAL KHAIRIYAN BHARARI": ["JUNGLE KHAIRIYAN BHARI"], "JHARERI": ["BAGA", "GHARAMARA", "JHARERI", "KHARAKARA", "LOWER JHARERI", "NAMNALA"], "KALOL": ["BHOLIAN", "CHAMARDI", "GIHRI", "KALOL", "KARLATA", "KEHRAN", "MAJHAR", "TARAD", "TIKKER"], "KHAIRIYAN BHARARI": ["BHARI", "HAR", "KHAERIAN BHARI", "NENI-KA-HAR", "PUD"], "LAG": ["BAG", "BEHLA", "BHALIAN", "DAL", "LAG"], "TIHRI": ["GOPLEYALI", "GURNADI", "KAMLOAO", "KHIL", "THIRI"]}, "KAPAHARA": {"HIMAR": ["CHALARAN", "DINWAN", "GHAGDYANI", "GURNARA"], "KHUNGAN": ["KHUNGAN"]}, "KARLOTI": {"GALIAN": ["GALLIAN"], "KARLOTI": ["GHUMARTI", "KARLOTI", "KHADAR", "MAKRU"], "MACHHWAN": ["KALSI", "MUCHHAN", "ROPPERI"], "MAKDA": ["MAKRA"], "SUNALI": ["JANEH", "SUNALI"]}, "KOSARIYAN": {"DHANGU BAONGRI": ["DANGU BANGRI", "KUT BANGRU"], "JANGAL JAI SHRI DEVI": ["JAI SHRI DEVI JANGAL", "JAI SHRI DEVI JANGAL -II"], "KOSRIAN": ["KOSHRIAN"], "KOTHI": ["KOTHI"], "PIAUNGLI": ["PIAUNGLA"]}, "KOTLU BRAHMNA": {"DUN": ["DOON LOWER", "DUN", "JAJROO"], "JANGLE DOON": ["JANGLE DOON"], "KALLAR": ["KALLAR", "KALLAR UPPER"], "KOTLU BANDRIAN": ["BAROT", "KOTLU BINDRIAN"], "KOTLU BRAHMNA": ["KOTLU BEHNA", "KOTLU BRAHMNA"]}, "KULJYAR": {"ARLOH": ["ARLOH"], "BHATER KUNDO": ["BHATER KUNDO"], "CHANGAR MISRAN": ["CHANGER MIBBAN"], "CHAUNTA": ["CHAUNTA"], "GOIND": ["GOIND"], "JADU": ["JADDU"], "JANGAL THATHAL CHAUNTA": ["JANGAL THATHAL"], "JOHAR DHYANI": ["JOHAR DHIYANI"], "KAROH": ["KAROH"], "KHAMERA KHURD": ["KHAMERA KHURD"], "KULJIAR": ["KULZIAR"], "ULJYAR": ["ULZIAR"]}, "MALANGAN": {"KALAR": ["BANGOLI", "KALLAR", "KURMUND", "TARKHOLLA"], "KUTHERA": ["BALH", "CHHARI", "JOLE", "KUTHERA", "TANDA"], "MALANGAN": ["BHUSAL", "CHIHATER", "MALANGAN", "NICHLI FATH"]}, "MALRAON": {"BOHRWIN": ["BARNALA", "BOHARWIN", "DORA BALH"], "D.P.F.BAHL": ["D.P.F. BALH"], "D.P.F.KOZAR": ["D.P.F. KOZER"], "D.P.F.MALRAON": ["DPF MALROAN"], "MALRAUN": ["BALHI", "BEHRUA", "CHRADA", "DOLE", "DUKLA", "GHARAN", "KOTLI", "MALROAN", "NARI"], "SARAK KI JOHAR": ["SARAK KI JOHAR"]}, "NAGHIAR": {"BHAGATPUR": ["BHAGATPUR"], "NAGHIAR": ["KHU SATH", "KUT", "MARUHRA", "NAGHIAR", "SIDH SATH", "THERU"]}, "NAKHLERA": {"BASANDWARI": ["BASANDWARI", "THURALA"], "GHARANN": ["DALIAN", "DOHRA", "GHARAN"], "KHALSAI": ["GAHAR", "KHALSAI"], "LURHAR": ["BAJOURA", "DORAWALA", "LURHAR", "TINDIWALA"], "MATLA": ["MATLA"], "MUSAHAN": ["MUSHAN"], "NAKHLERA": ["NEKHLEHRA"], "PASOL": ["CHANGER", "PASOL"], "TIHRI": ["NICHLA HAR", "TIHRI"]}, "PAPLAH": {"DHALOH": ["DALOH"], "JUNALA": ["JUNALA"], "MAHORA": ["KAPAHRA", "MOHRA"], "MUND KHAR": ["MUNDKHAR"], "PANIALA": ["PANIALA"], "PAPLAH": ["PAPLAH"], "PLASLA": ["PLASLA"], "TALAO": ["TALAO"]}, "PAPLOA": {"BUHAR": ["BUHAR", "BUHAR TAL", "BUHAR TIKKAR", "DALH"], "DOL": ["DOL"], "GADIANA": ["BANDAWALI", "CHOR GHAT", "DPF GADIANA", "GADIANA", "GORKHWALI", "LALAN"], "GAH": ["BARIYAN", "DAGODA", "DOLE", "GAH", "GHORI", "MANDIKHAR", "MOHALI", "SAREPANI", "THANA", "THANKAR"], "JANGAL KOT MALHOT": ["JUNGLE KOT MALHOT"], "KOT": ["BADEEN", "BARAHIAN", "KOT"], "PAPLOA": ["ARNALI", "BERAWALI", "CHIDA", "DABBEWALI", "GEHRI", "PAPLOA", "REHALI"]}, "ROHAL": {"BHADOL": ["BADHOL-2ND", "BAHAL", "BALRAHA", "BHADOL", "BHADOL-IST", "MADAHGI"], "DOKRU": ["DOKRU", "GAJREARA", "KHUJRAL"], "JEORA": ["JEORA", "PARLA JEORA"], "LAIHAD": ["LEHR"], "NAGRAON": ["DOL", "KOTLU", "NAGROUN"], "NAHRAL": ["BHUD", "KARTHIAL", "NAHRAL", "NERI"], "NAND": ["BALETA", "BALOYANI", "NAND"], "ROHAL": ["CHANGER-I", "CHANGER-II", "GHAT", "JHULA", "KUDAN", "ROLE"]}, "SALWAR": {"BADHU": ["BADDU"], "BALH CHALOG": ["BAL CHALOG", "BALH", "CHANGROT", "THERU"], "BALH FATU": ["BALH FATTU"], "BHALIAR": ["BHALIYAR"], "DHANAR": ["DHANER", "GOBBER", "KHARI", "MAROTAN-2ND", "PAHIA"], "JANGAL BHAGPHAL": ["JANGAL BHAGPHAL"], "JANGAL BHALIAR": ["JANGAL BHALIAR"], "JANGAL KAKREHAR": ["JANGAL KAKREHAR"], "JANGAL MAROTAN": ["JANGAL MAROTAN"], "KAKREHAR": ["KAKRAIR", "KAKRAIR TIKKER", "KANGAR"], "MALHOT": ["CHIMLAU", "MALOT", "MALOT GHAT", "MALOT TIKER", "PLAKHI"], "MAROTAN": ["MAROTAN", "PAHIA"], "MOA": ["MOA"], "PHUPLI JHALWANA": ["DUKALI", "PHUPLI", "PHUPLI JALWANA"], "SALWAR": ["BAG", "GHORE GHAT", "NAIN", "SALWAR", "TWALI"], "SERI": ["KANDELLA", "SHERI"]}, "SAMOH": {"BIJEPUR": ["BIJEPUR"], "JANGAL DHINGU": ["JANGAL DINGU"], "JANGAL TUNGRI": ["JANGAL TUNGRI"], "KUJEL": ["KAJAIL"], "NERAS": ["BHAJWAN", "NERAS", "NERAS-II", "NERAS CHANGER", "NERAS DEVI"], "NIHAN": ["NIHAN", "NIHAN-I", "NIHAN_II"], "RELI": ["RAILY", "RAILY LOWER"], "SAMOH": ["SAMOH"]}, "SANIHRA": {"BAROTI": ["BAROTI"], "GANGLOH": ["GANGLOH"], "JANGAL BAROTI": ["JANGAL BAROTI"], "JANGAL SANIRA": ["JANGAL SANIHRA"], "SANIRA": ["SANIHRA"]}, "SUNHANI": {"BARD": ["BALHI", "BARD", "BARD UPPER HAR"], "DOHAK": ["DUHAK", "DUHAK DHAR", "MANAN DOLI BASSI"], "SUNHANI": ["BALRA SUNHANI", "DOHRAG", "GOHAR", "LEHAR", "SUNHANI"]}}, "SADAR": {"BAMTA": {"BADHIAT": ["BADHAYAT-I.", "BADHAYAT-II.", "CHABRIAN-I.", "CHABRIAN."], "BAIHL KANDAILA": ["BEHAL KANDELA-I.", "BEHAL KANDELA-II.", "BEHAL KANDELA-III.", "BEHAL KANDELA-IV.", "BEHAL KANDELA-V.", "BEHAL KANDELA."], "BAMTA": ["BAMTA-I.", "BAMTA-II.", "BAMTA-III.", "BAMTA."], "DANOH": ["DANOH", "DANOH -III"], "KIARIAN": ["KHERIAN-I.", "KHERIAN-II.", "KHERIAN."], "NIHAL": ["NIHAL", "NIHAL-I", "NIHAL-II", "NIHAL-III", "NIHAL-IV", "NIHAL-VI", "NIHAL-VII"], "OEL": ["OEL-4", "OEL-V.", "OEL-VI."]}, "BASSI": {"BASSI": ["BASSI", "GUJAR BASTI", "GUJAR BASTI THERA", "HARIJAN BASTI", "LOWER BASTI"]}, "BINOLA": {"BAGI": ["CHANGER."]}, "CHANDPUR": {"CHANDPUR": ["CHANDPUR", "CHANDPUR-I", "CHANDPUR-II", "CHANDPUR-III", "CHANDPUR-V", "CHANDPUR-VI", "CHANDPUR-VII", "CHANDPUR-VIII"], "GHUGRAR": ["GHUGRAR", "GHUGRAR-I", "GHUGRAR-II", "GHUGRAR-III", "GHUGRAR HARIZEN BASTI", "GHUGRAR HARIZEN BASTI-II", "GHUGRAR HARIZEN BASTI-III", "GHUGRAR HARIZEN BASTI-IV"], "KHAN": ["KHAN", "KHAN-I", "KHAN-II", "KHAN-III"], "KIARA": ["KIARA"], "KOTHI": ["KOTHI", "KOTHI (H.B)-I"], "LUNU KANAITA": ["LUHNOO", "LUHNOO - I"], "TALWAR": ["TALWAR", "TALWAR-I", "TALWAR-II", "TALWAR-III"], "TRER": ["TARER", "TARER-I", "TARER -II", "TARER HARIZEN BASTI -I", "TARER HARIZEN BASTI -II"]}, "CHHAKOH": {"CHHAKOH": ["CHHAKOH", "HADODI THARU", "KATAL"], "KAYARAN": ["KAYARAN"], "SAMOG BRAHMNA": ["SAMOG BRAHMNA"], "SAMOG KANAITAN": ["SAMOG KANAITAN"]}, "CHHAROL": {"BAHL KARAINTA": ["BALH KARETA"], "BHAL POTHAR": ["BALH POTHER"], "CHAIHRI": ["CHEHARI"], "CHHAROL": ["BURAL", "CHHAROL", "LOWER BURAL", "LOWER CHHAROL"], "JAMLI": ["BANALI", "JAMLI", "UPPER JAMLI (NH-21)"], "NERI": ["BHEDLI", "LOWER BHEDLI", "MANDPUR", "NERI"]}, "DEOLI": {"DALTA": ["DALTA"], "DEOLI": ["BALCHAL", "DEOLI", "SARYALI", "SHANOW"], "GOIND": ["GOIND"], "MANAR": ["MANNER"]}, "DEOTH": {"BHAJUN": ["CHANGER", "KOTLA"], "DEOTH": ["DEOTH"], "HUMBER": ["HUMBER"], "KOTHI": ["KOTHI", "WAHNI"], "MAJHER": ["MAJHER"], "VAO": ["VAO"]}, "DHAR TATOH": {"DHAR TATOH": ["DROBER", "HUDDU", "JAJJAR", "NALI-CHANGER", "NERI", "PARNALI"]}, "DHAROT": {"JHIRIAN": ["JHIRIYAN"], "LAKHNUN": ["LAKHNOO"]}, "DHUON-KOTHI": {"BAUHAT": ["BAUHT"], "DHAON KOTHI": ["DHAUN KOTHI"], "GAHAR": ["GAHAR", "NATRA"], "KANAUN": ["KANAUN"], "KASOL": ["KASOL", "KHOB", "PATTI"], "TIKRI": ["KUDDI", "TIKKRI"]}, "GHAWANDAL": {"BADHARAN": ["KAPARAH BASTI"], "BADOH": ["BADOH HARIZAN BASTI"], "BHATEHR": ["TIBA"], "KANFARA": ["CHAMARARI"], "KANFARA DPF": ["KANFARA HARIZAN BASTI"], "MALETA": ["BAHLI"], "MALETA DPF": ["DHARARA", "THALIYA"]}, "JUKHALA": {"DHAMTHAL": ["HAMLET OF DHAMTHAL -I"]}, "KACHOULI": {"BADHU": ["BADDU", "LOWER BADDU"], "CHILLA": ["CHILLA", "JANOTA", "JOHARI-BABEEN", "LOWER CHILLA"], "KACHOLI": ["KACHOULI"], "SAI BRAHMNA": ["LOWER SAI BRAHMANA", "SAI BRAHMANA"], "SAI KANAITAN": ["BEHAL", "FAKRED", "SAI KANETA"], "SAUTI": ["LOWER SAUTEE", "SAUTEE"]}, "KANDROUR": {"BANDLA MIYAN": ["BENDLA MIAN", "BENDLA MIAN-II", "BENDLA MIAN-III", "BENDLA MIAN-IV", "BENDLA MIAN-V", "BENDLA MIAN -I", "BENDLA MIAN(H B)-I", "BENDLA MIAN(H B)-II"], "BENLA BRAHMANA": ["BALH", "BENDLA BRAHMANA", "BENDLA BRAHMANA-I", "BENDLA BRAHMANA-II", "BENDLA BRAHMANA-III", "BENDLA BRAHMANA-IV", "BENDLA BRAHMANA-V"], "KANDROR": ["CHAKLI-II", "CHAKLI-III", "CHAKLI -I", "DHAR-I", "DHAR-II", "DHAR HARIZEN BASTI", "GADHARU", "KANDROUR-I", "KANDROUR-III", "KANDROUR-V", "KANDROUR -II", "KANDROUR -IV", "PARLA HEAD", "SARH-I", "SARH-II"]}, "KHARKARI": {"KHARLEARI": ["BONTTA", "GHARAN", "HUYANI"]}, "KOT-KHAS": {"BASSA": ["BASA KANAIT", "HARIJAN BASTI"], "GURU-KA-LAHAUR": ["GURU KA LAHORE", "RAJ PUT BASTI"], "JANGAL MEHDUDA GURU KA LAHAUR": ["CHOEY WALE", "JUNGLE MEHDODA GURU KA LAHORE"], "JHIRA": ["BARBARE GUJAR", "HARIJAN BASTI", "JHIRA GUJJAR", "JHIRA KHAS"], "KANGOWALI": ["KOT"], "KHERI BAOHOLRA": ["KHERI HARIJAN"], "RANNI": ["RAJ PUT BASTI", "RANNI HARIJAN BASTI"]}, "KOTLA": {"KOLNU": ["HARIZAN BASTI-I", "HARIZAN BASTI-II", "KOLNOO-I", "KOLNOO-II", "KOLNOO-III"], "KOTLA": ["KOTLA"], "NIHARKHAN BASLA": ["NIHARKHAN"]}, "KUDDI": {"DELAG": ["CHALAMA", "CHALAMA GALU", "DELAG", "DELAG -I", "DELAG BADDU", "DELAG DARAHARI", "DELAG DOL", "DELAG GALLAN", "DELAG HAR", "DELAG HARIZEN BASTI", "DELAG HARIZEN BASTI -II", "DELAG HARZEN BASTI II", "DELAG II", "DELAG III", "DELAG IV", "DELAG JOL", "DELAG KUNIH", "DELAG LANGNA", "DELAG LANI", "DELAG MARAYALU", "DELAG TAEARE", "DELAG TILRU", "DELAG V", "DELAG VI", "DELAG VII"], "JANGAL JHALEDA": ["JUNGLE CHALEDA"], "KHANGAR": ["KHANGER"]}, "KUTEHLA": {"BHULAN": ["BHULAN", "KHALTU"], "DADRANA": ["BARNAL"], "DHAR BHARTHA": ["DHARBRTHA", "SURAL"], "DHAR BINDRYAN": ["DHAR BINDRA"], "KATHLA": ["BAPAR", "KATHLA", "LOLAWAN"], "KIAHRAN": ["DULANA", "KAYARIAN"], "MAJHER": ["KHURANI", "MAJHER", "NAL", "REE", "THARU"], "MATNOH": ["MATNOH", "TIKKAR JANGLU"], "PANGA": ["BURANI"], "SAMLETU": ["SAMELTU"], "THAPNA": ["KAITAL", "KALLAR", "KHALT"]}, "LEHRI": {"DHALET": ["KAHALA", "NEELAWAS", "THATHAL BASTI", "TIBIBASTI"], "JANGAL MEHDUDA DHALET": ["JUNGLE MEHDUDA DULET"], "JUNGLI LEHRI": ["JUNGLE LEHRI"], "LEHRI": ["DEHRA"], "PALSED": ["BAAG", "DATOIYAN", "GUJAR TIBI", "HARIJAN PALSED", "JHIRHA", "JUNGLE PALSED", "KALA KUND", "TILLAWALI"]}, "MAJARI": {"MAJARI": ["DHARIYANA", "MAJARI"]}, "MAKRI MARKAND": {"BAROG": ["BAROG"]}, "MANDYALI": {"MANDHALI": ["LOWERMADYALI"]}, "MEATHI": {"CHIRAN": ["CHARAN"], "DADHOG": ["DADHOG"], "KHOI": ["KHUI", "KHUI (NAL -TIKKER)"], "LADHERA KHURD": ["LADEHRA-KHURD"], "LAG": ["LAG", "LAG-TIKKER"], "MAITHI": ["BALH-RA-HAR", "LOWER MEATHI TIKKER", "MEATHI", "MEATHI-TIKKER"], "NALI PALON": ["NALI-PLON", "NALI-PLON (TIKKER)"], "PALAH": ["PLAH", "PLAH-TIKKAR"], "SAIKLI": ["KARYAN", "SAIKALI"], "TARAMBRI": ["TARAMBRI"]}, "NAKRANA": {"NAKRANA": ["CHAHRU", "CHAT", "SWANA", "TURKHI"], "OEL": ["KHANDAL", "KOTHI", "OEL"]}, "NAMHOL": {"BAG KHURD": ["BAG KHURD"]}, "NICHLI BHATER": {"BAGHARIN": ["DORA."], "BAHLI CHALEDA": ["BALHI CHALEDA", "BALHI CHALEDA HARIZEN BASTI"], "BALHI VILAN": ["BALHI VILAN -I", "BALHI VILAN -II"], "BATHO": ["REHRA.", "RIHARA."], "DALLI": ["DALLI", "DALLI-II", "DALLI -I", "DALLI SALOO", "DALLI STRALU", "DALLI THATHAL"], "JANGAL BRANS": ["DEOLI CHANGER", "DEOLI MANGROT", "GHAGUS", "JANGAL BRANCE", "KAWAI"]}, "PANJGAIN": {"PANJGAIN": ["KUNANU", "THARMANAL"]}, "RAGHUNATHPURA": {"GARNAL": ["GARNAL"]}, "RAJPURA": {"CHALAILI": ["CHALELI"]}, "ROUR JAMAN": {"BAROTA DOBHALA": ["BAROTA", "DABALA", "HADDANWALI"]}, "SAI KHARSI": {"KHARSI BRAHMNA": ["LARAGHAT"], "LEONGARI BRAHMNA": ["BAHANI", "CHANGER", "RIHRI"], "LEONGARI KANAITAN": ["HAWANI", "KHANGER", "MADWAD"]}, "SALOA": {"KHAL": ["JATTAN THA MODE", "KHAK GAJAN", "KHAL TIBA", "KOLKA", "THERAN"]}, "SIHRA": {"BADSAUR": ["BADSAOR"], "DHAMNAN": ["DHAMNA"]}, "SIKROHA": {"CHANDPUR": ["DAN-RA-HAR"]}, "SIYOHLA": {"SIYOHLA": ["SANGLERI"]}, "SOLDHA": {"CHAMBI": ["RIHRI"], "GARAWAR": ["DOLL"], "GHAMRARA": ["BOG-RA-NAL", "KANGU-RI-RIHRI", "SILL-I", "SILL-II"], "SOLDHA": ["CHAKALI", "LARA GHAT", "PALAH", "SIMLI-RA-HAR"], "THACH": ["THACH"]}, "SUI SURHAR": {"BARNU": ["MARCHRD"], "BHOJPUR": ["BESHANK"], "DIGTHALI": ["CHANGRU", "KANNOLI NALI", "ROUN", "SAJI HAWANI"], "GHANSER": ["BAG"], "SURHWAR": ["BAISHANIC", "CHANGRU"]}, "SWAHAN": {"KHURANI": ["BURAL", "KAMJAMAN"]}, "TARSOOH": {"GAWAL THAI": ["BARIALA", "CHHAROLA", "GUGE", "HARIZAN KHAD"], "NELLA": ["NELLA", "OLINDA"], "SAMTEHN": ["SAMTEHAN-II"]}, "TARWAR": {"BHARSARA": ["MAKDU", "SUDU"], "MAYOTH": ["BANIWALA", "KHALA"], "SINMA SADHA": ["LADER"]}}}