{"BAIHAR": {"AAMGAHAN": {"AMGAHAN": ["MAIN BASTI", "SCHOOLTOLA", "TALABTOLA"], "ATARCHUHA": ["MAIN BASTI"], "BAJGUNDI": ["MAIN BASTI"], "KHIRASDI": ["BARRATOLA", "MAIN BASTI", "MATUTOLA"]}, "AAMGAON": {"AMGAON": ["AWAS TOLA", "CHALISH QUATAR", "GHASSU TOLA", "MAIN BASTI", "MAKHAN TOLA", "NAHAR TOLA", "PONGAR"], "BHARI": ["MAIN BASTI", "PATEL TOLA", "SADAK TOLA", "TIKARA TOLA"]}, "AJANPUR": {"AJANPUR": ["BAD TOLA", "BAIGA TOLA", "DAHIYAN TOLA", "MAIN BASTI"], "JHOLAR": ["BAIGA TOLA", "MAIN BASTI", "NAKA TOLA"], "SUKHADI": ["MAIN BASTI", "UPPAR TOLA"]}, "ALNA": {"ALNA": ["CHANABATITOLA", "DAIHANTOLA", "GYANTOLA", "MAIN BASTI", "PIPARTOLA", "SAHUTOLA", "SCHOOL TOLA", "TALABTOLA", "TIKARATOLA"]}, "BAMHANI": {"BAMHNI": ["BANDINIYA", "GALBALI TOLA", "MAIN BASTI", "SADAK TOLA"], "BHARDA": ["AWAS TOLA", "MAIN BASTI"], "MOHGAON": ["AWAS TOLA", "DAHYAN TOLA", "MAIN BASTI", "PATEL TOLA"], "MUKKHI": ["BAD TOLA", "BERIR TOLA", "HUDDI TOLA", "MAIN BASTI", "PARSA TOLA"]}, "BHALAPURI": {"BALGAON": ["AWASTOLA", "MAIN BASTI"], "BHALAPURI": ["AWASTOLA", "DAHIYAN TOLA", "MAIN BASTI", "SADAK TOLA"], "NIWAS": ["BADATOLA", "BAHRINTOLA", "MAIN BASTI"]}, "BHANDERI": {"BHANDERI": ["BAIGATOLA", "HUDDITOLA", "MAIN BASTI", "MANTITOLA", "PATELTOLA", "THAKUR TOLA"]}, "BIRWA": {"BIRWA": ["AWASTOLA", "BAHITOLA", "MAIN BASTI", "MARARITOLA", "SAKRUTOLA", "THAKURTOLA"]}, "BITHLI": {"AMANALA": ["MAIN BASTI"], "BITHLI": ["BAIGA TOLA-2", "BAIGATOLA-1", "CHUDURKA TOLA", "JANIYA TOLA", "KATIYA TOLA", "MAIN BASTI", "PANDRA PANI", "POLICE CHOWKI"], "BODKHI": ["MAIN BASTI"], "DUGLAI": ["MAIN BASTI"], "HARRANALA": ["AWAS TOLA", "MAIN BASTI", "NAYA TOLA", "PANDA TOLA", "SAMAR TOLA"]}, "BITHLI(GARHI)": {"BENDA": ["BAIGATOLA", "MAIN BASTI"], "BITHLI": ["MAIN BASTI", "NAKATOLA"], "LINGA": ["MAIN BASTI"], "RANGWAHI BAH": ["MAIN BASTI", "NAKATOLA", "NICHETOLA", "PIPERTOLA"], "SUPARWAR": ["MAIN BASTI"]}, "BODA": {"BODA MAL.": ["CHULUNG TOLA", "HARIJAN TOLA", "MAHAVIR TOLA", "MAIN BASTI", "RASI TOLA"], "BODA RYT.": ["CHIMKA TOLA", "MAIN BASTI"]}, "DALDALA": {"DALDALA": ["BHALI TOLA", "DHANI TOLA", "HUDITOLA", "MAIN BASTI", "NAYA TOLA", "PIPAR TOLA", "UMAR TOLA"], "PACHAMA": ["BHARAT TOLA", "MAIN BASTI"]}, "DHIRI": {"DHIRI": ["DHANTOLA", "HARRATOLA", "MAHUATOLA", "MAIN BASTI", "NAKATOLA", "SCHOOL TOLA"], "GHURSI BOHRA": ["MAIN BASTI"], "MUREIDA": ["MAIN BASTI"]}, "GARHI": {"GARHI": ["AWASTOLA", "CHOURAHA", "HARRATOLA", "JAMTOLA", "MAIN BASTI", "PARSATOLA", "PATELTOLA", "SARAITOLA", "THAKURTOLA"]}, "GOHARA": {"GOHARA": ["AWASTOLA", "BAIGATOLA", "MAIN BASTI", "NAYAK TOLA", "TANTA TOLA"], "JALDIDAD": ["MAIN BASTI"], "KOPARO": ["MAIN BASTI"]}, "GOWARI": {"GOWARI": ["AWASTOLA", "MAIN BASTI", "RATANATOLA"], "SUMERIKHEDA": ["MAIN BASTI"]}, "HATTA": {"DUDWA": ["LABHANTOLA", "MAIN BASTI"], "HATTA": ["DAIHANTOLA", "MAIN BASTI", "PANDHRI"], "SANJARI": ["MAIN BASTI"]}, "JAITPURI": {"JARATOLA": ["MAIN BASTI"], "JARRA TOLA": ["MAIN BASTI"], "JEITPURI": ["DAYHANTOLA", "KOTWARTOLA", "MAIN BASTI"], "TOPLA": ["BAIGATOLA", "DHURITOLA", "HALMTOLA", "HATHITOLA", "KOTWAR TOLA", "MAIN BASTI", "SUATIKRITOLA"]}, "JAMI": {"GHUITOLA": ["MAIN BASTI"], "JAMI": ["BAIGATOLA", "MAIN BASTI"], "JANGLI KHEDA": ["MAIN BASTI", "PANDRI TIKARA"], "KATANGI": ["MAIN BASTI"], "ROL": ["MAIN BASTI"]}, "JATTA": {"JATTA RYT.": ["BAIGA TOLA", "BIJA TOLA", "MAIN BASTI"], "JATTA THEKE": ["BAIGA TOLA", "MAIN BSTI", "MARARI TOLA"]}, "KADLA": {"HEERA PUR": ["AWAS TOLA", "MAIN BASTI"], "KADLA": ["MAIN BASTI", "NAKA TOLA", "UPPAR TOLA"], "KHALAUNDI": ["BAIGA TOLA", "MAIN BASTI"]}, "KANDAI": {"GARHPAYALI": ["BAIGATOLA", "CHHUDURK", "JHAKO", "MAINBASTI"], "KANDAI": ["BAIGATOLA", "HARRA TOLA", "IMLITOLA", "KOTWARTOLA", "LOTANA", "MAIN BASTI"]}, "KARELI": {"KARELI": ["GOMCHI TOLA", "GOREKHPUR", "MAIN BASTI", "PARSA TOLA"], "UMARDEHI": ["LINE TOLA", "MAIN BASTI", "SALANG TOLA"]}, "KARWAHI": {"BARWAHI": ["MAIN BASTI"], "KARWAHI": ["BAIGATOLA", "MAIN BASTI", "MARARI TOLA"], "SAREKHA": ["MAIN BASTI", "PIPAR TOLA"]}, "KATANGI": {"KATANGI": ["DADDI TOLA", "KISANTOLA", "MAIN BASTI", "SIDBABATOLA"]}, "KATANGI BHURUK": {"BHURRUK": ["BAIGA TOLA", "CHIKHLI TOLA", "MAIN BASTI", "NAYA TOLA", "SARAI TOLA"], "KATANGI": ["MAIN BASTI", "NAKA TOLA", "PATEL TOLA"], "KINIYA": ["AAKHARTOLA", "BAIGATOLA", "JHRIA TOLA", "MAIN BASTI", "URAWTOLA"]}, "KEOLARI": {"ARAMTOLA": ["BAIGA TOLA", "MAIN BASTI"], "ATARIYA": ["BAIGA TOLA", "MAIN BASTI"], "KEOLARI": ["BAD TOLA", "BHELAWA TOLA", "DATLA TOLA", "MAIN BASTI", "SAKRU TOLA"]}, "KHAJRA": {"KHAJARA": ["CHHINDI TOLA", "IMLI TOLA", "KHAJRI", "MAIN BASTI", "SARI TOLA"]}, "KHOLWA": {"GURAKHARI": ["BAIGA TOLA", "BHIMATOLA", "BIJATOLA", "GOMCHITOLA", "MAIN BASTI"], "KHOLWA": ["BANGA PAHAR", "GONDI TOLA", "LOHAR TOLA", "MAIN BASTI", "PANDA TOLA"]}, "KINARDA": {"KINARDA": ["HETITOLA", "MAIN BASTI", "MASANATOLA", "MUKADAM TOLA", "SARITOLA", "SIKARI TOLA", "TOTARATOLA"], "POLA": ["BAIGATOLA-1", "BAIGATOLA-2", "JAMTOLA", "MAHAJAN TOLA", "MAIN BASTI", "PATPARI", "SARI TOLA"]}, "KOHAKA": {"BHIMODI": ["MAIN BASTI"], "KOHKA": ["AWAS TOLA", "BHOI TOLA", "GARHI TIRAHA", "MAIN  BASTI", "NAYAK TOLA", "SAI TOLA"]}, "KOYALIKHAPA": {"KOYALIKHAPA": ["AAMATOLA", "JHALITOLA", "MAIN BASTI", "NAYATOLA", "NAYATOLA-2", "SARAITOLA"]}, "KUGAON": {"ARANDI": ["BAIGA TOLA", "IMLI TOLA", "MAIN BASTI", "TINSA TOLA"], "GHINYA JHOR": ["MAIN BASTI"], "KUGAON": ["BAHITOLA", "BARRA TOLA", "GHURRI TOLA", "MAIN BASTI", "NAYA TOLA"]}, "KUKARRA": {"KUKARRA": ["AWASTOLA", "BADATOLA", "BAKTATOLA", "BRAHMANTOLA", "CHUCHRUNPUR", "CHUTTITOLA", "DEOLALTOLA", "LATTITOLA", "MAINBASTI", "SANTANTOLA", "SCHOOLTOLA"]}, "LANGHA KANHA": {"GANJAISARRA": ["BHUTDABRA", "KANHARTOLA", "MAIN BASTI"], "LAHANGAKANHA": ["DUMRAHI", "LALPUR", "MAIN BASTI", "PATPRI", "SONTALA"]}, "LATRI": {"DOGRIYA": ["MAIN BASTI"], "KOREYJHRI": ["KATANG TOLA", "MAINBASTI"], "LATRI": ["BAIGA TOLA", "HARRATOLA", "MAIN BASTI"], "MANDWA": ["MAINBASTI"]}, "LUD": {"BAMHNI": ["BHARAT TOLA", "BUNDER TOLA", "DAHIYAN TOLA", "MAIN BASTI"], "HIRRI": ["MAIN BASTI"], "KONGEWANI": ["BAIG TOLA", "MAIN BASTI", "MANSINGH TOLA"], "LUD": ["BAIGA TOLA", "MAIN BASTI", "MANDAI TEKRA", "MASIYA TOLA", "PUJARI TOLA", "SARRATHI TOLA"], "SARAD": ["MAIN BASTI", "PATEL TOLA"]}, "MANA": {"BAIJALPUR": ["MAIN BASTI"], "LAPTI": ["AWAS TOLA", "CHHIPI TOLA", "MAIN BASTI", "TINGA TOLA"], "MANA": ["BHURSA TOLA", "HARRA TOLA", "MAIN BASTI", "NARGHU TOLA", "TINGA TOLA"]}, "MEDHAKI": {"DEWARBELI": ["MAIN BASTI"], "MENDKI": ["AWAS TOLA", "CHARRTOLA", "MAIN BASTI", "PATEL TOLA"]}, "MOHBATTA": {"BIJORA": ["BAIGATOLA-1", "BAIGATOLA-2", "MAIN BASTI", "SARITOLA"], "MOHBATTA": ["BAIGA BASTI", "BANDHATOLA", "CHALISH QUARTAR", "MAIN BASTI", "SADAK TOLA"]}, "MOHRAI": {"ARMI": ["ARMI CHHOTI", "MAIN BASTI"], "MOHRAI": ["IMARTOLA", "JHIJRATOLA", "MAIN BASTI", "SCHOOLTOLA", "TLABTOLA"], "SEMARKHEDI": ["MAIN BASTI"]}, "MOWALA": {"MOWALA": ["AAMATOLA", "BANJAR BAIGA", "HARIJAN TOLA", "KOTWAR TOLA", "MAHU TOLA", "MAIN BASTI", "NARSARI BAIGA"], "RAJMA": ["BAIGA TOLA", "BHAWANI TOLA", "LABHAN TOLA", "MAIN BATI", "MARARI TOLA", "NAYA TOLA", "SUKALU TOLA"]}, "NAVHI": {"JAGLA": ["BAIGATOLA", "KEHAR SINGH TOLA", "MAINBASTI", "PIPROHI", "TABLUTOLA"], "JALDA": ["BAIGATOLA", "BHAREWA TOLA", "MAINBASTI", "PATEL TOLA", "SANTOSHTOLA"], "LIMOTI": ["CHUKTOLA", "MAIN BASTI", "PIPARTOLA"], "NAVHI": ["MAIN BASTI", "PURATOLA"]}, "PANDUTALA": {"CHARTOLA": ["MAIN BASTI"], "PANDUTALA": ["BAJARTOLA", "KANCHANTOLA", "KIRGITOLA", "MAHUATOLA", "MAIN BASTI"]}, "PARSAMAU": {"MORENDA": ["MAIN BASTI"], "PARSAMAU": ["AWASTOLA", "CHAITUTOLA", "MAIN BASTI", "PARSATOLA", "SARAITOLA", "THAKURTOLA"]}, "PARSATOLA": {"GOGATOLA": ["BAIGA TOLA", "JUGALTOLA", "MAIN BASTI", "RAMATOLA", "TITURBARRA"], "HIRAPUR": ["AWASTOLA", "MAIN BASTI", "SCHOOL TOLA"], "PARSATOLA": ["AWASTOLA", "MAIN BASTI", "SADAK TOLA"]}, "PATHRI": {"DEODONGRI": ["BAIGA TOLA", "BITHLI BAHERA", "MAINBASTI"], "MADI": ["AAMATOLA", "BHAGWANDIH", "MAIN BASTI"], "PATHARI": ["BAIGATOLA", "BARTOLA", "GUDRUWARA", "KHUMRITOLA", "MAIN BASTI"]}, "PATWA": {"CHHATARPUR B": ["MAIN BASTI", "SCHOOL TOLA"], "PATWAS BAHEI": ["BHARRI TOLA", "KHOWA TOLA", "MAIN BASTI", "SANWAHI", "SCHOOL TOLA", "UMMAR TOLA"]}, "PIPARIYA": {"BANNA": ["MAIN BASTI"], "BHAISWAHI": ["MAIN BASTI"], "MANIKPUR": ["MAIN BASTI"], "PIPARIYA": ["MAIN BASTI", "NAYATOLA"]}, "PONDI": {"BHARRI": ["MAIN BASTI"], "PAUNDI": ["BAIGA TOLA", "KANCHA TOLA", "LALDHADI", "MAIN BASTI", "SALETOLA"]}, "POUNDI (G)": {"AGANTARA": ["KARIYA TOLA", "KHALE TOLA-1", "KHALE TOLA-2", "MAIN BASTI", "SIMAR TOLA"], "PONDI": ["AWAS TOLA", "MAIN BASTI", "PIPAR TOLA", "THAKUR TOLA", "TIKRA TOLA"]}, "RAMHEPUR": {"RAMHEPUR": ["BAHERA TOLA", "BALHERI", "BARRA TOLA", "MAIN BASTI"]}, "SAMARIYA": {"BILAIKHAR": ["MAIN BASTI", "SCHOOL TOLA"], "DONGARIYA": ["BAIGATOLA", "LADIYATOLA", "MAINJ BASTI"], "SAMRIYA": ["BAHERATOLA", "BAIGATOLA\\", "IMLITOLA", "MAIN BASTI", "SIHRATOLA"]}, "SERPAR": {"NEWARGAON": ["AWAS TOLA", "BAIGA TOLA-1", "BAIGA TOLA-2", "MAIN BASTI", "SCHOOL TOLA"], "SERPAR": ["MAIN BASTI", "PATEL TOLA", "SAMITOLA"]}, "SIJORA": {"KHURSIPAR": ["AWAS TOLA", "BAD TOLA", "BAIGA TOLA", "KARAN TOLA", "MAIN BASTI", "OJHA TOLA"], "KOMO": ["GANGARAM TOLA", "MAIN BASTI", "SAMPAT TOLA"], "SIJORA": ["AWAS TOLA", "BAIGA TOLA", "BARKAT TOLA", "KOLIYA TOLA", "MAIN BASTI", "NUNKA TOLA", "RAM SINGH TOLA"]}, "SONPURI": {"NARANGI": ["BAIGA TOLA", "KANCHAN TOLA", "MAIN BASTI"], "SONPURI": ["MAIN BASRI"]}}, "BALAGHAT": {"AMEDA": {"AMEDA": ["AMEDA", "RICE MIL TOLA"]}, "AMGAON": {"AMGAON": ["AMGAON", "BELDAR TOLA", "GHANDGA TOLA", "KAWADIYA TOLA", "VISHRAMPUR"], "KHARA": ["KHARA"], "KOKAMA": ["KOKNA"], "POLAWATUR": ["PALAWATOR"], "SONPURI": ["SONPURI"]}, "ARNAMETA": {"ARNAMETA": ["ARNAMETA", "SAINI  TOLA", "STATION TOLA"], "DHIMRUTOLA": ["BAIGA TOLA", "DHIMRUTOLA", "NEW AWAS"], "MAHAKE PATA": ["MAHKAPATA", "PUJARI TOLA"], "TIKHAKHARI": ["AWAS TOLA", "TIKAKHARI"]}, "ATARI": {"AMOLI": ["AMOLI", "LOHARI TOLA", "MATKA TOLA"], "ATRI": ["ATARI", "INDRA AWAS", "MARARI TOLA"]}, "AWALAJHARI": {"AWLAJHARI": ["AWALAJHARI", "KATING TOLA", "KRANTI TOLA"]}, "BAGDARRA": {"BAGDARA": ["BAGDARRA", "LABHAN TOLA", "MARAR TOLA", "NARBAD TOLA"]}, "BAGOLI": {"BAGHOLI": ["AWAS TOLA", "BAGHOLI"]}, "BATUWA": {"BARKHEDA": ["BARKHEDA", "TURANGA TOLA"], "BASEGAON": ["BASEGAON", "KURLU TOLA"], "BATUWA": ["ADIWASI TOLA", "BATUWA", "KAMAL TOLA"]}, "BHALEWADA": {"BHALEWADA": ["BHALEWADA"], "CHACHERI": ["CHACHERI", "GUNDI TOLA"], "DONGARBODI": ["DONGARBODI", "KUSUM TOLA", "SEETA DONGRI"], "JHIRIYATOLA": ["JHIRIYA TOLA"], "MUNDITOLA": ["MUNDITOLA"]}, "BHAMODI": {"BHAMODI": ["BHAMODI"]}, "BHARWELI": {"BHARWELI": ["BHARWELI", "GONDI TOLA", "MARARI TOLA", "NAYA TOLA"]}, "BHATERA": {"BHATERA": ["BHATERA"]}, "BHONDWA": {"BHONDWA": ["BHONDWA", "CHAMAN TOLA", "KURSI TOLA", "SALANG TOLA"], "DAUNI": ["DOUNI"], "MEIRA": ["MAIRA (C.V.)"]}, "BODA": {"BODA": ["BODA"]}, "BUDHIYAGAON": {"BUDHIYAGAON": ["ADIWASI TOLA", "ALIPUR", "BUDHIYAGAON"], "DHUTI": ["DHUTI", "GONDI TOLA"], "KHURSUDA": ["GONDI TOLA", "KHURSODA"]}, "CHAMARWAHI": {"BIJAPURI": ["BIJAPURI", "SADAK TOLA"], "CHAMARWAHI": ["CHAMARWAHI", "KATANGTOLA", "KUMHARTOLA", "LALTOLA"], "HIRMUTOLA": ["HIRWATOLA"]}, "CHANGOTOLA": {"CHANGOTOLA": ["AMRAI TOLA", "CHANGOTOLA", "KRISHI UPAJ MANDI", "MACHINE TOLA", "MAJAR TOLA", "POLICE LINE"], "MAU": ["BAJAR TOLA", "KHAM TOLA", "MAU"]}, "CHAREGAON": {"CHAREGAON": ["CHAREGAON", "GONDI TOLA"], "MANPUR": ["MANPUR", "MANPUR TOLA"]}, "CHICHGAON": {"CHICHGAON": ["AWAS TOLA", "CHICHGAON"]}, "DEVARI": {"DEORI": ["DEVARI"]}, "DHANSUA": {"DHANSUWA": ["BHASDEO TOLA", "DHANSUA", "GADIYA TOLA", "NAGARCHI TOLA", "NATTHU TOLA ]"], "ODA": ["OADA", "OADA MAL"]}, "DHAPEWADA": {"DHAPEWADA": ["DHAPEWADA"], "PANCHERA": ["PANCHERA"]}, "GADADA": {"BUDHENA KHUR": ["BUDHENA KHURD"], "GADDA": ["AWAS TOLA", "GADADA", "KODPA TOLA", "PAWAR TOLA"]}, "GHANGARIYA": {"GHANGHARIA": ["DHIMAR TOLA", "GHANGARIYA"]}, "GHUNADI": {"GHUNADI": ["BHUTAI TOLA", "GHUNADI", "NAYA TOLA"], "PINDKEPAR": ["MACHINE TOLA", "PINDKEPAR"]}, "GONGLAI": {"GONGLAI": ["GONGLAI"]}, "GUDRU": {"GUDROO": ["GUDRU", "GUDRU TOLA", "STATION TOLA"], "THEMA": ["HIRMAN TOLA", "THEMA"]}, "HARDOLI": {"HARDOLI": ["HARDOLI", "HARDOLI TOLA"]}, "HATTA": {"HATTA": ["DUBI TOLA", "GOPAL TOLA", "HATTA", "HATTA TOLA", "SADAR TOLA"]}, "HIRAPUR": {"HIRAPUR": ["HIRAPUR BASTI", "IMALI TEKRA", "MARARI TOLA", "PARSA TOLA", "RAMJI TOLA"]}, "JAGPUR": {"JAGPUR": ["AWAS TOLA", "JAGPUR", "SCHOOL TOLA"]}, "JARERA": {"AGARWADA": ["AGARWADA", "GONDI TOLA"], "JARERA": ["JARERA", "JHODHI TOLA"], "KORTHITOLA": ["KURATHITOLA"], "TALABODI": ["TALABODI"], "UMARDAUNI": ["UMARDONI"]}, "KATANGI": {"BORI": ["AWAS TOLA", "BORI", "GONDI TOLA"], "KATANGI": ["KATANGI", "NEW AWAS", "NEW AWAS TOLA", "OLD AWAS TOLA"]}, "KESHLEWADA": {"KESHLEWADA": ["KESHLEWADA"]}, "KHAIRGAON": {"KHAIRGAON": ["KHAIRGAON", "PATEL TOLA"]}, "KHAIRI": {"KHAIRI": ["KHAIRI"]}, "KHODSEONI": {"KHODSEONI": ["AWAS TOLA", "KHODSEONI", "PARSATOLA"]}, "KHURSODI": {"KHURSODI": ["AWAS TOLA", "KHURSODI"]}, "KOCHEWADA": {"KOCHEWADA": ["KOCHEWADA", "KUMHAR TOLA"], "NARSINGA": ["NARSINGHA"]}, "KOHKA DIBAR": {"KOHKA DIBAR": ["AWAS TOLA", "KOHKADIBAR"]}, "KOSMI": {"KOSMI": ["AMRAHI TOLA", "JHIRIYA TOLA", "KOSMI"]}, "KUKDA": {"KUKDA": ["KUKDA", "KUKDA TOLA", "PAHADI TOLA"], "THAKURTOLA": ["NEW AWAS", "THAKUR TOLA"]}, "KUMHARI": {"KUMHARI": ["INDIRA AWAS TOLA", "KUMHARI BADI", "KUMHARI CHHOTI"]}, "LAMTA": {"KHAIRA": ["BAGICHATOLA", "KHAIRA"], "LAMTA": ["BAGICHA TOLA", "LAMTA"]}, "LINGA": {"LINGA": ["INDIRA AWAS TOLA", "LINGA"], "PARASWADA": ["AWAS TOLA", "PARASWADA"]}, "LOHARA": {"LOHARA": ["AWAS TOLA", "LOHARA"]}, "MAGARDRRA": {"MAGARDARRA": ["KEWA TOLA", "MAGARDRRA", "TUMADI TOLA"]}, "MANEGAON": {"MANEGAON": ["AMA TOLA", "AWAS TOLA", "MACHINE TOLA", "MANEGAON"]}, "MOHGAON MAL": {"BAKWADA": ["BAKWADA", "BIJATOLA"], "BARKHO": ["BARKHOH", "PIPARTOLA"], "MALDHAR": ["MALDHAR"], "MOHGAON MAL.": ["MOHGAON MAL", "RAMATOLA"]}, "MORIYA": {"KUMHARI": ["KUMHARI"], "MOURIYA": ["MORIYA"], "PANDEWADA MA": ["PANDEWADA MAL"]}, "MOTEGAON": {"KANARI": ["KANARI"], "MOTEGAON": ["HARPAL TOLA", "MOTEGAON"], "UMARIA MAL.": ["UMARIYA MAL"]}, "NAGARWADA": {"CHANEWADA": ["CHANEWADA", "PAWAR TOLA", "SCHOOL TOLA"], "NAGARWADA": ["NAGARWADA", "NEW AWAS TOLA", "PANCHAYAT TOLA"]}, "NAHARWANI": {"CHACHAN META": ["CHICHNMETA"], "NAHARWANI": ["NAHARWANI"], "TILPEWADA": ["MAHUWA TOLA", "TILPEWADA"]}, "NAITRA": {"NAITRA": ["NAITRA"]}, "NAWEGAON": {"NAWEGAON": ["NAWEGAON"]}, "NEWARGAON": {"LAWERI": ["LAWERI"], "MOHGAON KHUR": ["MOHGAON KHURDA"], "NEWARGAON": ["GONDI TOLA", "NEWARGAON"]}, "ORAMA": {"DONGARBODI": ["DONGARBODI"], "ORMA": ["ORMA", "THAKUR TOLA"], "TEKADI": ["TEKADI"]}, "PACHPEDI": {"KHAIRGAON": ["AMATOLA", "KHERGAON"], "KUMJHAR": ["IMALITOLA", "KUMJHAR", "PARDHITOLA"], "PACHPEDHI": ["BARI TOLA", "PACHPEDI"]}, "PARASPANI": {"PARASPANI": ["AWAS TOLA", "DHOLI TOLA", "GONDI TOLA", "PARASPANI"]}, "PARASWADA": {"PARASWADA": ["PARASWADA"], "RATNARA": ["RATNARA"]}, "PATHARWADA": {"KOLHWA": ["KOLWA"], "PATHARWADA": ["PATHARWADA"]}, "PAYLI": {"PAYALI": ["AWAS TOLA", "GONDI TOLA", "PARSATOLA", "PAYLI"], "RAWADBANDI": ["RAWADBANDI"]}, "PENDRAI": {"KANHADGAON": ["AWASTOLA", "KANHADGAON"], "PENDHRAI": ["AWAS TOLA", "PENDRAI", "PENDRAI TOLA"]}, "PRATAPPUR": {"PRATAPPUR": ["MAGRA TOLA", "PRATAPPUR"]}, "RATTA": {"BHANPUR": ["BHANPUR", "BHANPUR TOLA"]}, "ROSHNA": {"NEWARGAON": ["NEVARGAON", "SITKU TOLA"], "ROSHNA": ["AWAS TOLA", "ROSHNA"]}, "SAKARI": {"DEOSARRA": ["DEVSARRA", "NEW AWAS"], "SAKRI": ["SAKRI"], "TINGADHI": ["SIYARTOLA", "TINGADHI"]}, "SAMNAPUR": {"DUGLAI": ["DUGLAI"], "SAMNAPUR": ["AWAS TOLA", "SAMNAPUR"]}, "SERVI": {"DURENDA MAL.": ["DURENDA MAL"], "DURENDA RYT.": ["DURENDA RAIYAT"], "KHAMI": ["KHAMI"], "SERVI": ["SERVI", "SHANKAR TOLA"], "SURIYA": ["AWAS TOLA", "SURIYA"]}, "SONKHAR": {"PATADEH": ["PANDATOLA", "PATADAH"], "SONKHAR RYT.": ["GOWARI TOLA", "SONKHAR"]}, "SURWAHI": {"SURWAHI": ["KHARRA TOLA", "SURWAHI"]}, "TAKABARRA": {"TAKABARRA": ["KHARRAKONA", "TAKABRRA"]}, "TAVEJHARI": {"MANJHARA": ["BAIGA TOLA", "GONDI TOLA", "MANJHARA"], "TAWEJHARI": ["BANGLA TOLA", "JONA TOLA", "TAVEJHARI"]}, "TEKADI": {"GANGULPARA": ["GANGULPARA"], "KERA": ["GONDI TOLA", "KERA"], "PIPARTOLA": ["PIPARTOLA"], "TEKADI": ["BERIYA TOLA", "TEKADI"]}, "TITWA": {"HIRBATOLA": ["HIRMU TOLA"], "KATEGAON": ["KACHURNA TOLA", "KATEGAON"], "TITWA": ["PIPAR TOLA", "SALAI TOLA", "TITWA"]}, "TIWADIKALA": {"TIWADI KALAN": ["TIWADIKALA"], "TIWADI KHURD": ["SHANKAR TOLA", "TIWADI KHURDA"]}}, "BIRSA": {"ACHANKPUR": {"ACHANAKPUR": ["JUTHAIL TOLA", "LIMA TOLA", "MAIN BASTI"]}, "ADORI": {"ADORI": ["BAIGA TOLA", "BAKHRU TOLA", "KOTWAR TOLA (DALLA TOLA)", "MAIN BASTI", "PATEL TOLA", "USRI TOLA"], "BONDARI": ["BAIGA TOLA", "MAIN BASTI", "SAJA PANI", "USARI KALA"], "KUNDEKASA": ["MAIN BASTI", "PARIPANI TOLA", "PATEL TOLA", "SCHOOL TOLA", "TOPLA"]}, "AJGARA": {"AJGARA": ["AWAS TOLA", "CHHINDITOLA", "GONDI TOLA", "MAIN BASTI", "MARARI TOLA", "PANKA TOLA", "SARAI TOLA"]}, "BAHKAL": {"BAHKAL": ["AWAS TOLA", "BACHHERA PATH", "BADA BAHKAL", "MAIN BASTI", "MINAHI TOLA"]}, "BAKIGUDA": {"BAKIGUDA": ["AWAS TOLA", "GONDI TOLA", "HARRA TOLA", "JHILBOLI TOLA", "MAHAJAN TOLA", "MAIN BASTI", "NAHAR TOLA", "PICHAKYA TOLA"]}, "BALGAON": {"BALGAON": ["AWAS TOLA", "BAIGA TOLA", "MAIN BASTI"], "BASINKHAR": ["BAIGA TOLA", "JAMUNIYA TOLA", "MAIN BASTI", "MANGAL TOLA"], "BHADGAON": ["AWAS TOLA", "BAIGA TOLA - II (AKHAR TOLA)", "BAIGA TOLA (I)", "MAIN BASTI"]}, "BHANDARPUR": {"BHANDARPUR": ["HARRA TOLA", "KATIYA TOLA", "MAIN BASTI", "MARARI TOLA", "PUJARI TOLA"], "DEORI DAKSHI": ["BAIGA TOLA", "CHUHARI TOLA", "MAIN BASTI", "MARARI TOLA", "UKARIYA TOLA"], "DEVARITHEKA": ["BAIGA TOLA", "MAIN BASTI"]}, "BHERABHATA": {"BAHERABHATA": ["BAJAR CHOUK", "MAIN BASTI", "MANIYA PARA", "SAREKHA TOLA"]}, "BHIMLAT": {"BAHERAKHAR": ["AMA TOLA", "MAIN BASTI", "TIKARA TOLA"], "BHIMLAT": ["MAIN BASTI", "SARAI TOLA"]}, "BHUTHNA": {"BHUTNA": ["BAD TOLA", "BAIGA TOLA", "BIHARI TOLA", "BIHI TOLA", "DAYARAM TOLA", "KUDAN TOLA", "MAIN BASTI", "NAG BAHERA", "NAKA TOLA", "PANDA TOLA"], "CHAINATOLA": ["MAIN BASTI", "SARAI TOLA", "URAW TOLA"], "GORAKHPUR": ["AWAS TOLA", "MAIN BASTI"]}, "BIJATOLA": {"BAKHARIKONA": ["BHARRI TOLA", "DUMAR TOLA", "MAIN BASTI", "SARAI TOLA", "TENDU TOLA"], "BEEJATOLA": ["DUMAR TOLA", "MAIN BASTI"], "TINGATOLA": ["CHHOTA TOLA", "MAIN BASTI", "TIKRA TOLA"]}, "BITHLI": {"BITHLI": ["BITHLI MAIN BASTI", "MAIN BASTI", "MASHIN TOLA"], "MUNDGHUSRI": ["AWAS TOLA", "KATIYA TOLA", "MAIN BSTI"]}, "BORKHEDA": {"BITHLI": ["AWASTOLA", "BAIGA TOLA", "MAIN BASTI SUJI", "NAYA TOLA", "TIKARA TOLA"], "BORKHEDA": ["BAIGA TOLA", "NAYA TOLA (II)", "NAYATOLA"], "CHHINDITOLA": ["MAIN BASTI"], "KOSA TOLA": ["AWAS TOLA", "MAIN BASTI", "MAIN BSTI"], "KOSHATOLA": ["BAIGA TOLA", "MAIN BASTI"], "SUJI": ["MAIN BASTI", "TIKARA TOLA"]}, "CHHAPLATHEKA": {"CHHAPALA THE": ["HARRATOLA", "MAIN BASTI", "MAYAN TOLA (BEL TOLA)", "PANKA TOLA"], "CHHAPLA RYT.": ["KHERO TOLA", "MAIN BASTI"]}, "CHICHGAON": {"CHICHGAON": ["DEVA TOLA", "MAIN BASTI"]}, "CHOURIYA": {"CHAURIYA": ["MAIN BASTI"], "CHILORA": ["MAIN BASTI", "MOGHA TOLA", "PATEL TOLA", "PAWSERA TOLA"], "JAITPURI": ["CHITAL KHOLI", "IMALI TOLA", "KOSAM BAHERA", "MAIN BASTI"], "LAPHRA": ["MAHAJAN TOLA", "MAIN BASTI", "NAYA TOLA"]}, "DABARI": {"DABRI": ["DAHIYAN TOLA", "KOTWAR TOLA", "MAIN BASTI", "NAKA TOLA", "PATEL TOLA", "RADHA TOLA", "SARPANCH TOLA", "THAKUR TOLA"], "JHAKORDA": ["GAYAN TOLA", "GORJHOLA", "MAIN BASTI"], "LATRI": ["MAIN BASTI", "MARIHAN TOLA"], "MAHURDALI": ["MAIN BASTI", "UPAR TOLA"]}, "DADKASA": {"DADKASA": ["BAKAR KATTA", "BILALKASA", "CHUNA PATHERA", "KOSAMBAL", "MAIN BASTI", "SARAD TOLA", "SARAI TOLA"], "MUNDA": ["GOUR JHOLA", "KOTIYA TOLA", "MAIN BASTI"], "PITKONA": ["KERAJJHARI", "LALDHADI", "MAIN BASTI"], "TUMA": ["MAIN BASTI", "MUNGA TOLA", "SODHANDONGARI"]}, "DAMOH": {"DAMOH": ["AWAS TOLA", "DAMOH TOLA", "HARIJAN TOLA", "KUMARI TOLA", "MAIN BASTI", "PATEL TOLA", "TELI TOLA"]}, "DEOGAON": {"BANDANIYA": ["KHUDRAHI TOLA", "MAIN BASTI"], "DEOGAON": ["AWAS TOLA", "BADTOLA", "BAIGA TOLA", "CHUCHRUNGPUR", "HADA TOLA", "KHURKHURITOLA", "MAIN BASTI", "UMED TOLA"], "HATHWAN": ["BANDHAN KHERO", "MAIN BASTI", "NAYA TOLA (I)", "NAYA TOLA (II)"], "MALUMJHOLA": ["AWAS TOLA", "MAIN BASTI"], "SARAI PATERI": ["BELTOLA", "MAIN BASTI"], "SHERPAR": ["MAIN BASTI", "SCHOOL TOLA", "TUSAR"]}, "DHUNDHUNWARDHA": {"AKO": ["BAIGA TOLA (I)", "BAIGA TOLA (II)", "BAIGA TOLA (III)", "MAIN BASTI", "PATEL TOLA"], "BHANDERI": ["CHHINDI TOLA", "DODARA TOLA", "LANI TOLA", "MAIN BASTI"], "DHUNDHUNWARDHA": ["DALI TOLA", "KACHAR TOLA", "MAIN BASTI", "UPAR TOLA"], "SONPURI": ["AMA TOLA", "MAIN BASTI", "PATEL TOLA"]}, "DONGARIYA": {"BODA": ["MAIN BASTI", "SONJHIRIYA TOLA", "YEMAN TOLA"], "DONGARIYA": ["KHUNTA TOLA", "MAIN BASTI", "SARAI TOLA"], "THURRIMETA": ["DUMARTOLA", "HAJARIYA TOLA", "MAIN BASTI"]}, "DULHAPUR": {"DULHAPUR": ["ANTRAM TOLA", "KALAM TOLA", "MAIN BASTI", "PATEL TOLA", "TAKI TOLA"], "MURUM": ["BAIGA TOLA", "BATRANGA TOLA", "MAIN BASTI"], "RASIMETA": ["CHAMYAN TOLA", "MAIN BASTI", "NAGDEO TOLA"], "SUNDARWAHI": ["ADKU TOLA", "IMLI TOLA", "MAIN BASTI", "PATEL TOLA", "TIKARIYA TOLA"]}, "GHUMMUR": {"CHIKHALI": ["IMALI TOLA", "KHAIR TOLA", "MAIN BASTI"], "GHUMMUR": ["BAIGA TOLA (I)", "BAIGA TOLA (II)", "BHONGADWAR", "KOTHIYA TOLA", "MAIN BASTI", "SADAK TOLA"], "KODBIRKONA": ["MAIN BASTI"], "MURKUTA": ["BAKHUJI", "DUMRAHI", "MAIN BASTI", "PARSAI"]}, "GIDORI": {"GIDORI": ["JUNGAL TOLA", "KATAR TOLA", "MAIN BASTI", "PATEL TOLA", "PIPARDAR", "SHIKARI TOLA"], "MALIYA": ["AGRIYA TOLA", "BAIGA TOLA", "BENDRAPANI", "BHITRINI PANI", "MAIN BASTI", "NAYA TOLA"]}, "GOWARI": {"DEORIMETA  R": ["HARIJAN TOLA", "MAIN BASTI"], "GOWARI": ["GITTI TOLA", "MAIN BASTI"], "SUKTAR": ["MAIN BASTI", "MAIN BSTI"], "SUKTARA": ["AWAS TOLA", "GENDAN TOLA", "HARRA TOLA", "JUNGAL TOLA", "MAIN BASTI"]}, "GUDMA": {"BHIMA": ["CHICHARNPUR", "DOLIYA TOLA", "MAIN BASTI"], "GUDMA": ["DUMAR TOLA", "MAIN BASTI"], "LAGMA": ["BAIGA TOLA", "MAIN BASTI", "MANJI TOLA", "NAYA TOLA", "SAKARAI TOLA"], "SAHEGAON": ["BAIGA TOLA", "MAIN BASTI", "THAKUR TOLA"], "SANTAPUR": ["BAIGA TOLA", "MAIN BASTI"]}, "HARRABHAT": {"CHARCHENDI": ["AWAS TOLA", "DHOLIYA TOLA", "MAIN BASTI"], "HARRABHAT": ["MAIN BASTI", "NADI TOLA", "PATEL TOLA"], "KINDGITOLA": ["GONDI TOLA", "MAIN BASTI"]}, "JAGLA": {"JAGLA": ["KANTA BAHRA", "MAIN BASTI", "MINAHI TOLA", "PATEL TOLA", "SHIKARI TOLA"], "TAREGAON": ["MAIN BASTI", "SCHOOL TOLA"]}, "JAIRASHI": {"AKALPUR": ["MAHUWA TOLA", "MAIN BASTI"], "JAIRASI": ["BAD TOLA", "MAIN BASTI", "UMARDIHI"], "PANDHARAPANI": ["BAIGA TOLA (I)", "BAIGA TOLA (II)", "BAIGA TOLA (III)", "BAIGA TOLA (IV)", "BAIGA TOLA (V)", "BAIGA TOLA(VI)", "MAIN BASTI"]}, "JAMUNIYA": {"DORLI": ["BAIGA TOLA", "BHANGI TOLA", "MAIN BASTI", "TENDU TOLA"], "JAMUNIYA": ["BAIGA TOLA", "KATANG TOLA", "MAIN BASTI", "SCHOOL TOLA", "SIKARI TOLA"]}, "JANPUR": {"BISTAWAHI": ["BAIGA TOLA", "GONDI TOLA", "MAIN BASTI"], "JANPUR": ["BAIGA TOLA", "BICH TOLA", "HUDDI TOLA", "JATTA TOLA", "MAIN BASTI", "PANDIYA TOLA", "SCHOOL TOLA"], "SARASDOL": ["MAIN BASTI", "NADI TOLA", "TIMAKI TOLA"]}, "JHAMUL": {"JHAMUL": ["ANGAD TOLA", "BANIYA TOLA", "DUMAR TOLA", "KEVRA TOLA", "MAIN BASTI", "PIPAR TOLA", "SHILATI TOLA"]}, "KACHNARI": {"KACHNARI": ["BANDHA TOLA", "HARRA TOLA", "MAIN BASTI", "MEMAN TOLA"]}, "KANIYA": {"BHAGATWAHI": ["BAD TOLA", "BANJAR TOLA", "MAIN BASTI"], "BORI": ["MADAN TOLA", "MAIN BASTI", "PAKHALA TOLA", "TILAI TOLA"], "KANIYA": ["MAIN BASTI", "TELI PARA"], "LORMI": ["BAIGA TOLA", "MAIN BASTI"]}, "KARONDA BAHE": {"KARONDA BAHE": ["DONGHI TOLA", "KHUDRAHI TOLA", "MAIN BASTI"]}, "KATANGI": {"JAISINGTOLA": ["MAIN BASTI", "MANSHU TOLA", "THAKUR TOLA"], "KATANGI": ["BANDHA TOLA", "DUMAR TOLA", "GOYA TOLA", "MAIN BASTI"], "PATPARA": ["MAIN BASTI", "NAYA TOLA"]}, "KENDA TOLA": {"KAINDATOLA": ["ALIN TOLA", "KHUDRAHI TOLA", "MAIN BASTI", "NAHAR TOLA"]}, "KHURSIPAR": {"DHOBGHAT": ["MAIN BASTI", "MARARI TOLA", "PATEL TOLA"], "KHURSIPAR": ["JAMAR TOLA", "KABRA TOLA", "MAIN BASTI"]}, "LALPUR": {"DHAMANGAON": ["DONGA TOLA", "MAIN BASTI"], "LALPUR": ["BAIGA TOLA (I)", "BAIGA TOLA (II)", "BAIGA TOLA (III)", "BHITARI PANI", "MAIN BASTI", "RUCHRUCHI KAWAHA", "TENDU TOLA"], "MASALWADA": ["MAIN BASTI"], "MATHARI": ["HARRA TOLA", "MAIN BASTI", "RANGI TOLA", "SUKHA TALAB"], "TORGA": ["GAOTHARIYA TOLA", "MAIN BASTI", "NAYA TOLA", "SCHOOL TOLA", "THUNNU TOLA"]}, "MACHHURDA": {"KOMO": ["BABA TOLA", "BENDAPANI", "MAIN BASTI"], "KORKA": ["CHUNA PATHRA", "DANDAIKASA", "MAIN BASTI", "URAIKASA"], "MACHHURDA": ["BAIGA TOLA", "GATIYA", "MAIN BASTI", "MATALA", "POLICE CHOUKI", "SADAK TOLA"], "RANJANA": ["BAD TOLA", "BAHARI TOLA", "MAHUWA PANI", "MAIN BASTI"]}, "MANDAI": {"MANDAI": ["BANDHA TOLA", "CHANDANI CHOWK", "KABARA TOLA", "MAIN BASTI", "PANDA TOLA"]}, "MANEGAON": {"MANEGAON": ["INDIRA AWAS", "MAIN BASTI", "MUNDA TOLA"]}, "MATE": {"BADGAON": ["MAIN BASTI", "PATEL TOLA"], "MATE": ["CHHAPAR TOLA", "MAIN BASTI", "MARARI TOLA", "NARSARI TOLA", "NAYA TOLA", "SACATA TOLA"]}, "NIKKUM": {"NIKUM": ["AWAS TOLA", "KABARA TOLA", "MAIN BASTI", "MARARI TOLA", "SARAI TOLA"]}, "PALHERA": {"PALHERA": ["MAIN BASTI", "MARARI TOLA", "MINAHI TOLA"]}, "PANDRIYA": {"BHIMDONGRI": ["MAIN BASTI"], "DONGARIYA": ["AWAS TOLA", "BULUKU TOLA", "MAIN BASTI", "SADAK TOLA", "THETHWAR TOLA"], "PANDHRIPATHR": ["AWAS TOLA", "MAIN BASTI"]}, "PIPER TOLA": {"PIPARTOLA": ["DAMOH TOLA", "GONDI TOLA", "MAIN BASTI", "MARARI TOLA", "SARAI TOLA"]}, "RAGHOLI": {"RAGHOLI": ["AGARWADA", "MAIN BASTI", "MANDIR TOLA"]}, "RAILWAHI": {"RELWAHI": ["BAD TOLA", "BANAFAR TOLA", "BICH TOLA", "BIJA TOLA", "DAHIYAN TOLA", "DAU TOLA", "HARIJAN TOLA", "JAM TOLA", "LATKAN TOLA", "MAIN BASTI", "PARSAI", "SARAI TOLA"]}, "RAMGARHI": {"RAMGARHI": ["ADMAL", "AWAS TOLA", "BADA TOLA", "KHARRADHAR", "MAIN BASTI"]}, "SALETEKARI": {"MAJGAON": ["BHATA PARA", "MAIN BASTI"], "SALETEKRI": ["BAIGA TOLA", "CHOUKI TOLA", "KOPEBHATA", "MAIN BASTI", "POLICE CHOUKI"]}, "SALEWADA": {"SALEWADA": ["AWASH TOLA", "DARJI TOLA", "MAIN BASTI", "MARARI TOLA", "MILKAT TOLA", "MUNDA TOLA", "TELI TOLA", "TELITOLA"]}, "SALGHAT": {"GARRATOLA": ["MAIN BASTI", "NAYA TOLA"], "PANDHARIYA": ["LALU TOLA", "MAIN BASTI"], "SALGHAT": ["AWAS TOLA", "CHHOTA SALGHAT", "MAIN BASTI"]}, "SAMNAPUR": {"SAMNAPUR": ["BAIGA TOLA (I)", "BAIGA TOLA (II)", "JAISINGH TOLA", "JHAGARA TOLA", "MAIN BASTI", "TIKARA TOLA"]}, "SAYAL": {"PARSATOLA": ["AWAS TOLA", "HARRA TOLA", "MAIN BASTI"], "SAYAL": ["GONDI TOLA", "MAIN BASTI", "NAHAR TOLA", "TIKRA TOLA"]}, "SINGHANPURI": {"SINGANPURI": ["GONDI TOLA", "MAIN BASTI", "MARARI TOLA"]}, "SONGUDDA": {"CHARGHAT": ["ANDHIYARIBAN", "BAIGA TOLA", "KIDGI TOLA", "KOKI TOLA", "MAIN BASTI", "PATEL TOLA"], "KODAPAR": ["BAIGA TOLA", "BAIGA TOLA (II)", "GAYAKI  TOLA", "KARIGAR TOLA", "MAIN BASTI"], "KUNDUL": ["MAIN BASTI"], "MAJDHAR": ["CHATWA TOLA", "MAIN BASTI"], "SONGUDDA": ["BAGDHARI", "BISI TOLA", "GARHI TOLA", "KASAR TOLA", "MAIN BASTI", "PANAWAHI TOLA", "SUKULPATH"]}, "SUNDARWAHI": {"SUNDARWAHI": ["DOSHI TOLA", "IMALI TOLA", "MAIN BASTI", "MARARI TOLA", "SONAR TOLA", "SUDIN TOLA", "SUKHI TOLA"]}, "SURWAHI": {"SURWAHI": ["AWAS TOLA", "CHHOTE SURWAHI", "MAIN BASTI", "MARARI TOLA", "THAKUR TOLA"]}, "TINGIPUR": {"CHAKARWAHI": ["BAIGA TOLA", "MAIN BASTI", "MINAHI TOLA"], "TINGIPUR": ["BAHI TOLA", "BAIGA TOLA", "GONDI TOLA", "MAIN BASTI", "MANDIR TOLA", "SARAI TOLA"]}}, "KATANGI": {"AGARWADA": {"AGARWADA": ["AGARWADA", "JANGAL TOLA", "NEEMTOLA"]}, "AGASI": {"AGASI": ["AGASI", "AWAS TOLA", "CHOKI TOLA", "MACHINE TOLA"]}, "AGRI": {"AGRI": ["AGRI", "AWAS TOLA", "JEEVAN TOLA", "JOTIYA TOLA"], "LAKHANWADA": ["STATION TOL", "STATION TOLA"]}, "AMBEJHARI": {"AGRI": ["AGARI"], "AMBEJHARI": ["AMBEJHARI", "AWASTOLA"], "CHUTKIDEORI": ["CHITKA DEVRI"], "KHAIRLANGI": ["KHAIRLANGI"], "PATHARAPET": ["PATHRAPET"]}, "AMBEJHRI": {"AGARI": ["AGARI"]}, "ANJAN BIHARI": {"ANJAN BIHARI": ["ANJANBIHARI"], "PANDHARI": ["PANDHRI"]}, "ARJUNI": {"ARJUNI": ["ARJUNI", "HUDKI TOLA", "KARNU TOLA"], "LOHAGRI RYT.": ["LOHAGRI"]}, "BADPANI": {"BADPANI": ["AWAS TOLA", "BADPANI"]}, "BAHKAL": {"ATRI": ["ATRI", "HOLIYA TOLA"], "BAHAKAL": ["ATRI", "BAHKAL", "GONDI TOLA", "NALA TOLA", "SCHOOL TOLA"]}, "BAMHNI": {"BAMHANI": ["BAMHNI", "GURU KUL TOLA", "KATIA TOLA", "SAHU TOLA"]}, "BANERA": {"BANERA": ["BANERA", "BHOI TOLA", "JAMRA TOLA", "MANGRU TOLA", "PARSA TOLA"]}, "BASI": {"BASI": ["AWAS TOLA", "BASI", "GONDI TOLA", "PAWARI TOLA"]}, "BHAJIYAPAR": {"BHAJIYAPAR M": ["AWAS TOLA", "BHAJIYAPAR (M)", "RANGO TOLA"], "BHAJIYAPAR(J": ["BHAJIYAPAR JADKHARID", "GONDI TOLA", "KHATI TOLA"]}, "BICHUWA": {"BICHHWA RYT.": ["AWAS TOLA", "BICHUWA RAYAT"], "CHANDADOH": ["AWAS TOLA", "CHANDA DOH"]}, "BISAPUR": {"BISAPUR": ["AWAS TOLA", "BALA PUR TOLA", "BISAPUR", "DHEEMAR TOLA", "DHIMRU TOLA", "DURJAN TOLA", "MARARI TOLA"]}, "BOLDONGARI": {"BOLDONGARI": ["BAN TOLI", "BOLDONGARI", "SCHOOL TOLA"], "DONGARGAON": ["DONGAR GAON"]}, "BONKATTA": {"BONKATTA": ["AWAS TOLA", "BONKATTA"]}, "BOTHWA": {"BOTHWA": ["BOTHWA"]}, "CHAKAHETI": {"CHAKAHETI": ["ARJUN TOLA", "AWAS TOLA", "CHAKA HETI", "JAMUN TOLA", "NAYA TOLA", "NEEM TOLA", "RAMJI TOLA", "SATI TOLA"], "JAMRAPANI": ["DAFAI TOLA", "ENGINEER TEKRI", "JAMRA PANI"]}, "CHAUKHANDI": {"CHAUKHANDI": ["CHAUKHANDI", "CHAUKHANDI TOLA", "KABIR TOLA"]}, "CHICHGAON": {"CHICHGAON": ["AWAS TOLA", "BHAKARA TOLA", "CHICHGAON", "PATEL TOLA", "RAM NAGAR"]}, "CHIKMARA": {"CHIKMARA": ["AAMA TOLA", "AWAS TOLA", "CHIKMARA", "CHOTA TOLA", "MARARI TOLA"]}, "DEORI": {"DEORI": ["BUS TOLA", "DEORI", "KANHAR TOLA", "MIRCHI TOLA"]}, "DEVTHANA": {"DEOTHANA": ["AAMATOLA", "AWAS TOLA", "CHAMRU TOLA", "DEVTHANA"]}, "DHANKOSHA": {"DHANKOSA": ["DANKHOSHA", "GONDI TOLA", "MARARI TOLA"]}, "DIGDHA": {"DIGDHA": ["AWAS TOLA", "DIGDHA", "HETI TOLA"]}, "GHUNADI": {"GHUNADI": ["AWAS TOLA", "GHUNADI", "NAK TOLA"]}, "GOREGHAT": {"BHONDKI": ["BHONDKI"], "GOREGHAT": ["AWAS TOLA", "GHOREGHAT", "HETITOLA"]}, "HARDOLI": {"CHITEWANI": ["CHEETEWANI"], "HARDOLI": ["AWAS TOLA", "HARDOLI"]}, "HATODA": {"BORI(HAMESHA": ["BORI HAMESHA"], "HATODA": ["HATODA", "NAWEGAON (H)"], "KAPOOR BIHAR": ["KAPOOR BIHRI"], "NAWEGAON(HAM": ["NAWEGAON (H)"]}, "JAM": {"JAM": ["AWAS TOLA", "CHAMAR TOLA", "DHEEMAR TOLA", "GUNDI TOLA", "JAAM", "JAMAR TOLA", "MAHARU TOLA", "MUNDA TOLA", "PANCHU TOLA", "PEEPAR TOLA", "TIKA RAM TOLA"]}, "JAMUNIYA": {"DHIMRU REETH": ["DHIMRURITH"], "JAMUNIYA": ["DEENA TOLA", "HOLIYA TOLA", "JAMUNIYA", "MARARI TOLA", "NAKA TOLA", "NEW AWAS"], "KACHHAR F.V.": ["KACHAR"]}, "JARAHMOHGAON": {"JARAH MOHGAO": ["GHANA TOLA", "INDIRA TOLA", "JARAHMOHGAON", "LAKKI TOLA", "SADAK TOLA"]}, "KALE MATI": {"BORIKHEDA MAL": ["BORIKHEDA MAL", "NATOTOLA", "SCHOOL TOLA"]}, "KALGAON": {"KALGAON": ["JANGAL TOLA", "KALGAON", "NADI TOLA"]}, "KALIMATI": {"BORIKHEDA MA": ["BORIKHEDA (MAAL)", "NANGO TOLA", "SCHOOL TOLA"], "BORIKHEDA RY": ["BORIKHEDA (RAIYAT)", "MATA TOLA", "PIPAR TOLA"], "KALIMATI": ["KALEMATI", "RAPTA TOLA", "RATAN TOLA", "SCHOOL TOLA"]}, "KAMTHI": {"KAMTHI": ["AKHAR TOLA", "GONDI TOLA", "HETI TOLA", "KAMTHI", "MAHAR TOLA", "MARARI TOLA", "TELI TOLA"]}, "KANAHADGOAN": {"CHITKADEORI": ["CHUTKIDEORI"], "DEORI BUJURG": ["DEORIBUJURG"], "KANHADGAON": ["KANAHADGAON"]}, "KATEDARA": {"KATEDARA": ["AMAA TOLA", "KATEDARA", "LAXMICHAND TOLA", "MUKA TOLA"]}, "KATERA": {"BOPLI": ["BOPLI", "MASTER TOLA"], "KATERA": ["AWAS TOLA", "KATERA", "PATEL TOLA", "SCHOOL TOLA", "SUKAN TOLA"]}, "KHAIRLANJI": {"KHAIRLANJI": ["DHEEMAR TOLA", "KHAIR LANJI", "MARARI TOLA", "NEW AWAS", "RAMNAGAR"]}, "KHAJARI": {"KHAJRI": ["AWAS TOLA", "GUNDI TOLA", "KHAJARI", "MANNU TOLA", "MARGHAT TOLA", "RAPTA TOLA", "SADAK TOLA"]}, "KHAMRIYA": {"KHAMARIYA": ["AWAS TOLA", "BANJARI TOLA", "KHAMRIYA", "SADAK TOLA", "SCHOOL TOLA", "SHANKAR TOLA"]}, "KHARPADIYA": {"HIRAPUR": ["HIRA PUR", "TILLI TOLA"], "KHARPADIYA": ["AWAS TOLA", "KANHAR TOLA", "KHARPADIYA"], "SIWANHETI": ["SIWAN HETI"]}, "KODBI": {"KODBI": ["KODBI"], "LAXMIPUR HAM": ["LAXMIPUR (H)"], "MASALKHAPA": ["MASUL KHAPA"]}, "KODMI": {"KODMI": ["AADIWASI TOLA", "AKHAR TOLA", "AWAS TOLA", "KODMI", "PUJARI TOLA"], "NAHLESARA": ["BAHADUR TOLA", "NAHLESARA", "SADAK TOLA", "TALAB KENDRA"]}, "KOHKA": {"KOHKA": ["AWAS TOLA", "KOHKA", "PATHAN TOLA", "SADAK TOLA"]}, "KOILARI": {"BANDAREWA": ["BANDEREWA"], "DULHAPUR": ["AWAS", "DULHAPUR"], "KOILARI": ["KOILARI", "SADAK TOLA"]}, "KOSMI": {"KOSMI": ["AAKHAR TOLA", "GOWARI TOLA", "KOSMI", "NEW AWAS", "SCHOOL TOLA"]}, "KOSUMBA": {"KOSAMBA": ["GOWARI TOLA", "HOLIA TOLA", "KOSUMBA"]}, "KUDWA": {"KUDWA": ["COLONY", "KUDWA", "TUMDI TOLA"], "SANGRAMPUR H": ["SANGRAMPUR"]}, "LAKHANWADA": {"LAKHANWADA": ["LAKHANWADA", "STATION TOLA"]}, "LINGAPAUNAR": {"LINGA PAUNAR": ["BAZAR TOLA", "GOULI TOLA", "INDIRA AWAS", "LINGAPAUNAR", "NALA TOLA", "NARBAD TOLA"]}, "LOHMARA": {"LOHAMARA": ["AAKHAR TOLA", "AMRAI TOLA", "AWAS TOLA", "LOHMARA", "SADAK TOLA"]}, "MAHDOLI": {"MAHEDULI": ["MEHDOLI", "NAHAR TOLA", "NARAYAN TOLA"]}, "MAHKEPAR": {"GANESHPUR(HA": ["GANESHPUR"], "KISANPUR(HAM": ["KISHANPUR"], "KOSAMTOLA (H": ["KOSAM TOLA"], "MAHKEPAR": ["BADTOLA", "BHIMSEN TOLA", "CHANDRESH TOLA", "JAFARTOLA", "KANDRUTOLA", "MAHKEPAR", "SARWANTOLA"]}, "MANEGAON": {"MANEGAON": ["AWAS TOLA", "KESHAV TOLA", "MANEGAON", "NANDU TOLA", "SAWAR TOLA"]}, "MOHGAON": {"MOHGAON": ["GUNDI TOLA", "MOHGAON", "SCHOOL TOLA"]}, "NANDI": {"NANDI": ["AWAS TOLA", "INDIRA AWAS TOLA", "NANDI"]}, "NANDLESARA": {"NANDLEASRA": ["NANDLESARA", "SADAK TOLA", "SCHOOL TOLA", "TALAB KENDRA"]}, "NANDORA": {"NANDORA": ["NANDORA", "NANDORA TOLA"]}, "NAWEGAON": {"JHANJHAGI": ["AWAS TOLA", "JHANJHAGI"], "NAWEGAON(ANT": ["AWAS TOLA", "DHEEMAR TOLA", "NAWEGAON"]}, "PARASWADAGHAT": {"PARASWADAGHA": ["AWAS TOLA", "LODHI TOLA", "NEW AWAS", "PARASWADA GHAT"]}, "PATHARWADA": {"PATHARWADA": ["AWAS TOLA", "DHEEMAR TOLA", "MARARI TOLA", "PATHARWADA"]}, "PAUNIYA": {"PAUNIYA": ["GONDI TOLA", "GONDI TOLA (NEW)", "PAUNIYA"]}, "SADABODI": {"CHICHGAON": ["CHICHGAON (H)"], "GARRAGUSAI": ["GARRA CHOUKI", "GARRA GOSAI", "NEW AWAS"], "GUSAITOLA": ["GOSAI TOLA"], "SADABODI": ["SADABODI"]}, "SAMATPURI": {"SAMATPURI": ["AWAS TOLA", "GONDI TOLA", "PAWARI TOLA", "SAMATPURI"]}, "SAONGI": {"SAWNGI": ["BAD TOLA", "BADA TOLA", "NADI TOLA", "SAONGI"]}, "SAWRI": {"SAWRI": ["SAWRI"]}, "SELWA": {"BADGAON": ["AWAS TOLA", "BADGAON"], "SELWA": ["DONGRU TOLA", "NARSU TOLA", "SELWA"]}, "SINGODI": {"SINGODI": ["RAMJI TOLA", "SINGODI", "SUNDAR TOLA", "TELI TOLA"]}, "SIRPUR": {"SIRPUR": ["AWAS TOLA", "DAK TOLA", "MOHAN TOLA", "PARSA TOLA", "SINDHI TOLA", "SIRPUR"]}, "SITAKHOH": {"SITAKHOH": ["AWAS TOLA", "BUDDA TOLA", "NEEM TOLA", "SHEETAL TOLA", "SITAKHOH"]}, "SONE GOAN": {"PIPRIYA": ["DEEMRI TOLA", "PIPRIYA"], "SONEGAWON": ["AMRAI TOLA", "SONEGAON"]}, "SONEGAON": {"PIPRIYA": ["DHEMRI TOLA", "PIPARIYA"], "SONEGAON": ["AMRAI TOLA", "SONEGAON"]}, "SUKLI": {"SITAPATHOR": ["AWAS TOLA", "CPMO KENDRA", "KHIRBANDH DAFAI", "SITAPATHOUR"], "SUKALI": ["AMADAFAI", "AMEER TOLA", "AWAS TOLA", "BHIMSEN TOLA", "GOPIKISAN DAFAI", "STATION DAFAI", "SUKLI"]}, "SUNDER": {"BIRSULA": ["AWAS TOLA", "BIRSOLA", "SHANKAR TOLA"], "SUNDAR": ["PATEL TOLA", "PIPAR TOLA", "SUNDAR"]}, "TEKADI (K)": {"TEKADI": ["AWAS TOLA", "BAHEDA TOLA", "HETI TOLA", "TEKADI ( KALI MATI)"]}, "TEKADI (M)": {"KATARKANA": ["AWAS TOLA", "CHAMARI TOLA", "DHEEMAR TOLA", "KATARKANA"], "TEKADI": ["GONDI TOLA", "NARAYAN TOLA", "PAWARI TOLA", "TEKADI (M)"]}, "TEKAKDI (BH)": {"CHIRCHIRA": ["CHIRCHIRA", "MEGA TOLA"], "TAKADI": ["RAGU TOLA", "SADAK TOLA", "TEKADI (BH)"]}, "TIRODI": {"TIRODI": ["TIRODI"]}, "UJADBOPLI": {"GOPALPUR": ["GOPAL PUR", "MARARI TOLA"], "UJAD BOPLI": ["AWAS TOLA", "KASHI TOLA", "KHOLA PUR", "MANGO TOLA", "NARSINGH PUR", "UJADBOPLI"]}, "UMARI": {"UMRI": ["AWAS TOLA", "NADI TOLA", "UMARI"]}, "VARUD": {"VARUD": ["AWAS TOLA", "BUDHHA TOLA", "VARUD"]}}, "KHAIRLANJI": {"AMAI": {"AMAI": ["AMAIEE", "AWAS TOLA", "KANHAR TOLA", "NEW AWAS"]}, "ARAMBHA": {"ARAMBHA": ["ARAMBHA"]}, "ATARI": {"ATRI": ["ATARI", "GONDI TOLA", "HETI TOLA", "NEW AWAS", "TUKA TOLA", "UDAL TOLA"]}, "BAKODI": {"BAKODI": ["AAKHO TOLA", "AWAS TOLA", "BAKODI", "GOSI TOLA", "MARARITOAL", "NEW AWAS", "PHAGO TOLA"]}, "BENI": {"BENI": ["BENI", "BENI TOLA", "MARARI TOLA", "NEW AWAS"]}, "BHAJIYADAND": {"BHAJIYADAND": ["AEAS TOLA", "BHAJIYADAND", "INDRAAWAS", "NEW AWAS", "PATEL TOLA"]}, "BHANDARBODI": {"BHANDARBODI": ["BHANDARBODI", "GOVIND TOLA", "LAMNDOH TOLA", "NAGO TOLA", "NAHAR TOLA", "NEW AWAS", "PIPAR TOLA"], "YENAGONDI": ["AKHAR TOLA", "YANAGONDJ"]}, "BHANPUR": {"BHANPUR": ["AWAS TOLA", "BHANPUR"]}, "BHENDARA": {"BHENDARA BAS": ["AWAS TOLA", "BHENDARA", "DHEMAR TOLA"]}, "BHOURGARH": {"BHAURGARH": ["AWAS TOLA", "BHOURGARH", "DHEEMAR TOLA", "NEW AWAS"]}, "BITODI": {"BITODI": ["BITODI", "KANHAR TOLA", "NEW AWAS", "PAHADI TOLA"]}, "CHHATERA": {"CHHETERA": ["CHHATERA", "INDIRA TOLA"]}, "CHICHOLI": {"CHICHOLI": ["CHICHOLI", "INDIRA AWAS", "MATA TOLA", "SCHOOL TOLA"]}, "CHIKHALA": {"CHIKHALA": ["AWAS TOLA", "CHIKHALA"]}, "CHUTIYA": {"CHUTIYA": ["CHUTIYA", "CHUTIYAAWARI TOLA", "MAHAJAN TOLA", "MAHAR TOLA", "NEW AWAS"]}, "DONGARIYA": {"DONGARIYA": ["DONGARIYA TOLA", "DUDHARA", "HOLYA TOLA", "PUJARI TOLA"]}, "DUDHARA": {"DUDHARA": ["DUDHARA", "SARWAN TOLA", "SCHOOL TOLA"], "JAMKHARI": ["AWAS TOLA", "JAMKHARI"], "MANGLEGAON": ["AWAS TOLA", "MAHAJAN TOLA", "MANGALE GAON"]}, "FULCHUR": {"FULCHUR": ["FULCHUR", "NEW AWAS", "SCHOOL TOLA"]}, "GAJPUR": {"GAJPUR": ["CHICHTOLA", "GAJPUR"]}, "GHOTI": {"GHOTI": ["AWAS TOLA", "AWAS TOLAHEEMAR TOLA", "GHOTI", "NEW AWAS TOLA", "PATHAN TOLA"]}, "GHUBADGONDI": {"GHUBADGONDI": ["AWAS TOLA", "BABAJI TOLA", "GHUBADGONDI"]}, "GUDRUGHAT": {"GUDRUGHAT": ["GUDRUGHAT"]}, "GUNAIEE": {"GUNAI": ["CHANDAN TOLA", "GUNAIEE", "NEW AWAS"]}, "JHARIYA": {"JHIRIYA": ["GONDI TOLA", "JHARIYA", "KEHRI TOLA", "NEW AWAS", "PATEL TOLA"]}, "KACHEKHANE": {"KACHEKHANI": ["DHEEMAR TOLA", "HETI TOLA", "KHACHEKHANE BASTI", "NEW AWAS"], "MURJHAD": ["MURJHAD", "MURJHAD TOLA"]}, "KANHADGAON": {"CHICHOLI": ["CHICHOLI", "PARIHAR TOLA"], "KANHADGAON": ["GULAB TOLA", "KANHADGAON"], "KATANGI": ["KATANGI", "KATANTI TOLA"]}, "KATORI": {"KATORI": ["KATORI", "SAI TOLA"]}, "KHAIRI": {"KHAIRI": ["DAMA TOLA", "DHEEMAR TOLA", "GUSAI TOLA", "KHAIRI", "MAHADEO TOLA", "PAWAR TOLA", "TIJU TOLA"]}, "KHAIRLANJI": {"KHAIRLANJI": ["AWASTOLA", "KHAIRLANJI"]}, "KHARKHADI": {"KHARKHADI": ["AWAS TOLA", "KHARKHADI", "MAHAJAN TOLA"]}, "KHURSIPAR": {"KHURSIPAR": ["DHEEMAR TOLA", "KHURSIPAR", "NEW AWAS", "PHOGAL TOLA"]}, "KINHI": {"KINHI": ["INDIRA AWAS", "KINHI", "KRISHI FORM TOLA", "MANDIR TOLA"]}, "KOTHURNA": {"KOTHURNA": ["AWAS TOLA", "GONDI TOLA", "KOTHURNA", "NEW AWAS"]}, "KUMHLI": {"KUMAHALI": ["KUMHLI"], "MANEGAON": ["AKHARTOLA", "AWAS TOLA", "MANEGAON"]}, "LAWANI": {"LAWANI": ["DHEEMAR TOLA", "LAWANI", "NEW AWAS"]}, "MIRGPUR": {"MIRAGPUR": ["INDIRA AWAS", "MIRAGPUR"], "PANDHARWALI": ["BANA TOLA", "PANDARWANI", "SATI TOLA"]}, "MOHADI": {"MOHADI": ["AWAS TOLA", "MOHADI"]}, "MOHGAONBAIJU": {"MOHAGAON BAI": ["MOHGAONBAIJU", "SARWAN TOLA"]}, "MOHGAONGHAT": {"MOHGAON GHAT": ["MOHGAONGHAT", "MUSHLMAN TOLA"]}, "MOWAD": {"DONGARIYA": ["DONGARIYA", "NEW AWAS"], "MOWAD": ["INDIRA AWAS", "MATE TOLA", "MOWAD"]}, "NAWEGAON (KH-)": {"CHICHTOLA": ["AWAS  TOLA", "CHICHTOLA"], "NAWEGAON KHU": ["AWAS TOLA", "NAWEGAON (KH)", "NEW AWAS TOLA"]}, "NEWEGOAN TINTOLA": {"NEWEGAON  TINTOLA": ["HANUMAN TOLA", "MANDIR TOLA", "NEW AWAS", "NEWEGAON  TINTOLA"]}, "NONSA": {"NONSA": ["NONSA", "NONSA TOLA"]}, "PANJRA": {"PANJRA": ["PANJRA", "PANJRA TOLA"]}, "PINDKEPAR": {"KHAPA": ["KHAPA"], "PINDKEPAR": ["MARARI TOLA", "PINDKEPAR"]}, "PIPRIYA": {"PIPARIYA": ["AWAS TOLA", "NEW AWAS", "PIPARIYA", "TALAB TOLA"]}, "PULPUTTA": {"PULFATTA": ["HETI TOLA", "INDIRA AWAS", "NEW AWAS", "PULPUTTA"]}, "SABARGAON": {"SABARGAON": ["SAWARGAON"]}, "SAKDI": {"SAKDI": ["PANCHU TOLA", "SAKDI"]}, "SALEBARDI": {"SALEBARDI": ["AWAS TOLA", "DARIYA TOLA", "GANNU TOLA", "SALEBARDI"]}, "SALETEKA": {"SALETEKA": ["HETI TOLA", "INDIRA AWAS", "JHINGAR TOLA", "SALETEKA"]}, "SATONA": {"CHICHAGAON": ["CHICHGAON", "NEW AWAS"], "SATONA": ["DHEEMAR TOLA", "NEW AWAS", "SATONA"]}, "SAWRI": {"SAWARI": ["DHEEMAR TOLA", "GONDI TOLA", "LODHI TOLA", "SAWRI"]}, "SELOTPAR": {"SELOTPAR BAS": ["BRAHAMN TOLA", "GONDI TOLA", "MACHKURI TOLA", "SELOTPAR"]}, "SHANKAR PIPARIYA": {"SHANKAR PIPA": ["GONDI TOLA", "SANKAR PIPARIYA"], "TEKADI TIJU": ["INDIRA AWAS", "SCHOOL TOLA", "TEKADI TIJU"]}, "SHIVPURLILMA": {"SHIVPURLILMA": ["AWAS TOLA", "LILAMA TOLA", "SHIVPUR LILMA"]}, "SIWANGHAT": {"FUTARA": ["FUTARA"], "SUKDIGHAT": ["SIWANGHAT"]}, "TATEKASHA": {"TATEKSA": ["TATEKASHA"], "TUMSAR": ["TUMSAR"]}, "TEKADIGHAT": {"SUKADIGHAT": ["NEW AWAS", "SUKADIGHAT"], "TEKADIGHAT": ["TEKADIGHAT"]}, "TEMNI": {"TEMANI": ["DHEEMAR TOLA", "GANGA TOLA", "JAGAN TOLA", "LODHI TOLA", "SHIV TOLA", "TEMNI"]}, "TUINYAPAR": {"CHORPINDKEPA": ["CHOR PINDKEPAR", "TOLA"], "TUYYAPAR": ["CHANDRA KUNWA", "DHANOD TOLA", "TUINYAPAR"]}, "YERWAGHAT": {"GIRRA BODI": ["FUTA  TOLA", "GARRABODI", "GONDI TOLA", "SCHOOL TOLA"], "YEKHAGHAT": ["HETI TOLA", "YERWA TOLA", "YERWAGHAT"]}}, "KIRNAPUR": {"AKOLA": {"AKOLA": ["AKOLA BASTI", "CHOTU TOLA", "NADI TOLA", "TAR TOLA"], "BIRANPUR": ["BIRANPUR BASTI"]}, "AMGAON": {"AMGAON": ["AMGAON BASTI"], "KOTARI": ["KOTARI BASTI"]}, "BADAGAON": {"BADGAON": ["BADAGAON BASTI", "HALBI TOLA"]}, "BAGADMARA": {"BAGADMARA": ["BAGADMARA BASTI"]}, "BAKKAR": {"BAKKAR": ["BAKKER BASTI"]}, "BAMHANGAON": {"BAMHANGAON": ["BAMHANGAON ASTI", "PARSA TOLA"]}, "BAMHANI": {"BAMHANI": ["AWAS TOLA", "BAMHANI BASTI", "NEW AWAS"]}, "BELGAON": {"BATAMA": ["BATAMA BASTI", "SIKARI TOLA"], "BELGAON": ["BELGAON BASTI", "GONDI TOLA"], "GOPALPUR": ["GOPALPUR BASTI", "MARARI TOLA"]}, "BENEGAON": {"BENEGAON": ["AWAS TOLA", "BENEGAON"]}, "BHALWA": {"BHALWA": ["BHALWA BASTI", "DONGA TOLA", "GHASSU TOLA", "LALLA TOLA", "SARVAN TOLA"]}, "BHUWA": {"BHUWA": ["AWAS TOLA", "BHOWA BASTI", "MARARI TOLA"]}, "BINORA": {"BINORA": ["BINORA BASTI", "KUMAHAR TOLA"]}, "BODANDA KALA": {"BODUNDA KALA": ["AWAS TOLA", "BODANDA KALA BASTI", "NEW AWAS"], "CHHINDGAON": ["CHINDGAON BASTI"]}, "BORGAON": {"BORGAON": ["BORGAON BASTI", "RADHO TOLA"]}, "BUDHI": {"BUDHI": ["AWAS TOLA", "BUDHI BASTI", "BUDHI MARATHA", "BUDHI SAHARIYA"], "RATTAPAYLI": ["AWAS TOLA", "CHAMARI TOLA", "RATTAPAYLI"]}, "CHIKHALA": {"CHIKHLA": ["AWAS TOLA", "CHIKHALA BASTI"]}, "DAHIGADWA": {"DAHEGADHWA": ["AWAS TOLA", "DAHIGADWA BASTI"], "DHARAPURI": ["DHARAPURI BASTI"]}, "DATTA": {"DATTA": ["DATTA BASTI"]}, "DEOGAON": {"DEOGAON": ["ADIWASI TOLA", "DEOGAON BASTI"]}, "DHADI": {"DHADI": ["AWAS TOLA", "DHADI BASTI", "SCHOOL TOLA"]}, "DHEDI": {"DEHDI BASTI": ["DEHDI BASTI", "INDIRA WARD", "NEELJI TOLA", "PEEPAR TOLA"], "MORWAHI": ["MORVAHI BASTI"]}, "DONGARGAON": {"BATKARI": ["BATKARI BASTI"], "DONGARGAON": ["BAR TOLA", "DONGERGAON BASTI"]}, "DUNDA SEONI": {"DUNDASEONI": ["DUNDA SEONI BASTI", "PARSA TOLA"]}, "GODRI": {"BHAGATPUR": ["BHAGATPUR BASTI", "THAKUR TOLA"], "BHANPUR": ["BHANPUR BASTI"], "BODAL JHOLA": ["ABADI TOLA", "BODALJHOLA BASTI"], "GAURBHATTI": ["GODRI BASTI"], "NANDORA": ["NANDORA BASTI"], "SUKALDAND": ["SHUKALDAND BASTI"]}, "HIRRI": {"HIRRI": ["HIRAPUR", "HIRRI BASTI", "MATKA TOLA"]}, "JAMADI METHA": {"BANGALITOLA": ["BANGALI TOLA BASTI"], "CHANGERA": ["CHANGERA BASTI", "MADKU TOLA", "NAYA AWAS"], "CHINDI KUWA": ["CHINDI KUWA BASTI"], "JAMDIMETA": ["JAMADI METHA BASTI"], "NUMBERTOLA": ["NAYA TOLA", "NUMBER TOLA BASTI"], "SIRKA": ["SIRKA BASTI"]}, "JAMDI": {"DHORIYA PARA": ["BAMHAN TOLA", "DOLIYA PARASWADA BASTI"], "JAMDI": ["BANJARI TOLA", "HARIJAN TOLA", "JAMDI BASTI"]}, "JANWA": {"JANWA": ["AWAS TOLA", "JANWA BASTI"]}, "JARAHI": {"JARAHI": ["JARAHI BASTI"]}, "KADKNA": {"KADAKNA": ["AWAS TOLA", "GOWARI TOLA", "KADKNA BASTI", "LODHI TOLA"]}, "KAKODI RAN": {"KAKODI (RAN)": ["JHIRIYA TOLA", "KAKODI RAN BASTI", "NADI TOLA", "NEEM TOLA", "PAND TOLA"], "LODHANGI": ["KATANG TOLA", "LODANGI BASTI"], "SAKRITOLA": ["BOAR BAN", "GANESH TOLA", "SAKARI TOLA BASTI"]}, "KAKUDIRON": {"KAKODI RAN": ["JHIRIYA", "KAKODI RAN", "NIM TOLA", "PANDA TOLA"], "LODHAGI": ["KATANG TOLA", "LODHAGI"], "SAKRI TOLA": ["BOARBAN", "GANESH TOLA", "SAKRI TOLA"]}, "KANDR": {"CHATRU TOLA": ["CHATRU TOLA"], "CULLCATTA": ["CULLCATTA", "DEV TOLA"], "KANDRA": ["ALI TOLA", "KANDRA", "NEW AWAS", "NEW BOMBAY"], "KODA BARRA": ["KODA BARRA"]}, "KANDRA": {"CHATRUTOLA": ["AWAS TOLA", "CHATRU TOLA BASTI"], "CULCUTTA": ["CULCUTTA BASTI", "DEO TOLA"], "KANDRA": ["ALI TOLA", "KANDRA BASTI", "NEW AWAS", "NEW BOMBAY"], "KODOBARRA": ["KODOBARRA BASTI"]}, "KANDRI KALA": {"KANDRI KALAN": ["GANNA TOLA", "KANDRI KALA BASTI", "NEELAGONDHI"]}, "KANDRI KHURD": {"DHUDWA": ["DUNDVA"], "KANDRI KHURD": ["AWAS TOLA", "KANDRI KHURD BASTI", "MADHAV TOLA"]}, "KARIYA DAND": {"KARIADAND": ["BHOUTA TOLA", "KARIYA DAND BASTI", "TENDU TOLA"], "KHAPRAJHARI": ["KHAPRA JHARI BASTI"], "NEWARGAON KH": ["GONDI TOLA", "NEWARGAON KHURD BASTI"]}, "KASANGI": {"KASANGI": ["KASANGI BASTI", "KOHILA TOLA", "KOKRA TOLA", "RANU TOLA", "SIKARI TOLA"], "KOTHIATOLA": ["KOTHIYA TOLA BASTI"], "KUWAGONDI": ["KUWAGONDI BASTI"], "MADKA MANDAI": ["MADKAMADIA BASTI"]}, "KATANGI": {"KATANGI": ["KATANGI BASTI"]}, "KESA": {"KESHA": ["AWAS TOLA", "KESA BASTI", "NEW AWAS"]}, "KHARA": {"KHARA": ["AWAS TOLA", "INDIRA AWAS", "KHARA BASTI", "MATA TOLA", "SCHOOL TOLA"]}, "KINNHI": {"KINHI": ["HARIJAN TOLA", "INDIRA AWAS", "KINNHI BASTI", "KOHANGA TOLA", "KUNBHI TOLA", "LODHI TOLA", "MAHAJAN TOLA", "MARARI TOLA", "NUMBER TOLA", "PREM NAGAR"]}, "KIRNAPUR": {"KIRNAPUR": ["KIRNAPUR BASTI", "NARAYAN TOLA", "SONPURI"]}, "KOKNA": {"KOKNA": ["AWAS TOLA", "KOKNA BASTI", "LODHI TOLA"]}, "KOSMARA": {"BHAKKUTOLA": ["BHAKKU TOLA"], "KOSAMDEHI": ["AWAS TOLA", "KOSAMDEHAI"], "KOSMARA": ["GONDI TOLA", "KOSMARA", "KOSMORA"], "SIRRI": ["BICH TOLA", "NAKA TOLA", "PENDI TOLA", "SIRRI"]}, "KOSTE": {"KOSTE": ["KOSTE BASTI", "PATEL TOLA"]}, "KUNDE": {"KUNDE": ["CHIMAN TOLA", "HARI TOLA", "KATANG TOLA", "KUNDE BASTI", "SCHOOL TOLA", "SHIV TOLA"]}, "LAVERI": {"LAWERI": ["AWAS TOLA", "LAVERI BASTI", "PAWER TOLA"]}, "MADAKAPAR": {"MADKAPAR": ["AWAS TOLA", "MADAKAPAR BASTI"]}, "MANGOLI KALA": {"MANGOLI KALA": ["AWAS TOLA", "MANGOLI KALA BASTI", "NAYA TOLA"]}, "MANGOLI KHUR": {"BATARMARA": ["BATARMARA BASTI"], "MANGOLI KHUR": ["AWAS TOLA", "MANGOLI KHURD BASTI"]}, "MARRI": {"DIGODA": ["DIGODA BASTI"], "MARRI": ["MARRI BASTI"]}, "MATE": {"MATE": ["AWAS TOLA", "MATE BASTI", "POTITOLA"]}, "MOHAGAON KALA": {"MOHAGAON KALA": ["AWAS TOLA", "MOHAGAON KALA BASTI"]}, "MOHAGAON KHURD": {"MOHGAON KHUR": ["AWAS TOLA", "MACHINE TOLA", "MATA TOLA", "MOHAGAON BASTI", "MUKARDAM TOLA", "NARBAD TOLA", "PARSA TOLA", "TIMKI TOLA"]}, "MOUDA": {"MAUDA": ["MOUDA BASTI"]}, "MUNDESARA": {"MUNDESARA": ["AWASTOLA", "MUNDESARA"], "TIMKITOLA": ["TIMKI TOLA"]}, "MURKUDA": {"MURKUDA": ["AWAS TOLA", "MURKUDA BASTI"]}, "MURRI": {"MURRI": ["BADA TOLA", "MURRI BASTI"]}, "NAKSI": {"NAKSHI": ["NAKSI BASTI", "PAWARI TOLA"]}, "NEWARA": {"DONGARGAON": ["DONGERGAON"], "NEWARA": ["KUMHAR TOLA", "NEWARA BASTI"]}, "NEWARGAON KALA": {"NEWARGAON KA": ["AWAS TOLA", "NEWARGAON KALA BASTI", "SCHOOL TOLA"]}, "NIMDEWADA": {"NIMDEWADA": ["AWAS TOLA", "KUMAHI TOLA", "NIMDEWADA BASTI", "PATEL TOLA"]}, "PALA": {"PALA": ["PALA BADA", "PALA CHOTA"]}, "PALERA": {"PALHERA": ["NEW AWAS", "PALERA BASTI"]}, "PANGAON": {"PANGAON": ["KANAHAR TOLA", "PANGAON BASTI"]}, "PARASWADA": {"PARASWADA": ["PARASWADA BASTI"]}, "PARDI": {"PARDI": ["GONDI TOLA", "PARDI BASTI"]}, "PATHARI": {"PATHRI": ["PATHARI BASTI"]}, "PAUNI": {"KHOLMARA": ["KHOLMARA", "LOHAR TOLA", "POONA BHARRI"], "PAUNI": ["MARAR TOAL", "MASKA TOLA", "PANCHAYAT TOLA", "PAUNI", "SATI TOLA"]}, "PIPALGAON KALA": {"ATARIA": ["ATTARIYA"], "JODHITOLA": ["JHODI TOLA", "NEW AWAS"], "MENTHRA": ["BHASKA TOLA", "MENDRA"], "PIPALGAON  K": ["NAYA TOLA", "PIPALGAON KALA"]}, "PIPALGAON KH": {"PIPALGAON KH": ["AMARIYA TOAL", "KOTWAR TOLA", "PIPALGAON KHURD", "RANI TOLA"], "SONE SARAD": ["RAMU TOLA", "SONASERAD"]}, "PIPARJHARI": {"PIPARJHARI": ["AWAS TOLA", "PIPARJHARI BASTI"]}, "RAJEGAON": {"KOHKA": ["KOHAKA BASTI"], "RAJEGAON": ["RAJEGAON"]}, "RAMGADI": {"RAMGARHI": ["AWAS TOLA", "GONDI TOLA", "RAMGADI BASTI"]}, "SALETEKA": {"SALETEKA": ["AWAS TOLA", "SALETEKA BASTI"]}, "SALHE": {"SALHE": ["SALHE BASTI", "SARAI"], "SITAPARA": ["MUKDUM TOLA", "SITIPAR"]}, "SARAD": {"SARAD": ["BHUTIYA TOLA", "DHEMAR TOLA", "PATEL TOLA", "SARAD BASTI"]}, "SEONI KALA": {"OKASI": ["OKASI BASTI"], "SEONI": ["AWAS TOLA", "SEONI KALA BASTI"]}, "SEONI KHURD": {"KATORI": ["BHOUTHA TOLA", "KATORI BASTI"], "SEONI": ["AWAS TOLA", "SEONI KHURD"]}, "SEVITI": {"GULWA": ["GULWA BASTI", "KESHAW TOLA", "NADI TOLA"], "SEOTI": ["BHOWARA TOLA", "SEVITI BASTI"]}, "SIHORA": {"SIHORA": ["SIHORA BASTI"]}, "SINGODI": {"GUNAI": ["GUNAI BASTI"], "SINGODI": ["DEVI TOLA", "GOPAL TOLA", "SINGODI BASTI"]}, "SUSWA": {"MANAGARH": ["MANAGADH BASTI"], "SUSWA": ["HUDDU TOLA", "SOHCKI TOLA", "SUSWA BASTI"]}, "WARA": {"KANERI": ["HETI TOLA", "KANERI BASTI"], "WARA": ["DULIYA TOLA", "WARA BASTI"]}}, "LALBURRA": {"AMOLI": {"AMOLI": ["AMOLI BASTI", "AWAS TOLA", "DADIYA TOLA"]}, "ATRI": {"ATRI": ["AAMA TOLA", "ATRI", "ATRI BASTI", "CHANDAN TOLA", "GANPATI TOLA"], "DORLI": ["AWAS TOLA", "DORLI BASTI"]}, "AWALYA KANAR": {"AWALYA KANAR": ["AWALYA KANAR BASTI", "AWAS TOLA"], "BITHALI": ["BHIMSEN TOLA", "BITHALI BASTI", "MURLIKHAM"]}, "BABARIYA": {"BABARIYA": ["BABARIYA BASTI", "BABARIYA TOLA", "SCHOOL TOAL"], "KATANGA": ["ADIWASI TOLA", "AWAS TOLA", "KATANGA BASTI"]}, "BADGAON": {"BADGAON": ["BADGAON BASTI", "JEEVAN TOLA"], "NAYATOLA": ["NAHAR TOLA", "NAYA TOLA BASTI", "PATEL TOLA"]}, "BADI PANBIHARI": {"PANBIHARI": ["AWASTOLA", "BADI PANBIHARI", "NAYA AWAS TOLA"]}, "BAGDAHAE": {"BAGDEHI": ["AAMA TOLA", "BAGDEHI BASTI", "GONDI TOLA", "MARARI TOLA", "SCHOOL TOLA"], "DOHARA": ["AWASTOLA", "DOHARA BASTI"], "SELWA": ["DHIMAR TOLA", "GONDI TOLA", "SALWA BASTI", "SHANKAR"]}, "BAGHOLI": {"BAGHOLI": ["BAGHOLI BASTI", "NAYA AWAS", "RATAN TOLA", "SCHOOL TOLA"]}, "BAHEGAON": {"BAHEGAON": ["AWASTOLA", "BAHEGAON BASTI", "PAWARI TOLA"]}, "BAHIYA TIKUR": {"BAHIYATIKUR": ["AWAS TOLA", "BAHIYA TIKUR BASTI", "CHITA TOLA"], "MARHERA": ["DASHRA TOLA", "MARARA BASTI", "PREMA TOLA"]}, "BAKODA": {"BAKODA": ["BAKODA BASTI", "KEMP TOLA", "PIPAL TOLA"]}, "BALEGAON": {"BELGAON": ["AWAS TOLA", "BELGAON BASTI", "DADIYA TOLA", "NAHAR TOLA", "SENIYA TOLA"]}, "BALHARPUR": {"BALHARPUR": ["AWAS TOLA", "BALHARPUR BASTI", "LAKHAN TOLA"]}, "BAMHANI": {"BAMHANI": ["AWAS TOLA", "BAMHANI BASTI"], "DORLI": ["AWAS TOLA", "DORLI BASTI"]}, "BANDRI": {"BANDRI": ["AWAS TOLA", "BANDARI BASTI", "MANDAI TOLA", "PANJRA TOLA"], "BOTTA": ["BOTTA BASTI", "PAHADI TOLA"]}, "BEHRAI": {"BEHARAI": ["BEHRAI BASTI", "DHAR SHAHI TOLA", "GONDI TOLA", "MACHINE TOLA", "UDASI TOLA"]}, "BHANDA MURRI": {"BHANDAMURRI": ["BHANDA MURRI BASTI", "BIGARI TOLA", "BIROLI", "KACHHAR", "KANAHAR TOLA", "SCHOOL TOLA"]}, "BIRSOLA": {"BIRSULA": ["AWAS TOLA", "BIRSOLA BASTI", "SADAK TOLA"]}, "BORI": {"BORI": ["BORI BASTI", "BORI TOLA", "PARSA TOLA", "POTU TOLA", "SALAI TOLA"]}, "BUTTA HAJARI": {"BUTTE (HAZAR)": ["BUTTA HAJARI BASTI", "GONDI TOLA", "LODHI TOLA", "PAWARI TOLA", "SAGAR TOLA"]}, "CHANDRAPURI": {"CHANDPURI": ["BAD TOLA", "CHANDRAPURI BASTI", "NAHAR TOLA", "SHIV TOLA", "SURAJ TOLA"]}, "CHHATERA": {"CHHATERA": ["CHHATERA BASTI", "GONDI TOLA", "INDIRA AWAS", "SONARI TOLA"]}, "CHHILOD": {"CHILLOD": ["BHOAI TOLA", "BITTI TOLA", "CHHILOD BASTI", "GONDI TOLA", "MARARI TOLA", "RAGHO TOLA"]}, "CHHINDLAI": {"CHHINDLAI": ["CHHINDLAI BASTI", "CHHINDLAI TOAL", "INDIRA AWAS"], "KHAIRGAON": ["DEVI TOLA", "KHAIRGAON BASTI", "SHANKAR TOLA"]}, "CHICHGAON": {"CHICHGAON": ["BIJATOLA", "CHICHGAON", "HARRA TOLA", "NAKA TOLA"]}, "DADIYA": {"DADIYA": ["AWAS TOLA", "DADIYA BASTI", "KANDRA TOLA", "MANDAI TOLA", "MARARI TOLA"]}, "DEORI": {"DEORI": ["BID TOLA", "DEORI BASTI", "MANDIR TOLA", "SADAK TOLA"], "KHAMGHAT": ["AMRIT TOLA", "FAKIR TOLA", "KHAMGHAT BASTI", "NANDLAL TOLA"]}, "DHAPERA": {"DHAPERA": ["DHAPERA BASTI", "KATI TOLA", "LALGHAT TOLA", "NATHA TOLA"]}, "DHARAWASI": {"CHAWARPANI": ["CHAWARPANI BASTI"], "DHARAWASI": ["DHARAWASI BASTI", "KEMPA TOLA", "SALANG TOLA", "UDASI TOLA"], "MALGONDI": ["MALGONDI BASTI"], "MOSMI": ["AWAS TOLA", "KEWA TOLA", "MANU TOLA", "MOSAMI BASTI"]}, "DHARPIWADA": {"DHARPIWADA": ["AWAS TOLA", "DHARPIWADA BASTI", "SADAK TOLA", "SCHOOL TOLA"]}, "DOKARBANDI": {"DOKARBANDI": ["AWAS TOLA", "DOKARBANDI BASTI", "GONDI TOLA", "SHINDHI TOLA", "SONI TOLA", "THEKEDARI TOLA"], "GONDEGAON": ["AWAS TOLA", "GONDEGAON BASTI", "NAYA TOLA"]}, "DONGARIYA": {"BARBASPUR": ["BARBASPUR BASTI", "GONDI TOLA"], "DONGARIYA": ["AWAS TOLA", "DONGARIYA BASTI", "GONDI TOLA", "JAGAT TOLA", "MASIH NAGAR", "PRADHAN TOLA"]}, "GANESHPUR": {"GANESHPUR": ["AWAS TOLA", "GADEWAL TOLA", "GANESHPUR BASTI", "NAYA AWAS TOLA", "PATEL TOLA", "PAWARI TOLA"], "PALAKAMTHI": ["AWAS TOLA", "PALAKHAMTHI BASTI", "SADAK TOLA"]}, "GARAPURI": {"GARAPURI": ["AWAS TOLA", "GARAPUDI BASTI", "GARAPUDI TOLA"], "KHURSODI": ["KHURSODI BASTI", "KHURSODI TOLA", "NAHAR TOLA"]}, "GARRA": {"GARRA": ["BABAJI TOLA", "GARRA BASTI", "MACHINE TOLA", "SALAI TOLA"]}, "GHOTI": {"GHOTI": ["AWAS TOLA", "GHOTI BASTI", "KATANG TOAL", "SHANKAR TOAL"]}, "JAM": {"JAM": ["AWAS TOLA", "JAM BASTI", "JAM TOLA", "KANHAR TOLA", "KULCI BARRA"]}, "KAMTHI": {"KAMTHI": ["GONDI TOLA", "KAMTHI BASTI", "SCHOOL TOLA"]}, "KANJAI": {"KANJAI": ["BAGICHA TOLA", "GONDI TOLA", "INDIRA AWAS", "KALAG", "KANGAI BASTI", "NALA TOLA", "PARSA TOLA", "PIPAR TOLA", "SADAK TOLA"]}, "KANKI": {"KANKI": ["AWAS TOLA", "BANJARI TOLA", "DASHRA TOLA", "KANKI BASTI", "SCHOOL TOLA", "UPAJMANDI"]}, "KATANGJHARI": {"KATANGJHARI": ["BAZAR TOLA", "KATANGJHARI BASTI", "MARARI TOLA", "MINES TOLA", "NAHAR TOLA", "PATEL TOLA"]}, "KHAMIRIYA": {"KHAMARIYA": ["KHAMRIA BASTI"]}, "KHARI": {"KHARI": ["AWAS TOLA", "HIRA LAL TOLA", "KHARI BASTI", "MARTHA TOLA", "MEHAL TOL", "MUKDDAM TOLA"]}, "KHIRRI": {"KHIRRI": ["AWAS TOLA", "KHIRRI BASTI", "MARARI TOLA", "NADI TOLA", "PATEL TOLA"]}, "KHURPUDI": {"KHURPUDI": ["AWAS TOLA", "KHURPUDI BASTI", "NADI TOLA"]}, "KOPE": {"KOPE": ["AMRAI TOLA", "BUDHA TOLA", "KOPE BASTI", "PIPAR TOLA", "UDHAI TOLA"]}, "LANDEJHARI": {"LENDEJHARI": ["AWAS TOLA", "LANDEJHARI"]}, "LAWADA": {"LAWADA": ["GONDI TOLA", "LAWADA BASTI", "SADAK TOLA"]}, "LOHARA": {"LOHARA": ["DASRA TOLA", "LOHARA BASTI", "SHIVA TOLA"]}, "MANJHAPUR": {"MANJHAPUR": ["GONDI TOLA", "MANJHAPUR BASTI", "SAHU TOLA"]}, "MANPUR": {"MANPUR": ["MANDIR TOLA", "MANPUR BASTI", "SADAK TOLA"]}, "MIRAGAON": {"MIRAGAON": ["AWAS TOLA", "HADAH TOLA", "MIRAGAON BASTI", "SADAK TOLA", "SCHOOL TOLA"]}, "MIREGAON": {"MIREGAON": ["AWAS TOLA", "HADAH TOLA", "MIREGAON BASTI", "SADAK TOLA", "SCHOOL TOLA"]}, "MOHGAON (BORI)": {"BARGHAT": ["BARGHAT BASTI", "SCHOOL TOLA"], "MOHGAON": ["MANDIR TOLA", "MOHAGAON BASTI"]}, "MOHGAON (DHAPERA)": {"MOHGAON (DHA": ["AMRAI TOLA", "BHASNGA TOLA", "INDIRA AWAS", "KHONGA TOLA", "MOHGAON (DHAPERA) BASTI", "SURJA TOLA"]}, "MOHGAON JAM": {"MOHGAON JAM": ["AWASTOLA", "MOHGAON BASTI"]}, "MURJHAD": {"KAUDIYA": ["KAUDIYA BASTI", "MARARI TOLA", "PRADHAN TOLA", "SCHOOL TOLA"], "MURJHAD": ["AWAS TOLA", "GONDI TOLA", "MURJHAD BASTI"]}, "NAGPURA": {"NAGPURA": ["AWAS TOLA", "HALWA TOLA", "JABAL TOLA", "NAGPURA BASTI", "NAHAR TOLA", "NAKA TOLA"]}, "NATIRA": {"NAITRA": ["GONDI TOLA", "KOUDI TOLA", "MARGHAT TOLA", "NATIRA BASTI", "TEKADI TOLA"]}, "NEWARGAON": {"NEWARGAON": ["NEWARGAON"], "PONDI": ["AWAS TOLA", "NEW AWAS TOLA", "PONDI", "SADAK TOLA"]}, "NEWARGAON (WA)": {"NEWARGAON (WA)": ["GOPI TOLA", "NANGA TOLA", "NEWARGAON (WA) BASTI", "SALANG TOLA"]}, "NILJI": {"NILJI": ["BAJAR TOLA", "CHITAL TOLA", "HUDKI TOLA", "INDIRA AWAS", "KANHAR TOLA", "KATI TOLA", "KOSAM TOLA", "MARARI TOLA", "MEHKA TOLA", "NAJIM TOLA", "NILJI BASTI"]}, "PANBIHARI": {"PANBIHARI": ["AWAS TOLA", "BADI PANBIHARI BASTI", "CHHOTI PANBIHARI", "NAYA AWAS TOLA"]}, "PANDEWADA": {"PANDEWADA": ["BUDHA TOLA", "PANDEWADA BASTI", "SCHOOL TOLA"]}, "PANDHARWANI": {"PANDHARWANI": ["AMATOLA", "KATANG TOLA", "LALBURRA", "PANDHARWANI BASTI", "RAMJI TOLA", "SUNAR TOLA", "UDASI TOLA"]}, "PATHARI": {"PATHRI": ["AKHAR TOLA", "AWAS TOLA", "KHAIRTOLA", "PATHARI BASTI", "PHOGAL TOLA", "PUJARI TOLA", "SANJAY TOLA"]}, "PATHARSHAI": {"PATHARSAHI": ["AWAS TOLA", "KANHAR TOLA", "PATHARSHAI BASTI"]}, "PIPARIYA": {"PIPARIYA": ["CHOPAN TOLI", "ISHU TOLA", "KARU TOLA", "MARARI TOLA", "MARGHAT TOLA", "NEWARE TOLA", "PIPAR TOLA", "PIPARIYA (CH.) BASTI", "PIPARIYA BASTI", "VIRA TOLA"]}, "RAMPURI": {"GHATOLGAON": ["GHATOLGAON"], "RAMPURI": ["NADITOLA", "RAMPURI"]}, "RANIKUTHAR": {"DEOGAON": ["DEOGAON BASTI"], "GANKHEDA": ["GANKHEDA BASTI"], "PANDHRAPANI": ["GANESH TOLA", "LAL TOLA", "PANDARAPANI BASTI", "PATEL TOLA"], "RANIKUTHAR": ["BIJA TOLA", "GANESH TOLA", "RANI TOLA", "RANIKUTHAR BASTI"]}, "RATEGAON": {"KOSMI": ["BANGLA TOLA", "KOSMI BASTI"], "RATEGAON": ["RATEGAON BASTI"]}, "SALAI (MOHGAON)": {"SALHE": ["NARAYAN TOLA", "SALAI (MOHGAON) BASTI"]}, "SALHEL LA": {"KHAIRGONDI": ["KHAIRGONDI BASTI"], "SALHE": ["CHAMAN TOLA", "SALHE (LA) BASTI"]}, "SIHORA": {"SIHORA": ["RAJA TOLA", "SCHOOL TOLA", "SIHORA BASTI", "SIHORA TOLA"]}, "TEGANIKHURD": {"SALEBHARRI": ["AKHARTOLA", "GONDITOLA", "SALEBARRI BASTI"], "SALEBURRI": ["AKHAR TOLA", "GONDI TOLA", "SALEBARRI"], "TENGNI KHURD": ["TEGANI TOLA", "TEGANIKHURD BASTI"]}, "TEKADI": {"CHIKLAWARDI": ["BAIGA TOLA", "CHIKLAWARDI BASTI"], "NEWARGAON(LA": ["NEVEGAON BASTI", "SCHOOL TOLA"], "SILEJHARI": ["SILEJHARI BASTI"], "SONEWANI": ["REST HOUSE", "SONEWANI BASTI"], "TEKADI": ["JANGAL TOLA", "KATANG TOLA", "KHOL TOLA", "MARARI TOLA", "NAHAR TOLA", "PADAR TOLA", "PURAN TOLA", "TEKADI BASTI"]}, "TEKADI (LA)": {"CHIKHALABARD": ["BAIGA TOLA", "CHIKHLA BARDI BASTI"], "NAWEGAON": ["NAWEGAON BASTI", "SCHOOL TOLA"], "SILEJHARI": ["SILEJHARI BASTI"], "SONEWANI": ["SONEWANI BASTI"], "TEKADI": ["KATANG TOLA", "KEKADI (LA) BASTI", "MARARI TOLA", "PURAN TOLA", "TEKADI (LA) BASTI"]}, "TEKADI (LO)": {"TEKADI (LO) BASTI": ["JANGAL TOLA", "KHOL TOLA", "NAHAR TOLA", "PADAR TOLA", "TEKADI (LO) BASTI"]}, "TENGANI KALA": {"TENGNI KALAN": ["AWAS TOLA", "NEW AWAS TOLA", "TENGANI KALA BASTI"]}}, "LANJI": {"AMEDA (B)": {"AMEDA": ["AKHAR TOLA", "AMA TOLA", "AMEDA (B) BASTI", "AWAS TOLA", "BHAGAT TOLA", "NAHAR TOLA"], "THEMA": ["THEMA BASTI"]}, "AMEDA (P)": {"AMEDA": ["AMEDA (P) BASTI", "SCHOOL TOLA"]}, "ANDHIYA TOLA": {"ANDHIYATOLA": ["ANDHIYA TOLA BASTI", "AWAS TOLA"], "KATIPARKALAN": ["BEGIYA TOLA", "KATIPAR KALA BASTI"]}, "AWA": {"AWA": ["AWA BASTI", "NAKTA TOLA", "RAVIDAS NAGAR"], "CHOURLI": ["CHOURLI BASTI", "NAVIN AWAS"]}, "BADGAON": {"BADGAON": ["BADGAON BASTI", "CHHERKA TOLA", "GANESI TOLA", "VISHNU TOLA"]}, "BADGAON (MANARI)": {"BADGAON": ["MADGAON (MANARI)", "RAMATOLA"]}, "BAHELA": {"BAHELA": ["AWAS TOLA", "BAHELA BASTI", "DADWA TOLA", "MUNSHI TOLA", "NAYA TOLA", "PANCHAM TOLA"]}, "BALGAON": {"BALEGAON": ["BADPIRIT MOHALLA", "BALGAON BASTI", "PANDA TOLA"], "BIJAGARH": ["BAIGA TOLA", "BIJAGADH BASTI", "DALI TOLA"], "LODAMA": ["BAYGA TOLA", "LODAMAHA BASTI"], "MUNDIDADAR": ["MUNDIDADAR BASTI"]}, "BAMHANWADA": {"BAGHATOLA": ["AWAS TOLA", "BAKAYA TOLA", "BHAGHA TOLA BASTI", "NAYA TOLA", "PARSA TOLA", "TELI TOLA"], "BOMHANWADA": ["AWAS TOLA", "BAMHANWADA BASTI", "MAHAJAN TOLA", "MAHESH TOLA", "NAYA TOLA"]}, "BAPADI": {"BAPADI": ["AWAS TOLA", "BAPADI BASTI", "BASONA TOLA", "CHIKEN TOLA", "GOWARI TOLA", "JAMADAR TOLA", "LOHA TOLA", "MAHAJAN TOLA", "MAHAR TOLA", "PATEL TOLA", "SUKCHAIN TOLA"]}, "BENAGAON": {"BENAGAON": ["AWAS TOLA", "AWAS TOLA II", "BENAGAON BASTI", "SCHOOL TOLA"], "BENEGAON": ["AWAS TOLA", "AWASTOLA II", "BENAGAON BASTI", "BRAHMAN TOLA", "SCHOOL TOLA"]}, "BHANEGAON": {"BHANEGAON": ["AWAS TOLA", "BHANEGAON BASTI", "MARAR TOLA", "PIPAR TOLA", "TEKARI TOLA"]}, "BHIMODI": {"BHIMODI": ["AWAS TOLA", "BHIMODI BASTI", "MACHINE TOLA"]}, "BHURSA DONGARI": {"BHURSADONGAR": ["BHURSA DONGARI BASTI", "NAHAR TOLA", "SANKAR TOLA", "TELI TOLA"], "BORDI": ["BORDI BASTI", "TALAB TOLA"], "LOHARA": ["AWAS TOLA", "LOHARA BASTI", "PATEL TOLA", "SADAK TOLA", "UNDIR TOLA"]}, "BINJALGAON": {"BINJHALGAON": ["AWANITI CHOWK", "BINJALGAON BASTI", "SCHOOL TOLA"], "PONDI": ["AWAS TOLA", "PONDI BASTI"]}, "BIRANPUR": {"BIRANPUR": ["AWAS TOLA", "BAZAR TOLA", "BIRANPUR BASTI", "JWHAPADI TOLA", "KHIRHA TOLA", "NAYA TOLA", "SCHOOL TOLA"]}, "BISONI": {"BISONI": ["BISONI BASTI", "DHAKNI TOLA", "MANDAL TOLA"]}, "BOLEGAON": {"BOLEGAON": ["AWAS TOLA", "BOLEGAON BASTI", "MAHAJAN TOLA"]}, "BOTHALI": {"BOTHALI": ["BOTHALI BASTI", "MAHAJAN TOLA"]}, "CHICHOLI": {"CHICHEWADA": ["AWAS TOLA", "CHICHAWADA BASTI"], "CHICHOLI": ["CHICHOLI BASTI", "PATEL TOLA"]}, "CHIKHALI": {"CHIKHLI": ["CHIKHALI BASTI", "MAHAJAN TOLA"], "GORRA": ["GORRE BASTI"]}, "CHIKLAMALI": {"CHIKHALAMALI": ["CHIKLAMALI BASTI"]}, "DEHAGAON": {"DAHEGAON": ["AWAS TOLA", "DEHAGAON BASTI"], "KAREJA": ["KAREJA BASTI"]}, "DEVELGAON": {"DEWALGAON": ["DEVELGAON BASTI", "NAYA TOLA", "PARDHI TOLA"]}, "DEWARGALI": {"BARGUD": ["BARGUD BASTI", "KATRA", "SATONA"], "DEWARBELI": ["DEWARGALI BASTI"], "HARRADEHI": ["BHARRA DEHI", "HAMERA", "HARRADEHI BASTI", "KAMAHARDEHI", "KUMAHADEHI", "SANDUKA", "SAYAR", "SUJAN DEHI", "TEMNI"], "MALKUWA": ["MALKUWA BASTI"], "NALEJHARI": ["BAYGA TOLA", "NALEJHARI BASTI"], "NARPI": ["NARPI BASTI"]}, "DIGHORI": {"DIGHORI": ["DEVI TOLA", "DIGHORI BASTI", "MOHARAN TOLA"]}, "DONGERGAON": {"DONGARGAON": ["DONGERGAON BASTI", "DONGRI TOLA"]}, "DORLI": {"DORLI": ["AWAS TOLA", "DORLI BASTI", "TIKARI TOLA"]}, "DULAHAPUR": {"CHICHTOLA": ["CHICHTOLA BASTI", "NAYA TOLA", "SCHOOL TOLA"], "DULAPUR": ["AWAS TOLA", "CHIDI TOLA", "DULAHAPUR BASTI", "GIDHADI TOLA", "GOND TOLA", "PARSA TOLA", "WAKDA TOLA"]}, "FOFSA": {"BORIKHURD": ["BORI KHURD BASTI"], "KOPSA": ["KOPSA BASTI"]}, "GHANSA": {"GHANSA": ["GHANSA BASTI", "GONDI TOLA", "KATANG TOLA", "TELI TOLA", "TIM TOLA"], "KATANGI": ["KATANGI BASTI"]}, "GHOTI": {"GHOTI": ["GHOTI BASTI", "KACHAR TOLA"], "JUNEWANI": ["AWAS TOLA", "JUNEWANI BASTI"]}, "GHOTI GHUSMARA": {"GHOTI BHUSMARA": ["GHOTI GHUSMARA BASTI", "SCHOOL TOLA"]}, "KAKADI SONAR": {"KAKODI(SUNAR": ["KAKODI SONAR BASTI", "TINGLU TOLA"]}, "KALIMATI": {"KALIMATI": ["KALIMATI BASTI"]}, "KALPHATRI": {"KALPATHRI": ["BAJAR TOLA", "KALPHATRI BASTI"]}, "KANSOLI": {"BANJARTOLA": ["BANJARTOLA"], "DHARMARA": ["DHARMARA BASTI"], "GULPUR": ["GULPUR BASTI"], "KANSULI": ["GONDI TOLA", "GOWARI TOAL", "GOWARI TOLA", "KANSOLI BASTI", "KERA TOLA", "SONJHARI"], "KHANDWA": ["KANDHWA BASTI"], "MAHURKHODRA": ["MAHURKHODRA BASTI"], "SATONA": ["SATONA BASTI"]}, "KARANJA": {"KARANJA": ["AWARI TOLA", "BHARAT TOLA", "HALBI TOLA", "KARANJA BASTI", "SUI TOLA"]}, "KAREGAON": {"KEREGAON": ["GONDI TOLA", "KAREGAON BASTI", "SINGAL TOLA"]}, "KATANGI KALA": {"KATANGI KALA": ["KARU TOLA", "KATANGI KALA BASTI", "SCHOOL TOLA", "SINGAL TOLA"]}, "KHAJARI": {"ITORA": ["AWAS TOLA", "GOKUL TOLA", "ITORA BASTI", "SADAK TOLA"], "KHAJARI": ["AWAS TOLA", "GANESHY TOLA", "KHAJARI BASTI", "SADAK TOLA"]}, "KHANDAFARI": {"BAGDI": ["BAGADI BASTI", "NAYA TOLA"], "KAJALA": ["KAJALA"], "KARADI": ["KHARADI BASTI"], "KHANDAPHARI": ["AMAHA TOLA", "KHANDAFARI BASTI", "NAYA TOLA", "SALANG TOLA"], "PANDHARI": ["PANDARI BASTI"]}, "KHURSITOLA": {"BODALDALKHA": ["BODALDALKHA BASTI"], "DHIRI": ["BAYGA TOLA", "DHIRI BASTI", "RAMA TOLA", "TENDU TOLA"], "KHURSITOLA": ["ABADI TOLA", "KHURSITOLA BASTI"], "NASKATTA": ["NASKATTA BASTI", "TENDER TOLA"], "SARRASETI": ["SARASITI BASTI"], "SULSULI": ["KANAHAR TOLA", "POLICE CHOWKI", "SULSULI BASTI"], "WALEGAON": ["AWAS TOLA", "NAYA TOLA", "WALEGAON BASTI"]}, "KOCHEWAHI": {"KOCHEWAHI": ["KOCHEWAHI BASTI", "RAMU TOLA"]}, "KULPA": {"KULPA": ["BAGADI TOLA", "KULPA BASTI", "MADAN TOLA"]}, "KUMAHARI KALA": {"KUMHARIKALAN": ["KUMAHARI KALA BASTI", "TEKARI TOLA"]}, "KUMARI KHURD": {"JIWNARA": ["ADIWASI TOLA", "JEVNARA BASTI"], "KUMHARIKHURD": ["ADIWASI TOLA", "AWAS TOLA", "KUMARI KHURD BASTI"]}, "LADSA": {"LADSA": ["ABADI TOLA", "LADSA BASTI"]}, "LANJI": {"KASHITOLA": ["KASI TOLA BASTI"], "LANJI": ["AWAS TOLA", "BAKARA MUNDI", "LANJI BASTI", "NEEM TOLA", "SUNDER TOLA"]}, "MANARI": {"MANERI": ["KANARI", "MANARI BASTI"]}, "MIRIYA": {"MIRIYA": ["MIRIYA BASTI"], "TEKAPAR": ["TEKAPAR BASTI"]}, "MOHARA": {"MOHARA": ["AWAS TOLA", "GALA TOLA", "KADAM TOLA", "MARAR TOLA", "MOHARA BASTI"]}, "MOHJHARI": {"BORIKALAN": ["ADIWASI TOLA", "BORI BASTI", "GONDI TOLA", "SATI TOLA"], "MOHJHARI": ["BINJHWAR TOLA", "LABHANTOLA", "MARAR TOLA", "MOHJHARI BASTI", "PUJARI TOLA"]}, "NANDORA": {"BHANUTOLA": ["BAYGA TOLA", "BHANUTOLA BASTI"], "KADTA": ["KADTA BASTI"], "NANDORA": ["AWAS TOLA", "NANDORA BASTI", "NANDORA TOAL"]}, "NEWARWAHI": {"DEWALGAON": ["DEVELGAON"], "NEWARWAHI": ["KATANGTOLA", "KODAPPA", "KUTER", "NAKA TOLA", "NEWARWAHI BASTI", "PUJARI TOLA", "RAYALI"], "WARDHA": ["WARDHI BASTI"]}, "OTEKASA": {"OTEKASA": ["AWAS TOLA", "DOMA TOLA", "HALDI TOLA", "KANAR TOLA", "MAHAR TOLA", "OTEKASA BASTI", "TELI TOLA"]}, "PALDONGARI": {"PALDONGRI": ["BHAWANI TOLA", "NAGU TOLA", "PALDONGARI BASTI", "SCHOOL TOLA"]}, "PARASWADA": {"CHAUKITOLA": ["CHICHAMTOLA"], "PARASVADA": ["DHIMAR TOLA", "PARASWADA BASTI"]}, "PARSODI": {"PARSODI": ["AWAS TOLA", "DHIMAR TOLA", "GOWARI TOLA", "PARSODI BASTI", "TRANSFORMER TOLA"]}, "PATHARGAON": {"PATHARGAON": ["BAJAR TOAL", "GONDI TOLA", "JHINGU TOLA", "PATHARGAON BASTI"]}, "POWSARA": {"PAUSERA": ["DALKHA TOLA", "GANGI RAJA", "JAHARA TOLA", "LABHAN TOLA", "PHUNDARI TOLA", "POWSARA BASTI"]}, "PURVA TOLA": {"PURWATOLA": ["AWAS TOLA", "PATEL TOLA", "PURVA TOLA BASTI", "RANGNATH TOLA"]}, "RAMPURA": {"RAMPURA": ["BADE TOLA", "RAMPURA BASTI", "SCHOOL TOLA"], "SOGALPUR": ["SOGALPUR BASTI", "TIMKI TOLA"]}, "RESEWADA": {"CHOWKITOLA": ["CHOWKITOLA"], "KOSAMDHAI": ["BAIGA TOLA", "KOSAMDHAI BASTI", "MATA TOLA", "TENDA TOLA"], "RISEWADA": ["AWAS TOLA", "JAMUN TOLA", "RESEWADA BASTI"], "TATIKALAN": ["AMA TOLA", "CITIPALA", "POLICE CHOWKI", "SADAK TOLA", "TATIKALA BASTI"], "TIMKITOLA": ["TIMKITOLA"]}, "SADARA": {"SADRA": ["SADARA BASTI"]}, "SAHEKI": {"SAHEKI": ["BINJHHWAR TOLA", "SAHEKI BASTI"]}, "SARRA": {"SARRA": ["AWAS TOLA", "BHANDARI BASTI", "SARRA BASTI"]}, "SAVARI KALA": {"SAWARI": ["AWAS TOLA", "SAVARI KALA BASTI", "SAVARI TOLA"]}, "SEREGAON": {"KHARREGAON": ["ABADI TOLA", "KHAREGAON", "NAKTA TOLA"], "SIREGAON": ["NAYA TOLA", "SEREGAON BASTI"]}, "SHAVARI KHURD": {"SAWRI KHURD": ["ABADI TOLA", "ASOLI TOLA", "MAHAJAN TOLA", "SAVARI KHURD BASTI", "TEKARI TOLA"]}, "SIHARI": {"SIHARI": ["SIHARI BASTI"]}, "SINGOLA": {"SINGOLA": ["GHARI TOLA", "SADAK TOLA", "SINGOLA BASTI"]}, "TEDWA": {"TEDWA": ["AWAS TOLA", "BEDRYA TOLA", "MAHAJAN TOLA", "MILL TOLA", "TEDWA BASTI"]}, "TEKARI": {"MANPUR": ["DHILAD TOLA", "MANPUR BASTI"], "TEKRI": ["ABADI TOLA", "TEKARI BASTI"]}, "TEMNI": {"TEMNI": ["CHOUNDA TOLA", "DINA TOLA", "JUNEWANI", "TEMNI BASTI"]}, "THANEGAON": {"THANEGAON": ["THANEGAON BASTI"]}, "UMARI": {"UMARI": ["AWAS TOLA", "SHANKAR TOLA", "UMARI BASTI"]}, "WARI": {"WARI": ["MARAR TOLA", "PATEL TOLA", "TEKARI TOLA", "WARI BASTI"]}}, "PARASWADA": {"AMAWAHI": {"AMWAHI": ["AMWAHI", "BAIGA TOLA", "PATEL TOLA"], "BASI": ["BASI", "MUKDAM TOLA", "SADAK TOLA", "SAFARI TOLA", "SCHOOL TOLA"], "FANDKI": ["FANDKI", "GHASI TOLA", "PATEL TOLA"], "KESKLAI": ["AWAS TOLA", "KESKLAI"], "KURWAHI": ["KURWAHI"], "MANPUR": ["BHADU TOLA", "MANPUR", "TANDAN TOLA"]}, "ARANDIYA": {"ARANDIYA": ["ARANDIYA"]}, "BADGAON": {"BADGAON": ["BADGAON", "BAIGA TOLA", "NAKA TOLA"], "DORLI": ["CHAK TOLA", "DORLI"], "KATALBODI": ["KATALBODI"], "SALHE": ["SALHE"], "TIKARIYA (F.V.)": ["TIKARIYA (F.V.)"]}, "BAGHOLI": {"BAGHOLI": ["AWAS TOLA", "BAGHOLI", "INDIRA AWAS"]}, "BHIDI": {"BHIDI": ["AWAS TOLA", "BHIDI"]}, "BHIKEWADA": {"BHADUKOTA": ["BHADOKOTA"], "BHIKEWADA": ["BHIKEWADA (SCHOOL TOLA)", "LOHAR TOLA", "MUKUNANDI TOLA"], "KOSMI": ["AWAS TOLA", "KOSMI"]}, "BODA": {"BODA": ["AWAS TOLA", "BAIGA TOLA", "BAZAR TOLA", "BODA", "KATRA TOLA", "KURUMKHARI"]}, "CHALISBODI": {"CHALISBODI": ["ADIWASI MOHALLA", "CHALISBODI", "INDIRA  AWAS", "NAYATOLA"], "MATE (F.V.)": ["MATE (F.V.)"]}, "CHANDNA": {"CHANDNA": ["BAZAR TOLA", "CHANDNA", "JHALI TOLA", "SANTRI TOLA"]}, "CHHPARWAHI": {"CHHAPARWAHI": ["CHHAPARWAHI", "CHIKHLAJHODI", "SADAK TOLA"], "LOHUR PARASW": ["BAGATOLA", "LOUGUR (F.V.)", "UDGATI", "UDGHATI"], "TANTATOLA": ["BAIGA TOLA", "TANTATOLA", "THAKUR TOLA"]}, "CHINEE": {"CHINI": ["CHINEE", "GARPAGARI TOLA"]}, "DHANWAR": {"DHANWAR MAL": ["BAIGA TOLA", "DHANWAR THEKA", "JHADI TOLA", "PATEL"], "DHANWAR RYT.": ["DHANWAR RAIYAT"], "JHULUP": ["BAIGA TOLA", "JHULUP", "SANDA TOLA"], "NARNA": ["AWAS TOLA", "LOHAR TOLA", "NARNA", "PATEL TOLA"]}, "DONGARIYA": {"DONGARIYA": ["AWAS TOLA", "CHAKRI TOLA", "DONGARIYA", "LACCHITOLA"], "KUMANGAON": ["AWAS TOLA", "BIJA TOLA", "KHURITOLA", "KUMANGAON", "RAGHO TOLA"]}, "DUDGAON BAST": {"DUDGAON BAST": ["DUDGAON", "NAYA TOLA"]}, "FATEHPUR (MAL)": {"DALWADA": ["DALWADA", "PATEL TOLA"], "FATEHPUR RYT": ["FATEHPUR RAIYAT"], "FATEHPURTHEK": ["CHHINDI TOLA", "FATEPUR )MAL)"], "JALGAON": ["BAIGA TOLA", "JALGAON"], "KANARI": ["AMATOLA", "KANARI"], "KUKDA (F.V.)": ["KUKDA (F.V.)"], "VARUD GOTA (F.V.)": ["VARUD GOTA (F.V.)"]}, "GHODADEHI": {"GHODADEHI": ["BAIGA TOLA", "GHODADEHI", "PUJARI TOLA", "SCHOOL TOLA"], "LOTMARA": ["HARCHAND TOLA", "LOTMARA", "SCHOOL TOLA"]}, "GUDMA": {"GUDMA": ["DUGGALTOLA", "GUDMA", "GUDMA KEMP"]}, "HARRABHAT": {"CHHAPARA": ["CHHPARA"], "HARRABHAT": ["AWAS TOLA", "BAIGA TOLA", "HARRABHAT", "PARSA TOLA", "UMAR TOLA"], "SAHEJNA": ["MARAR TOLA", "SAHEJNA", "SEMAR TOLA"], "TARIGHAT": ["AWAS TOLA", "KAKRAJ PATH", "TATIGHAT"]}, "JAGANTOLA": {"GHONDI": ["GHONDI", "GHONDI CHHOTI"], "JAGANTOLA TH": ["JAGANTOLA"]}, "JHANGUL BAST": {"JHANGUL BAST": ["ADIWASI TOLA", "AWAS TOLA", "JHANGUL", "MOTI TOLA"]}, "JHIRIYA": {"DHIPUR RYT.": ["DHIPUR"], "JHIRIYA": ["BAIGA TOLA", "JHIRIYA", "JHIRIYA TOLA"], "KHURSITOLA": ["KHURSITOLA"], "PATORA": ["PATORA"]}, "KANAI": {"KANAI": ["BARRA TOLA", "KANAI", "MARAR TOLA", "SCHOOL TOLA"]}, "KAWELI": {"BODALBAHRA": ["BODALBEHRA", "CHHPURTOLA"], "KAWELI": ["KATANGTOLA", "KAWELI", "PATEL TOLA", "PUJARI TOLA"], "KODKA": ["KUKDA"], "LATTA MAL.": ["LATTA (F.V.)"], "PALAGONDI (F.V.)": ["BAIGA TOLA", "PALAGONDI (F.V.)"]}, "KHAIRLANJI": {"CHANDIYA RYT": ["CHANDIYA", "KURSI TOLA", "SCHOOL TOLA", "USARI TOLA"], "KHAIRLANJI": ["KHAIRLANJI RAIYAT"], "KHAIRLANJI R": ["PARDHI TOLA", "PATEL TOLA", "THAIRLANJI THEKA"], "SURWAHI": ["BAIGA TOLA", "SURWAHI"]}, "KHALONDI": {"CHANAI MAL.": ["CHANAI MAL"], "CHANAI RYT.": ["CHANAI RAIYAT"], "KHALONDI": ["DALKHA TOLA", "KATANG TOLA", "KHALONDI", "THAKUR TOLA"]}, "KHARPADIYA": {"KHARPADIYA": ["AWAS TOLA", "KHARPADIYA"]}, "KHURMUNDI": {"JHARAKHEDA": ["JHARKHEDA"], "KHURMUNDI": ["JAMUN TOLA", "KHURMUNDI", "SADAK TOLA", "SAMTA TOLA", "SCHOOL TOLA"], "SINGHODI BAS": ["SINGODI"]}, "KHURSUD (RAIYAT)": {"BIJORA MAL.": ["BIJORA"], "GAUNAJHOLA": ["GOUNAJHOLA"], "JAITPURI THE": ["JAITPURI"], "RHURSUD RAIYAT": ["KHURSUD", "PUJARITOLA"], "SALFA PARASW": ["SALFA (F.V.)"]}, "KORJA": {"DALWADA": ["DALWADA", "PATEL TOLA"], "GARARIBAHERA": ["DARARIBAHERA"], "KORJA": ["AWAS TOLA", "CHARTOLA", "GOLAR TOLA", "KORJA"]}, "KUMADEHI": {"KALEGAON": ["BAIGA TOLA", "KALEGAON"], "KUMADEHI": ["PATEL TOLA", "SALANG TOLA", "SCHOOL TOLA"], "PARRAPUR": ["PARRAPUR"]}, "KURENDA": {"KURENDA": ["AWAS TOLA", "BARRA TOLA", "KURENDA", "LABHAN TOLA"]}, "LAGAMA": {"KONDUL (F.V.)": ["KUNDUL (F.V.)"], "LAGMA": ["CHHINDI TOLA", "LAGMA"], "PINDKAPAR": ["PINDKEPAR", "SUNDARWAHI"], "RAJPUR  RYT.": ["RAJPUR MAL"], "RAJPUR THEKA": ["RAJPUR RAIYAT"]}, "LILAMETA": {"KHAMARIYA": ["KHAMARIYA"], "LILAMETA": ["AMATOLA", "BADHAI TOLA", "FOGALPUR", "KANAI TOLA", "LILAMETA"]}, "LINGA": {"BHORWAHI": ["BHORWAHI", "THAKUR TOLA"], "LINGA": ["LINGA"]}, "MAJHGAON": {"DANUTOLA": ["DHANU TOLA", "SARAI TOLA"], "MAJGAON MAL.": ["MAJHGAON", "PANDA TOLA"], "MAJGAON RYT.": ["MAJGAON RAIYAT"], "SADAR": ["HUDDI TOLA", "SADA"], "TIRGAON": ["AWAS TOLA", "DHANU TOLA", "TIRGAON"]}, "MOHANPUR": {"IRALI RYT.": ["IRALI RAIYAT"], "KANHATOLA": ["BAIGA TOLA", "KANHATOLA", "TARTOLA"], "KULPA MAL.": ["KULPA MAL"], "KULPA RYT.": ["KULPA RAIYAT"], "MOHANPUR": ["MOHANPUR"], "SONEWANI": ["BAIGATOLA", "SONEWANI"], "SUKALDAND": ["SUKALDAND"], "USKALACHAK": ["USKALCHAKRA"]}, "MOHGAON": {"AHAMADPUR": ["AHMADPUR"], "MOHGAON": ["MOHGAON", "SITA TOLA"], "SAWAR ?JODHI": ["SAWARJHODI"]}, "MOHGAON ( PATELI)": {"KESHA": ["KESA"], "KIDANGITOLA": ["KIDGITOLA"], "MOHGAON PATE": ["MOHGAON PATELI"], "MOHGAON(R)": ["MOHGAON RAIYAT"], "NAGJHOLA": ["KAPUR TOLA", "NAGJHOLA"]}, "NATA": {"BARIYA": ["BARIYA", "MUNNU TOLA", "NARWARI TOLA"], "DANDAIJHOLA": ["DANDAIJHOLA"], "NATA": ["BIJATOLA", "GANNA TOLA", "MALI TOLA", "NAKA TOLA", "PANDA TOLA", "PATEL TOLA", "TALAB TOLA"]}, "PARASWADA": {"PARASWADA": ["ADIWASITOLA", "BIJATOLA", "PARASWADA"], "SERPAR": ["HARI TOLA", "INDRA AWAS", "SHERPAR"]}, "PARSATOLA": {"BHILEWANI": ["BHILEWANI"], "CHAREGAON": ["BANJAR TOLA", "CHAREGAON", "KHURSI TOLA", "PATEL TOLA"], "KASHMIRI": ["AWAS TOLA", "KASHMIRI"], "PARSATOLA": ["PARSATOLA"]}, "PONDI": {"PONDI": ["AWAS TOLA", "PONDI", "RESHAM TOLA"]}, "PONGARJHODI": {"BHADA MAL.": ["BHADA MAL", "IMALI TOLA", "MARARI TOLA", "PATEL TOLA"], "BHAMODI MAL.": ["BHIMODI MAL"], "BHAMODI RYT.": ["BHIMODI RAIYAT"], "PONGARJHODI": ["PONGARJHODI", "TIKRATOLA"]}, "RUPJHAR": {"BALARAM PETH": ["BALRAMPETH"], "DINATOLA": ["DINATOLA"], "GODARITOLA": ["BAIGATOLA", "GODADITOLA"], "HUDDITOLA": ["HUDDITOLA"], "RUPJHAR": ["LAXMAN TOLA", "RUPJHAR"]}, "SAHEJANA BAS": {"SAHEJANA BAS": ["MARAR TOLA", "PANKA TOLA", "SAHEJNA"]}, "SAILA": {"GHANA": ["GHANA"], "KHAPA": ["BAIGA TOLA", "BAJRANG TOLA", "BIGARI TOLA", "KHAPA"], "MALKHEDI": ["BUDDHU TOLA", "MALKHEDI"], "MOHGAON": ["BAIGA TOLA", "MOHGAON", "SARAI TOLA", "SARPANCH TOLA"], "SAILA": ["BAIGA TOLA", "SAILA"]}, "SAMNAPUR": {"KHANDAPAR  R": ["KHANDAPAR"], "SAMNAPUR": ["GOWARITOLA", "NAI TOLA", "POARI TOLA", "SAMNAPUR"]}, "SAREKHA": {"SAREKHA": ["BAIGA TOLA", "HARIJAN TOLA", "JHODI TOLA", "NAYA TOLA", "SAREKHA"]}, "SILAGI": {"BODALJHOLA": ["BANJAR TOLA", "BODALJHOLA", "GOVARS TOLA"], "DHURWA": ["DHURWA"], "SILGI": ["GADHEWAL TOLA", "KANHAR TOLA", "SILAGI"]}, "SINGHAI": {"DORA": ["DORA"], "KHUDDIPUR": ["KHUDDIPUR"], "SINGHAI": ["BAPU TOLA", "SINGHAI"]}, "SITADONGARI": {"MADANPUR BAS": ["AMA TOLA", "BARRA TOLA", "GITTI TOLA", "MADANPUR"], "SITADONGRI": ["GONDI TOLA", "KHARI TOLA", "KIDKA TOLA", "SITADONGARI"]}, "SUKADI": {"KHAPAKHEDA": ["KHAPARKHEDA"], "KHARRA": ["AWAS TOLA", "KHARRA"], "SUKADI": ["NAHAR TOLA", "SUKADI", "TALAB TOLA"]}, "THEMA": {"KHUDURGAON": ["MARARI TOLA", "SUDURGAON"], "THEMA": ["AWAS TOLA", "BAJAR TOLA", "CHHINDI TOLA", "THEMA"]}, "TIKARIYA": {"BAIGANAGRI": ["BAIGA TOLA", "BAIGANAGRI"], "DENDWA": ["BAIGA TOLA", "DENDWA"], "SALGHAT": ["CHARTOLA", "DADU TOLA", "SALGHAT"], "TIKARIYA": ["SARAI TOLA", "TIKARIYA"]}, "UKWA": {"UKWA": ["DUGGAL TOLA", "PANI TOLA", "UKWA", "UKWA KEMP"]}, "UMARIYA": {"UMARIYA": ["ADIWASI MOHALLA", "AMRU TOLA", "UMARIYA"]}, "URADNA": {"KATANGA": ["KATANGA"], "URADNA": ["GONDI TOLA", "URADNA"]}}, "WARASEONI": {"AKODI": {"AKODI": ["AKODI BASTI", "BISI TOLA", "DANDU TOLA", "DASHRA TOLA", "PUSHU TOLA", "UMAR TOLA"]}, "ALAJHARI": {"ALEJHARI": ["ALAJHARI BASTI", "BHIM NAGAR", "CHANDRA NAGAR", "SALANG TOLA", "SCHOOL TOLA"], "RAJEGAON": ["BHIM NAGAR", "HUDKI TOLA", "RAJEGAON BASTI"]}, "ANSERA": {"ANSERA": ["ANSERA BASTI", "BAZAR TOLA", "CHIK TOLA", "GONDI TOLA", "SINGAL TOLA"], "KHADAKPUR(HA": ["KHADGPUR BASTI"]}, "BAGHOLI": {"BAGHOLI": ["BAGHOLI BASTI", "HIRA TOLA"]}, "BAKERA": {"BAKERA": ["BAKERA BASTI"]}, "BASI": {"BASI": ["BASI BASTI", "GONDI TOLA"], "POUNERA": ["POUNERA BASTI"]}, "BHANDI": {"BHANDI": ["AWAS TOLA", "BAGADMARA TOLA", "BHANDI BASTI", "BHANDI TOLA", "HUDKI TOLA", "LAXMAN TOLA"], "KERA": ["KERA BASTI", "NAKA TOLA"]}, "BODALKASA": {"BODALKASA": ["BODALKASA BASTI", "GONDI TOLA"]}, "BOTEJHARI": {"BOTEJHARI": ["AMIR TOLA", "AMRAT TOLA", "AWAS TOLA", "BAJIRA BAD TOLA", "BOTEJHARI BASTI", "GONDI TOLA", "KANHAR TOLA", "KHADAN TOLA", "MARARI TOLA"]}, "BUDBUDA": {"BUDBUDA": ["BUDBUDA BASTI", "DHANI TOLA", "DHOBI TOLA", "HUDKI TOLA", "MATA TOLA", "NADI TOLA", "SARAI TOLA"]}, "CHANGERA": {"CHANGERA": ["CHANGERA BASTI", "PATHAN TOLA"], "KHURSIPAR": ["KHURSIPAR BASTI"], "TUIYAPAR": ["GOVIND PUR", "TUIYAPAR BASTI"]}, "DEVEGAON": {"DEOGAON": ["DEVGAON BASTI"]}, "DINERA": {"DINERA": ["AWAS TOLA", "DINERA BASTI", "KIDGI TOLA", "MILAN TOLA"], "MURMADI": ["MURMADI BASTI", "SUNDAR TOLI"]}, "DINI": {"DINI": ["DINI BASTI", "SCHOOL TOLA"]}, "DOKE": {"DOKE": ["DOKE BASTI", "HUDKI TOLA"]}, "DONGARGAON": {"DONGARGAON": ["DONGARGAON BASTI", "SHIV NAGAR"], "MAHARAJPUR": ["BANJARI TOLA", "MAHARAJPUR BASTI", "PARSA TOLA"]}, "DONGARMALI": {"DONGARMALI": ["AWAS TOLA", "DONGARMALI BASTI", "INDIRA AWAS", "PURSODI", "UDASI TOLA"]}, "DORLI (MAL)": {"DORLI(JADKHA": ["DORLI (JAD) BASTI"], "DORLI(MALGUJ": ["BADA TOLA", "BAGRANJ TOLA", "DORLI (MAL) BASTI", "GONDI TOLA", "SAIYAN TOLA", "SHIV TOLA"]}, "GARRA": {"GARRA": ["AWAS TOLA", "BRAMHAN TOLA", "GANDHI CHOWK TOLA", "GARRA BASTI", "NAHAR TOLA", "PAWAR TOLA"]}, "GATAPAYLI": {"GATAPAYALI": ["AWAS TOLA", "DOMA TOLA", "GATAPAYLI BASTI"]}, "JAGPUR": {"JAGPUR": ["AWAS TOLA", "CHHINDI TOLA", "HARIJAN TOLA", "JAGPUR BASTI"]}, "JHALIWADA": {"JHALIWADA": ["JHALIWADA BASTI", "MAHU TOLA", "MIRCHI TOLA"]}, "JHARGAON": {"JHADGAON": ["JAIGUN TOLA", "JHARGAON BASTI", "SAIJA TOLA"]}, "KASPUR": {"KASPUR": ["AAMA TOLA", "AKHAR TOLA", "KASPUR BASTI", "MATA TOLA"]}, "KAULIWADA": {"KAULIWADA": ["KAULIWADA BASTI"]}, "KAYDI": {"KAYDI": ["BANIA TOLA", "CHHOTA TOLA", "INDIRA COLONY", "JODA PATH", "KAYDI BASTI"]}, "KHANDWA": {"KHANDWA": ["DAYAL TOLA", "KHANDWA BASTI"]}, "KHAPA": {"KHAPA": ["GONDI TOLA", "KHAPA BASTI"]}, "KOCHEWAHI": {"KOCHEWAHI": ["AKHAR TOLA", "BAJAR TOLA", "BANDAL TOLA", "INDIRA AWAS", "KOCHEWAHI BASTI", "MAHARAJ PUR TOLA", "MARARI TOLA", "NADI TOLA", "NATHA TOLA", "PUJARI TOLA", "SALANG TOLA"]}, "KOSTE": {"KOSTE": ["KOSTE BASTI", "MANDAI TOLA", "SADAK TOLA"]}, "LADSADA": {"LADSADA": ["AWAS TOLA", "BHIVLI TOLA", "LADSADA BASTI", "MATA TOLA", "PUJARI TOLA"]}, "LALPUR": {"LALPUR": ["AWAS TOAL", "LALPUR BASTI"]}, "LINGMARA": {"LINGMARA": ["HEATAI TOLA", "KALARI TOLA", "LINGMARA BASTI", "RAM TOLI"]}, "MADANPUR": {"MADANPUR": ["KADAM TOLA", "MADANPUR BASTI"]}, "MANGEJHARI": {"MANGEJHARI": ["BADRI TOLA", "BALIPATH TOLA", "DAKAL TOLA", "JAIRAM TOLA", "JHADU TOLA", "KALA GOTA TOLA", "MALAM TOLA", "MANGEJHARI BASTI", "SALAI TOLA", "SCHOOL TOLA"]}, "MEHDULI": {"MAHEDULI": ["MEHDULI BASTI", "SUNDAR TOLI"]}, "MEHNDIWADA": {"MEHANDIWADA": ["GONDI TOLA", "MEHNDIWADA BASTI"]}, "MENDKI": {"MENDKI": ["LODHI TOLA", "MENDKI BASTI", "PAWARI TOLA", "PIPAR TOLA", "PREM NAGAR"]}, "MOHGAON (KHURD)": {"BITHALI": ["BITHALI BASTI"], "MOHGAON KHUR": ["CHHATAR PUR TOLA", "MOHGAON (KHURD) BASTI"]}, "MURJHAD": {"MURJHAD": ["KOSRI TOLA", "MURJHAD BASTI", "SENWA TOLA"]}, "NANDGAON": {"NAGJHAR": ["CHAMARI TOLA", "DEVI TOLA", "MARARI TOLA", "NAGJHAR BASTI"], "NANDGAON": ["AWAS TOLA", "BEECH TOLA", "DHOBI TOLA", "MARARI TOLA", "NANDGAON BASTI"]}, "NARODI": {"NARODI": ["AKHAR TOLA", "BHAGWAT TOLA", "LUKKU TOLA", "NARODI BASTI", "SARAI TOLA", "SUKKU TOLA"], "NARWANJPAR": ["ABDULLA TOLA", "DEEMAR TOLA", "GONDI TOLA", "KARIYA TOLA", "NARWANJPAR BASTI"]}, "PADAMPUR": {"AMGAON": ["AMGAON BASTI"], "BARBASPUR UR": ["AWAS TOLA", "BARBASPUR BASTI"], "PADAMPUR": ["AWAS TOLA", "PADAMPUR BASTI"]}, "PIPARIYA": {"PIPARIYA": ["AWAS TOLA", "ENKA TOLA", "HUDKI TOLA", "KHAPRAIL TOLA", "OOJHA TOLA", "PIPARIYA BASTI"]}, "PUNI": {"PUNI": ["PUNI TOLA"]}, "RAMPALAYI": {"RAMPAYLI": ["GONDI TOLA", "KASBI TOLA", "RAMPAYALI BASTI"]}, "RAMRAMA": {"RAMRAMA": ["BADAKAMP", "C.P.P.O.", "MARARI TOLA", "MINES", "PENDI TOLA", "PURANI DAFAI", "RAMRAMA BASTI"]}, "RANGAJHARI": {"RENGAJHARI": ["RANGAJHARI BASTI"]}, "RENGATOLA": {"RENGATOLA": ["RENGATOLA BASTI"]}, "SARANDI": {"SARANDI": ["KANCHANPUR", "SARANDI BASTI"]}, "SAWANGI": {"SAWANGI": ["AWAS TOLA", "GONDI TOLA", "GOPI TOLA", "SAWANGI BASTI", "TUMDI TOLA"]}, "SHERPAR": {"SERPAR": ["BAJRANG TOLA", "DEEMAR TOLA", "HANUMAN TOLA", "MAIDA TOLA", "NAKA TOLA", "RLY. TOLA", "SHERPAR BASTI"]}, "SIKANDRA": {"SIKANDRA": ["NADI TOLA", "SIKANDRA BASTI", "UDHAI TOLA"]}, "SINGODI": {"KATANGTOLA": ["KATANGTOLA BASTI"], "SINGODI": ["SINGODI BASTI"]}, "SIRRA": {"SIRRA": ["BADA TOLA", "JAIRAM TOLA", "KATIYA TOLA", "SARAI TOLA", "SIRRA BASTI", "UDASI TOLA"]}, "SONJHARA": {"JABARTOLA": ["JABARTOLA BASTI"], "SONJHARA": ["SONJHARA BASTI"]}, "THANEGAON": {"THANEGAON": ["CHOPAN TOLA", "GARRA TOLA", "KALAGOTA", "KARYA TOLA", "SIRRA TOLA", "THANEGAON BASTI"]}, "TUMADI": {"TUMADI": ["TUMADI BASTI"]}, "UMARWADA": {"UMARWADA": ["UMARWADA BASTI"]}, "WARA": {"WARA": ["GONDI TOLA", "SHIVNAGAR", "WARA BASTI"]}}}