{"DAMBO RONGJENG": {"ANCHENGBOK": {"ANCHENGBOK": ["ANCHENGBOK"]}, "ARAGITTIM": {"ARAGITTIM": ["ARA", "ARAGITTIM"]}, "ASIM AGAL": {"ASIM AGAL": ["ASIM AGAL"]}, "AWAKEGITTIM": {"AWAKEGITTIM": ["AWEKGITTIM"]}, "AWANGGA": {"AWANGGA": ["AWANGGA"]}, "BARINGGRE BOLKRET": {"BARINGGRE BOLKRET": ["BARINGGRE BOLKRET"]}, "BARINGGRE CHAMBILDAM": {"BARINGGRE CHAMBILDAM": ["BARINGGRE CHAMBILDAM"]}, "BARINGGRE NOKAT": {"BARINGGRE NOKAT": ["BARINGGRE NOKAT"]}, "BARINGGRE WADRO": {"BARINGGRE WADRO": ["BARINGGRE WADRO"]}, "BLOCK CAMPUS": {"BLOCK CAMPUS": ["BLOCK CAMPUS"]}, "BODILPA APAL": {"BODILPA APAL": ["BADILPA APAL"]}, "BOLONG GITTIM": {"BOLONG GITTIM": ["BOLSALGITTIM", "RONGMIL"]}, "BOLSALGITTIM": {"BOLSALGITTIM": ["BOLSALGITTIM"]}, "CHEJONG AKONG": {"CHEJONG AKONG": ["CHIJONG AKONG"]}, "CHERAN ALDA": {"CHERAN ALDA": ["CHERAN ALDA"]}, "CHERAN CHIKOL": {"CHERAN CHIKOL": ["CHERAN CHIKAL"]}, "CHERAN SONGGITAL": {"CHERAN SONGGITAL": ["CHERAN SONGGITAL"]}, "CHERAN SONGGITCHAM": {"CHERAN SONGGITCHAM": ["CHERAN SONGGITCHAM"]}, "CHI-KAMA": {"CHI-KAMA": ["CHIKAMA"]}, "CHIBILBANG": {"CHIBILBANG": ["CHIBILBANG"]}, "CHICHRA APAL": {"CHICHRA APAL": ["CHICHRA APAL"]}, "CHIGISIM BISIKGITTIM": {"CHIGISIM BISIKGITTIM": ["CHIGISIM BISIKGITTIM"]}, "CHIGISIM GITTIM": {"CHIGISIM GITTIM": ["CHISIMGITTIM"]}, "CHIGROSONGGITAL": {"CHIGROSONGGITAL": ["CHIGRO SONGGITAL"]}, "CHIJONG GITTIM": {"CHIJONG GITTIM": ["CHIJONGGITTIM"]}, "CHIKAL SONGMA": {"CHIKAL SONGMA": ["CHIKOL SONGMA"]}, "CHIKOL DAWA": {"CHIKOL DAWA": ["CHIKOL DAWU"]}, "CHIKOL PEGRO": {"CHIKOL PEGRO": ["CHIKOL PEKRO"]}, "CHIRING DOKRU": {"CHIRING DOKRU": ["CHIRING DOKRUGITTIM", "CHRISTIANPARA", "NOKMAGITTIM"]}, "CHITIL APAL": {"CHITIL APAL": ["CHITIL APAL"]}, "DABITGITTIM": {"DABITGITTIM": ["DABITGITTIM"]}, "DAGAL -DOGRU": {"DAGAL -DOGRU": ["DAGAL DOGRU"]}, "DAGAL BOLLONGGITIM": {"DAGAL BOLLONGGITIM": ["BOLLONGGITTIM"]}, "DAGAL BOLMEDANG": {"DAGAL BOLMEDANG": ["DAGAL BOLMEDANG"]}, "DAGAL GADING": {"DAGAL GADING": ["DAGAL GADING"]}, "DAGAL NOKAT": {"DAGAL NOKAT": ["DAGAL NOKAT"]}, "DAGAL SIMSENG": {"DAGAL SIMSENG": ["DAGAL BOLKRET", "DAGAL SIMSENG"]}, "DAKRAM": {"DAKRAM": ["DAKRAM"]}, "DAMBO BIMA": {"DAMBO BIMA": ["DAMBO BIMA"]}, "DAMBO CHAREGITTIM": {"DAMBO CHAREGITTIM": ["DAMBO CHAREGITTIM"]}, "DAMBO GITONGGITTIM": {"DAMBO GITONGGITTIM": ["DAMBO GITTONGGITTIM"]}, "DAMBO MROK": {"DAMBO MROK": ["DAMBO MROK"]}, "DAMBO RESERVE -I": {"DAMBO RESERVE -I": ["DAMBO RESERVE-I"]}, "DAMBO RESERVE -II": {"DAMBO RESERVE -II": ["DAMBO RESERVE-II"]}, "DAMBO RONGDENG": {"DAMBO RONGDENG": ["DAMBO RONGDENG"]}, "DAMBO WARIKADA": {"DAMBO WARIKADA": ["DAMBO WARIKADA"]}, "DAMBO WATESA": {"DAMBO WATESA": ["DAMBO WATESA"]}, "DANAL SURE GITTIM": {"DANAL SURE GITTIM": ["DANAL SUREGITTIM"]}, "DARUGIRI": {"DARUGIRI": ["DARUGRE"]}, "DARUGIRI RESERVE": {"DARUGIRI RESERVE": ["DARUGRE RESERVE"]}, "DARUSAK": {"DARUSAK": ["DARUSAK"]}, "DATANG AGAL": {"DATANG AGAL": ["DATANG AGAL"]}, "DAWA SONGGITAL": {"DAWA SONGGITAL": ["DAWA SONGGITAL"]}, "DIPLOKGITTIM": {"DIPLOKGITTIM": ["DIPLOK APAL", "DIPLOKGITTIM"]}, "DIPLOKGITTIM SONGMA": {"DIPLOKGITTIM SONGMA": ["DIPLOK APAL", "DIPLOKGITTIM SONGMA"]}, "DOGEP GIPURAM": {"DOGEP GIPURAM": ["DOGEPGIPURAM"]}, "DOMBU GITTIM": {"DOMBU GITTIM": ["DOMBUGITTIM"]}, "DOMBU TERACEGITTIM": {"DOMBU TERACEGITTIM": ["DAMBU TERCEGITTIM"]}, "DUADUGITTIM": {"DUADUGITTIM": ["DUADUGITTIM"]}, "GABIL ADING": {"GABIL ADING": ["GABIL ADING", "GABIL AKONG"]}, "GABIL BISA": {"GABIL BISA": ["GABIL BISA", "GABIL BISA SONGGITAL"]}, "GABIL BOLDIL": {"GABIL BOLDIL": ["GABIL BOLDILGITTIM"]}, "GABIL DANINGKA": {"GABIL DANINGKA": ["GABIL DANINGKA", "GABILGITTIM"]}, "GABIL GANDUAL": {"GABIL GANDUAL": ["GANDUAL", "GANDUALA"]}, "GABIL KOKSI": {"GABIL KOKSI": ["GABIL KOKSIGITTIM"]}, "GABIL KOKSIGITTIM": {"GABIL KOKSIGITTIM": ["GABIL KOKSIGITTIM"]}, "GABIL NENGTEK": {"GABIL NENGTEK": ["GABIL NENGBREK"]}, "GABIL NENGTEKGITTIM": {"GABIL NENGTEKGITTIM": ["GABIL NENGTEKGITTIM"]}, "GABIL PATTAL": {"GABIL PATTAL": ["GABIL AKONG", "GABIL PATTAL"]}, "GINDILGITTIM": {"GINDILGITTIM": ["GINDILGITTIM"]}, "GOBEKRAM": {"GOBEKRAM": ["GOBERAM"]}, "HASLONG": {"HASLONG": ["HASLONG"]}, "IMSAMDROP": {"IMSAMDROP": ["IMSAMDROP"]}, "IMTRA APAL": {"IMTRA APAL": ["I.B. GITTIM", "IMTRAGITTIM"]}, "JALWAGRE ASOKAGITTIM": {"JALWAGRE ASOKAGITTIM": ["JALAWAGRE KAMA", "JALWAGRE ASOKAGITTIM"]}, "JALWAGRE SONGGITCHAM": {"JALWAGRE SONGGITCHAM": ["JALWAGRE SONGGITCHAM"]}, "JALWAGRE SONGITAL": {"JALWAGRE SONGITAL": ["JALWAGRE SONGGITAL"]}, "JAMBAL RONGSIL": {"JAMBAL RONGSIL": ["JAMBAL RONGSIL"]}, "JAMBALGITTIM": {"JAMBALGITTIM": ["RONGJENG JAMBALGITTIM"]}, "KAKDAP": {"KAKDAP": ["KAKDAP"]}, "KANCHIJAGITTIM": {"KANCHIJAGITTIM": ["KANCHIJAGITTIM"]}, "MANGSANG BABUPARA": {"MANGSANG BABUPARA": ["MANGSANG BABUPARA"]}, "MANGSANG BAMIL": {"MANGSANG BAMIL": ["MANGSANG BAMIL"]}, "MANGSANG BEKGITOGITTIM": {"MANGSANG BEKGITOGITTIM": ["MANGSANG BEKGITOKGITTIM"]}, "MANGSANG DOSIK GITTIM": {"MANGSANG DOSIK GITTIM": ["MANGSANG DOSIKGITTIM"]}, "MANGSANG MOGOGITTIM": {"MANGSANG MOGOGITTIM": ["MANGSANG MOGOGITTIM"]}, "MANGSANG RONGGISIM": {"MANGSANG RONGGISIM": ["MANGSANG RONGGISIM"]}, "MARI APAL": {"MARI APAL": ["MARI APAL"]}, "MEJOLGRE AMEBANG": {"MEJOLGRE AMEBANG": ["AMEBANG"]}, "MEJOLGRE CHEKJONGBRA": {"MEJOLGRE CHEKJONGBRA": ["MEJOLGRE CHEKCHUMBRA"]}, "MEJOLGRE DOGRU": {"MEJOLGRE DOGRU": ["MEJOLGRE APAL", "MEJOLGRE DOGRU"]}, "MEJOLGRE NOKAT": {"MEJOLGRE NOKAT": ["MEJOLGRE APAL", "MEJOLGRE SONGMA"]}, "MEJOLGRE WANCHO": {"MEJOLGRE WANCHO": ["MEJOLGRE WANCHO"]}, "MICHIMRAN": {"MICHIMRAN": ["MICHIMRAM"]}, "MIKTONGJENG": {"MIKTONGJENG": ["MIKTOKJENG"]}, "MILLAWAE": {"MILLAWAE": ["MILAWE"]}, "MISSION CAMPUS": {"MISSION CAMPUS": ["MISSION CAMPUS"]}, "MOKURA": {"MOKURA": ["MANGSANG MOKURA"]}, "MONGRU": {"MONGRU": ["MOGRU"]}, "NAGIRAM": {"NAGIRAM": ["NAGUMARAM"]}, "NARINGGIRI": {"NARINGGIRI": ["NARINGGIRI"]}, "NENGBRET": {"NENGBRET": ["NENGBRET"]}, "NENGBROK": {"NENGBROK": ["NENGBROK"]}, "NENGKRAM": {"NENGKRAM": ["HOSPITAL AREA", "NENGKHRAM"]}, "NENGPATCHI": {"NENGPATCHI": ["NENGPATCHI"]}, "NENGRING GITTIM": {"NENGRING GITTIM": ["NENGRIMGITTIM"]}, "NENGSIL": {"NENGSIL": ["NENGSIL"]}, "NONGBAK ADING": {"NONGBAK ADING": ["NONGBAK ADING"]}, "NONGBAK AGALGRE": {"NONGBAK AGALGRE": ["NONGBAK AGALGRE"]}, "NONGBAK APAL": {"NONGBAK APAL": ["CHURCHGITTIM", "NONGBAK APAL"]}, "NONGBAK DARAM": {"NONGBAK DARAM": ["NONGBAK DARAM"]}, "NONGCHRAM - I": {"NONGCHRAM - I": ["NONGCHRAM-I"]}, "NONGCHRAM DOADU GITTIM": {"NONGCHRAM DOADU GITTIM": ["NONGCHRAMII"]}, "NONGKONGKIL": {"NONGKONGKIL": ["NONGKANGKIL"]}, "PAKGREGRE DADONGGITTIM": {"PAKGREGRE DADONGGITTIM": ["PAKREGRE DODONGGITTIM"]}, "PAKREGRE": {"PAKREGRE": ["PAKREGRE"]}, "PAKREGRECHIJONG APAL": {"PAKREGRECHIJONG APAL": ["PAKREGRE CHIJONGAPAL"]}, "PHD CAMPUS": {"PHD CAMPUS": ["P.W.D CAMPUS"]}, "PHE CAMPUS": {"PHE CAMPUS": ["P.H.E CAMPUS"]}, "RANGBERAM": {"RANGBERAM": ["GABIL NENGBREK", "RANGBERAM"]}, "RANGME AGAL": {"RANGME AGAL": ["RONGME SALPARA"]}, "RANGME APA": {"RANGME APA": ["RANGME APAL"]}, "RENGKIL APAL": {"RENGKIL APAL": ["RENGKIL APAL", "RENGKILGITTIM"]}, "ROGU ALDA": {"ROGU ALDA": ["ROGU ALDA"]}, "RONGA AGAL": {"RONGA AGAL": ["CHURCHGITTIM", "MANGSANG RONGA AGAL"]}, "RONGBANG": {"RONGBANG": ["RONGBANG"]}, "RONGCHEK AKONG": {"RONGCHEK AKONG": ["DAGAL BOLKET", "RONGCHEK AKONG"]}, "RONGCHONG": {"RONGCHONG": ["RONGCHANG"]}, "RONGDO IMBOL": {"RONGDO IMBOL": ["RONGBU IMBOLGITTIM"]}, "RONGDU DIKKAGITTIM": {"RONGDU DIKKAGITTIM": ["DIKAGITTIM"]}, "RONGDU NINGJAGITTIM": {"RONGDU NINGJAGITTIM": ["RONGDU NENGJAGITTIM"]}, "RONGDU PAKRIGITTIM": {"RONGDU PAKRIGITTIM": ["RONGDU PAKREGITTIM"]}, "RONGDU RONGRAGITTIM": {"RONGDU RONGRAGITTIM": ["RONGDU RONGRAGITTIM"]}, "RONGDU RONGTIT GITTIM": {"RONGDU RONGTIT GITTIM": ["RONGDU RONGTITGITTIM"]}, "RONGGOM GITTIM": {"RONGGOM GITTIM": ["RONGGOMGITTIM"]}, "RONGITGITTIM": {"RONGITGITTIM": ["RONGITGITIM"]}, "RONGJENG BAZAR": {"RONGJENG BAZAR": ["RONGJENG BAZAR"]}, "RONGJENG GAURAM": {"RONGJENG GAURAM": ["NOKMAGITTIM", "RONGJENG GAURAM"]}, "RONGJENG GONGDOPGITTIM": {"RONGJENG GONGDOPGITTIM": ["RONGJENG GONGDOPGITTIM"]}, "RONGJENG RESERVE": {"RONGJENG RESERVE": ["DOBAKOLGITTIM", "RONGJENG RESERVE"]}, "RONGJENG SONGMA": {"RONGJENG SONGMA": ["CHRISTIANPARA (CHITIMGITTIM)", "RONGJENG SONGMA"]}, "RONGKU GITTIM": {"RONGKU GITTIM": ["RONGKUGITTIM"]}, "RONGMIL": {"RONGMIL": ["NEW BOLSALDAM", "RONGMIL", "RONGMIL BAZAR"]}, "RONGMITHU": {"RONGMITHU": ["RONGMITHU", "UPPER RONGMITHU"]}, "RONGSPONGGITTIM": {"RONGSPONGGITTIM": ["RONGSPONGGITTIM"]}, "SARANG APAL": {"SARANG APAL": ["SARANG APAL"]}, "SEIMAGRE": {"SEIMAGRE": ["SIMAGRE"]}, "SILCHANG GITTIM": {"SILCHANG GITTIM": ["SILCHANGGITTIM"]}, "SIMSAM ATIMBO": {"SIMSAM ATIMBO": ["RANGME SONGGITAL", "SIMSENG ATIMBO"]}, "SIMSENG ARINGGA": {"SIMSENG ARINGGA": ["SIMSENG ARINGGA"]}, "SIMSENG BALKOL": {"SIMSENG BALKOL": ["SIMSENG BALKOL"]}, "SIMSENG BOLMA": {"SIMSENG BOLMA": ["SIMSENG BOLMA"]}, "SIMSENG BONGGA": {"SIMSENG BONGGA": ["SIMSENG BONGGA"]}, "SIMSENG MINOR": {"SIMSENG MINOR": ["SIMSENG MINOL"]}, "SIMSENG NOKOL": {"SIMSENG NOKOL": ["SIMSENG NAKOL"]}, "SIMSENG RONGAL": {"SIMSENG RONGAL": ["SIMSENG RONGAL"]}, "SIMSENG WAGE APAL": {"SIMSENG WAGE APAL": ["SIMSENG WAGE APAL"]}, "SIMSENG WALE": {"SIMSENG WALE": ["SIMSENG WALE"]}, "SOLGITCHAK GITTIM": {"SOLGITCHAK GITTIM": ["SALGITCHAKGITTIM"]}, "TAMSURA": {"TAMSURA": ["TAMSURA"]}, "TAUGITTIM": {"TAUGITTIM": ["THAUGITTIM"]}, "TEBIL GITTIM": {"TEBIL GITTIM": ["TEBILGITTIM"]}, "TESOKGITTIM": {"TESOKGITTIM": ["TESOKGITTIM"]}, "TETENGGITOK": {"TETENGGITOK": ["TETENGGITOK"]}, "UPPER RONGJENG": {"UPPER RONGJENG": ["UPPER RONGJENG"]}, "WAJA GITTIM": {"WAJA GITTIM": ["WAJA B", "WAJAGITTIM"]}, "WAKCHI KONGGITTIM": {"WAKCHI KONGGITTIM": ["WAKCHIKONGGITTIM"]}, "WARI DIPO": {"WARI DIPO": ["WARIDIPO"]}}, "KHARKUTTA": {"ADOKGIRI": {"ADOKGIRI": ["ADOKGRE", "ADOKGRE SAMJAGITTIM", "ADOKGRE SONGGITALL"]}, "AGROPATHAR": {"AGROPATHAR": ["AGRO PATHAR"]}, "AMERIM": {"AMERIM": ["AMERIM"]}, "ARAIAPAL": {"ARAIAPAL": ["ARAI APAL"]}, "ARBELLAPARA": {"ARBELLAPARA": ["ALBELPARA"]}, "ARENGDO": {"ARENGDO": ["ARENGDOK"]}, "ARUAKGIRI": {"ARUAKGIRI": ["ARUAKGIRI", "BOLLONGGITTIM", "DORANG SARAM"]}, "ATHIABARI": {"ATHIABARI": ["ATHIABARI", "ATHIABARI KAMA"]}, "BADAKA": {"BADAKA": ["BADAKA", "BADAKA NALSA", "BADAKA SONGGITAL"]}, "BADAKARAJASALI": {"BADAKARAJASALI": ["BADAKA RAJASALI"]}, "BAFENGGITTIM": {"BAFENGGITTIM": ["BARENGGITTIM"]}, "BAGABATTA": {"BAGABATTA": ["BAGABATTA"]}, "BAKSALPARA (SONGITTAL)": {"BAKSALPARA (SONGITTAL)": ["BAKSALPARA SONGGITAL"]}, "BAKSALPARA 1": {"BAKSALPARA 1": ["BAKSALPARA - I", "BAKSALPARA CHICHANGGITTIM"]}, "BAKSALPARA NACHIRONGDIK": {"BAKSALPARA NACHIRONGDIK": ["BAKSALPARA BAKRAGITTIM", "BAKSALPARA NASINRONGDIK"]}, "BOLGRIMGITTIM": {"BOLGRIMGITTIM": ["BOLGRIMGITTIM", "RATIKA"]}, "BOLSALDAM": {"BOLSALDAM": ["BOLSALDAM"]}, "BUGAKOL1,2,3": {"BUGAKOL": ["BUGAKOL", "BUGAKOL APAL", "LOWER BUGAKOL"]}, "BUGAKOL4,5,6": {"BUGAKOL": ["BUGAKOL", "BUGAKOL APAL", "LOWER BUGAKOL"]}, "BUGAKOL7": {"BUGAKOL": ["BUGAKOL"]}, "CHACHINAT": {"CHACHINAT": ["CHACHINATH"]}, "CHARA -AKONG": {"CHARA -AKONG": ["CHARE AKONG"]}, "CHIBONGGA": {"CHIBONGGA": ["CHIBONGGA", "CHIBONGGA CHAMBILDAM", "CHIBONGGA CHIKONGGITTIM", "CHIBONGGA SONGGITCHAM"]}, "CHIBRA JAMBAL": {"CHIBRA JAMBAL": ["CHIBRA JAMBAL"]}, "CHIGRANGGRI": {"CHIGRANGGRI": ["CHIGRANGIRI"]}, "CHILPARA": {"CHILPARA": ["CHILPARA", "CHILPARA SONGGITUL"]}, "CHILPARA - RESERVE": {"CHILPARA - RESERVE": ["CHILPARA RESERVE", "CHILPARA SONGGITUL"]}, "CHIMA APAL": {"CHIMA APAL": ["CHIMA APAL"]}, "CHIMA IMPEL": {"CHIMA IMPEL": ["CHIMA AGA", "CHIMA IMPEL"]}, "CHIMADARE": {"CHIMADARE": ["CHIMADARE"]}, "CHIMAJAMBAL (RODU JAMBAL)": {"CHIMAJAMBAL (RODU JAMBAL)": ["CHIMAJAMBAL"]}, "CHIWA ADAPGITTIM": {"CHIWA ADAPGITTIM": ["CHIWA ADAPGITTIM"]}, "CHIWAKKI": {"CHIWAKKI": ["CHIWAKI", "CHIWAKI WATRIGTTIM"]}, "CHOTCHOLJA": {"CHOTCHOLJA": ["CHOLCHOLJA", "CHOLCHOLJA ARICHAGITTIM", "CHOLCHOLJA CHICHANGITTIM", "CHOLCHOLJA SONGGACHI"]}, "CHOTCHOLJA NAPAKGITTIM": {"CHOTCHOLJA NAPAKGITTIM": ["CHOTCHOLJA NAPAKGITTIM"]}, "DAMBORA": {"DAMBORA": ["DAMBORA", "DAMBORA SONGMA"]}, "DANGKONG GARO": {"DANGKONG GARO": ["KANGKONG GARO"]}, "DANGKONG RABHA": {"DANGKONG RABHA": ["DANGKONG RABHA"]}, "DAPOLPARA": {"DAPOLPARA": ["DAPOLPARA"]}, "DARANG PETCHONG": {"DARANG PETCHONG": ["DARANG PETCHONG"]}, "DEPA SARANGMA": {"DEPA SARANGMA": ["DEPA", "NEW DEPA"]}, "DIKAGITTIM": {"DIKAGITTIM": ["DIKAGITTIM"]}, "DILKANG": {"DILKANG": ["DILKANG"]}, "DILMA ADAP": {"DILMA ADAP": ["ATTIMBOGITTIM", "CHIDARE GITTIM", "DILMA ADAP"]}, "DILMA ADING": {"DILMA ADING": ["DILMA ADING"]}, "DIPLOKGITTIM": {"DIPLOKGITTIM": ["DIPLOKGITTIM"]}, "DOBANGGAL": {"DOBANGGAL": ["DOBANGAL"]}, "DOCHISORAM": {"DOCHISORAM": ["DOCHISORAM"]}, "DOKONGSI": {"DOKONGSI": ["DOKONGSI", "DOKONGSI SONGGITAL"]}, "DOSARAM": {"DOSARAM": ["DOSARAM"]}, "DOSINGKOL": {"DOSINGKOL": ["DOSINGKOL"]}, "GAIRONG (CHIMA -AGA)": {"GAIRONG (CHIMA -AGA)": ["GAIRONG", "GAIRONG BAZAR"]}, "GANGGASA": {"GANGGASA": ["GANGGASA", "TAMATCHIGITTIM"]}, "GOLDE - NANGRAK": {"GOLDE - NANGRAK": ["GOLDE NANGGRAK", "HALDO"]}, "GOROK": {"GOROK": ["GOROK", "GOROK ADING", "GOROK SONGGITAL"]}, "GULLUTGITTIM": {"GULLUTGITTIM": ["GULUKGITTIM"]}, "ILDEK AKONG": {"ILDEK AKONG": ["ILDEK AKONG", "ILDEK AKONG SONGGITAL"]}, "ILDEK RESERVE": {"ILDEK RESERVE": ["ILDEK RESERVE", "RESERVE SONGGITAL"]}, "ILLAGITTIM": {"ILLAGITTIM": ["ILLAGITTIM"]}, "IMBANGGI": {"IMBANGGI": ["IMBANGGI", "IMBANGGI UPPER", "KODAL"]}, "IMBENG AKONG": {"IMBENG AKONG": ["IMBENG AKONG", "UPPER & LOWER AKONG"]}, "IMSAMBAL": {"IMSAMBAL": ["IMSAMBAL", "IMSAMBAL SONGGITUL"]}, "JAJIL GITTIM": {"JAJIL GITTIM": ["JAJIL SONGGITAL", "JAJILGITIM"]}, "JALKIM": {"JALKIM": ["JALKIM"]}, "JEGALPARA": {"JEGALPARA": ["JEGALPARA"]}, "JONGKI GITTIM": {"JONGKI GITTIM": ["JONGKIGITTIM"]}, "KALWE": {"KALWE": ["KALWE"]}, "KAMA GANDIM": {"KAMA GANDIM": ["KAMAGANDIM", "KAMAGANDIM SONGMA"]}, "KARA MAJIPARA": {"KARA MAJIPARA": ["KARA MAJIPARA", "MAJIPARA SONGIGITUL"]}, "KARABALAPARA": {"KARABALAPARA": ["BALAPARA SONGGITUL", "KARA BALAPARA"]}, "KASIMARI": {"KASIMARI": ["KASIMARI"]}, "KEJUGITTIM": {"KEJUGITTIM": ["KEJUGITTIM"]}, "KENTRA": {"KENTRA": ["KENTRA"]}, "KHARKUTTA RESERVE": {"KHARKUTTA RESERVE": ["KHARKUTTA RESERVE", "KHARKUTTA RESERVEGITTIM"]}, "KHARKUTTA SONGGITAL": {"KHARKUTTA SONGGITAL": ["KHARKUTTA SONGGITAL"]}, "KONCHIKOL AGA": {"KONCHIKOL AGA": ["KONCHIKOL AGA", "KONCHIKOL SONGGITAL"]}, "KONCHIKOL APAL": {"KONCHIKOL APAL": ["KONCHIKOL APAL", "KONCHIKOL SONGMA"]}, "KOSAK GANDIM": {"KOSAK GANDIM": ["KOSAK GANDIM"]}, "LOWER  JAMBAL": {"LOWER  JAMBAL": ["LOWER JAMBAL"]}, "LOWER BOLMEDANG": {"LOWER BOLMEDANG": ["BOLMEDANG KHAMAGANDIM", "LOWER BOLMEDANG"]}, "LOWER KHARKUTTA": {"LOWER KHARKUTTA": ["LOWER KHARKHUTA"]}, "LOWER RONGBU": {"LOWER RONGBU": ["LOWER RONGBU", "RONGBU SONGGITAL"]}, "LOWER SAMBRAK": {"LOWER SAMBRAK": ["LOWER SAMBRAK", "SAMBRAK SEED FARM", "SAMBRAK SONGGITAL"]}, "LOWER SARI AWE": {"LOWER SARI AWE": ["LOWER SARI AWE"]}, "MAKKRE ADAP": {"MAKKRE ADAP": ["MAKRE ADAP"]}, "MANCHANG": {"MANCHANG": ["MANCHANG"]}, "MANDA- DROP": {"MANDA- DROP": ["MANDADROP"]}, "MANDU MANGSAKGITTIM": {"MANDU MANGSAKGITTIM": ["MANDU MANSAKGITTIM"]}, "MANGKRIP": {"MANGKRIP": ["MANGKRIP"]}, "MAPILKOL": {"MAPILKOL": ["ABIA", "CHICHANGITTIM", "MOPIKOL", "WALKANGITTIM"]}, "MATCHADU": {"MATCHADU": ["MACHADU"]}, "MATCHAGITTIM": {"MATCHAGITTIM": ["MATCHAGITTIM"]}, "MEGAM ADING": {"MEGAM ADING": ["MEGAM ADING"]}, "MEGAM AKONG": {"MEGAM AKONG": ["AGALGITTIM", "BAJILGITTIM", "DROPGITTIM", "MEGAM AKONG", "RONGRIM"]}, "MEMILLAM": {"MEMILLAM": ["MEMILAM"]}, "MEMILLAM MODIPARA": {"MEMILLAM MODIPARA": ["MEMILAM MODIPARA"]}, "MENADOBA": {"MENADOBA": ["MENADOBA", "MENADOBA ACHONGITTIM", "MENADOBA AROBAGITTIM", "MENADOBA KOBARGITTIM"]}, "MENDIMA (GARO)": {"MENDIMA (GARO)": ["GARO (MENDIMA)-I", "GARO (MENDIMA)-II", "MENDIMA GARO"]}, "MENDIMA BAKRAGITTIM": {"MENDIMA BAKRAGITTIM": ["MENDIMA BAKRAGITTIM"]}, "MENDIMA RABHA": {"MENDIMA RABHA": ["LOWER MENDIMA", "MENDIMA RABHA"]}, "MINGKRAK": {"MINGKRAK": ["MINGKRAK", "MINGKRAK SONGGITAL", "SELBAGIRI"]}, "MITTE SONGGITAL": {"MITTE SONGGITAL": ["MITE SONGGITAL"]}, "MITTEGITTIM": {"MITTEGITTIM": ["MITTEGITTIM"]}, "NACHIRONGDIK": {"NACHIRONGDIK": ["NACHIRONGDIK"]}, "NAMERAM": {"NAMERAM": ["MAMERAM SONGGITAL", "NAMERAM"]}, "NANGGILDING": {"NANGGILDING": ["NANGILDING"]}, "NEW AMERIM": {"NEW AMERIM": ["NEW AMERIM"]}, "NILWA GUARECHOL": {"NILWA GUARECHOL": ["NILWA GUARICHOL"]}, "NONGBAK CHICHRA": {"NONGBAK CHICHRA": ["NONGBAK CHICHRA"]}, "NONGBAKWAPIL": {"NONGBAKWAPIL": ["NONGBAK WAPIL"]}, "NORANGGA": {"NORANGGA": ["NORONGGA", "NORONGGA BOLONGGITTIM", "NORONGGA SONGGITAL"]}, "PANBARI": {"PANBARI": ["PANBARI"]}, "RAJASIMLA MONGSI": {"RAJASIMLA MONGSI": ["RAJASIMLA MONGSI", "RAJASIMLA SONGGITUL"]}, "RAJASIMLA RESERVE": {"RAJASIMLA RESERVE": ["RAJASIMLA RESERVE"]}, "RAJASIMLA RONGDAL ATIMBO": {"RAJASIMLA RONGDAL ATIMBO": ["RAJASIMLA ARIBAK GITTIM", "RAJASIMLA RONGDAL ATIMBO"]}, "RAJASIMLA SONGGITTAL": {"RAJASIMLA SONGGITTAL": ["RAJASIMLA SONGGITUL"]}, "RAJASIMLA SONGMA": {"RAJASIMLA SONGMA": ["RAJASIMLA BABUPARA", "RAJASIMLA SONGMA"]}, "RAJASIMLA WARI": {"RAJASIMLA WARI": ["NEW RAJASIMLA", "RAJASIMLA UPPER", "RAJASIMLA WARI", "WARI KOBALDAM"]}, "RAKUMA": {"RAKUMA": ["RAKUMA"]}, "RANGGA (NADILWANG)": {"RANGGA (NADILWANG)": ["RANGGA", "RANGGA NADILWANG"]}, "RANGKET GITTIM": {"RANGKET GITTIM": ["RANGKETGITTIM"]}, "RANGSA": {"RANGSA": ["RANGSA"]}, "REKING": {"REKING": ["REKING", "REKING KAMA", "REKING KOSAK"]}, "REMAGITTIM": {"REMAGITTIM": ["REMAGITTIM"]}, "RENGOK SARAM": {"RENGOK SARAM": ["RENGOK SARAM"]}, "RONGBANG": {"RONGBANG": ["RONGBANG"]}, "RONGCHRI": {"RONGCHRI": ["RONGCHRI"]}, "RONGIT RENGGINGITTIM": {"RONGIT RENGGINGITTIM": ["RONGIT"]}, "RONGKINGJENG": {"RONGKINGJENG": ["RONGKINGJENG"]}, "RONGMATCHU": {"RONGMATCHU": ["RONGMATCH APAL", "RONGMATCHU"]}, "SAKWARE": {"SAKWARE": ["SAKWARE", "SAKWARE KOROK", "SAKWARE SHAMA"]}, "SAKWARE SONGGITAL": {"SAKWARE SONGGITAL": ["SAKWARE ADING", "SAKWARE SONGGITAL"]}, "SARANGMA": {"SARANGMA": ["NEW SARANGMA", "SARANGMA"]}, "SARI - AWE (SONGMA)": {"SARI - AWE (SONGMA)": ["SARI AWE"]}, "SILKIGITIM": {"SILKIGITIM": ["SILKIGITTIM"]}, "SOBA-JAMBAL": {"SOBA-JAMBAL": ["SOBA JAMBAL"]}, "TEBRONGPARA": {"TEBRONGPARA": ["TEBRONGPARA"]}, "TENGABARI": {"TENGABARI": ["TENGABARI"]}, "TENGASOT": {"TENGASOT": ["TENGASOT", "TENGASOT SONGMAGITTIM"]}, "TINGBA": {"TINGBA": ["TINGBA", "TINGBA KAMA", "TINGBA KOSAK"]}, "TINSIMINA": {"TINSIMINA": ["TINSIMANE", "TINSIMANE RESERVE", "TINSIMANE SONGGITAL"]}, "TOKKOL": {"TOKKOL": ["TOKKOL", "TOKKOL SONGMA"]}, "TOMBUMA": {"TOMBUMA": ["TOMBUMA", "TOMBUMA KAMAGITTIM"]}, "UGURI": {"UGURI": ["UGURI", "UGURI SYNGOBGITTIM", "UGURI WAGAGGITTIM"]}, "UPPER BOLMEDANG": {"UPPER BOLMEDANG": ["BOLMEDANG SONGGITUL", "UPPER BOLMEDANG"]}, "UPPER JAMBAL": {"UPPER JAMBAL": ["JAMBAL SONGGITAL", "UPPER JAMBAL"]}, "UPPER KHARKUTTA": {"UPPER KHARKUTTA": ["KHARKUTTA DAKUMA", "KHARKUTTA KABARKHANA", "UPPER KHARKUTTA"]}, "UPPER RONGBU": {"UPPER RONGBU": ["NALSAGITTIM", "UPPER RONGBU"]}, "UPPER SAMBRAK": {"UPPER SAMBRAK": ["ARAPARA", "SAMBRAK", "UPPER SAMBRAK"]}, "UPPER SARI - AWE": {"UPPER SARI - AWE": ["UPPER SARI AWE"]}, "WAGE ASI": {"WAGE ASI": ["LOWER WAGEASI", "NEW WAGEASI GRAZING", "UPER WAGEASI", "WAGEASI", "WAGEASI BAZAR"]}, "WAKURAM": {"WAKURAM": ["WAKURAM (APAL)", "WAKURAM SONGGITUL"]}, "WARAMJA": {"WARAMJA": ["UPPER & LOWER WARAMJA", "WARAMJA"]}, "WARTREGITTIM": {"WARTREGITTIM": ["NEW BOLSALDAN", "WATREGITIM"]}}, "RESUBELPARA": {"ABANDA": {"ABANDA": ["ALBANDA"]}, "ACHOTCHONGGRE": {"ACHOTCHONGGRE": ["ACHOTCHONGGRE"]}, "AJASIRAM": {"AJASIRAM": ["AJA SIRAM"]}, "ANE-AGA": {"ANE-AGA": ["ANE AGA"]}, "ARUAK NOKATGRE": {"ARUAK NOKATGRE": ["ARUAK NOKATGRE"]}, "ARUAK SONGGITAL": {"ARUAK SONGGITAL": ["ARUAKE SONGGTAL"]}, "ARUAKGRE": {"ARUAKGRE": ["ARUAKGRE"]}, "BAJENGDOBA": {"BAJENGDOBA": ["BAJENGDOBA I"]}, "BAJENGDOBA BAZAAR": {"BAJENGDOBA BAZAAR": ["BAJENGDOBA BAZAR"]}, "BAJENGDOBA II": {"BAJENGDOBA II": ["BAJENGDOBA II"]}, "BAKENANG NALSA": {"BAKENANG NALSA": ["BAKENANG NALSA"]}, "BAKENANG RABHA": {"BAKENANG RABHA": ["BAKENANG RABHA"]}, "BAKENANG SONGMA": {"BAKENANG SONGMA": ["BAKENANG SONGMA"]}, "BALKOLGRE": {"BALKOLGRE": ["BALKOLGRE"]}, "BALMURI": {"BALMURI": ["BALMURI"]}, "BANGSI APAL": {"BANGSI APAL": ["BANGSI APAL"]}, "BANGSI DOGRU": {"BANGSI DOGRU": ["WAKSO ASUGRE"]}, "BANGSI MINOL": {"BANGSI MINOL": ["WAKSO NENGSA"]}, "BANGSIAGA (ALDA)": {"BANGSIAGA (ALDA)": ["WAKSO ASIMGRE"]}, "BARALI KATONGRE": {"BARALI KATONGRE": ["BARALI KATONGRE"]}, "BARALIPARA": {"BARALIPARA": ["BARALIPARA"]}, "BEKBEKGRE": {"BEKBEKGRE": ["BEKBEKGRE", "BEKBEKGRE SONGITTAL"]}, "BERUBARI": {"BERUBARI": ["BERUBARI"]}, "BODA APAL": {"BODA APAL": ["BODA APAL", "SELBALGIRI"]}, "BOKMAGRE": {"BOKMAGRE": ["BOKMAGRE"]}, "BOLLONGPANG": {"BOLLONGPANG": ["BOLONGPANG"]}, "BOLPUMA": {"BOLPUMA": ["BOLPUMA"]}, "BOLSAADING": {"BOLSAADING": ["BOLSAL ADING"]}, "BOLSONG B.MOHOL": {"BOLSONG B.MOHOL": ["BOLSONG B.MOHAL"]}, "BOLSONG KAMAGRE": {"BOLSONG KAMAGRE": ["BOLSONG KAMA"]}, "BOLSONG KELCHIDAM": {"BOLSONG KELCHIDAM": ["BOLSONG KELCHIDAM"]}, "BOLSONG SONGMA": {"BOLSONG SONGMA": ["BOLSONG SONGMA"]}, "BOLSONGSEMBALGRE": {"BOLSONGSEMBALGRE": ["BOLSONG SEMBALGRE"]}, "BONGBANCHI": {"BONGBANCHI": ["BONGBANCHI"]}, "BONGGARE CHIMITCHENG": {"BONGGARE CHIMITCHENG": ["BONGGARE CHIMITCHENG"]}, "BONGGARE OLBAKNANG": {"BONGGARE OLBAKNANG": ["BONGGARE OLBAKNANG"]}, "BORO GOKOL": {"BORO GOKOL": ["BORO GOKUL"]}, "BORO MIAPARA": {"BORO MIAPARA": ["BORO MIAPARA"]}, "CHAKODAM": {"CHAKODAM": ["CHAKODAM"]}, "CHAMBILDAM": {"CHAMBILDAM": ["CHAMBILDAM"]}, "CHENGGALMA": {"CHENGGALMA": ["CHENGALMA SONGGITAL", "CHENGGALMA"]}, "CHICHOTCHENG": {"CHICHOTCHENG": ["CHICHOTCHENG"]}, "CHIDARET AJAJRO": {"CHIDARET AJAJRO": ["CHIDARET AJAGRO"]}, "CHIDORENG": {"CHIDORENG": ["CHIDORENG"]}, "CHIMATCHA": {"CHIMATCHA": ["CHIMATCHA"]}, "CHIPAKRAM": {"CHIPAKRAM": ["CHIPSKRAM"]}, "CHIRAM CHRISTIAN GITTIM": {"CHIRAM CHRISTIAN GITTIM": ["CHIRAM CHRISTIANGGITTIM"]}, "CHIRAMAGA": {"CHIRAMAGA": ["CHIRAM AGA"]}, "CHIRARAGRE": {"CHIRARAGRE": ["CHIARAGRE"]}, "CHIRIMDARE": {"CHIRIMDARE": ["CHIRIM DARE"]}, "CHISIM ADUMAGRE": {"CHISIM ADUMAGRE": ["CHISIM ADUMAGRE"]}, "CHISIM APAL1,2": {"CHISIM APAL": ["CHISIM APAL", "NEW CHISIM  APAL"]}, "CHISIM APAL3": {"CHISIM APAL": ["CHISIM APAL"]}, "CHISIM MANDALPANG": {"CHISIM MANDALPANG": ["CHISIM MANDALPANG"]}, "CHISIMAKANANG": {"CHISIMAKANANG": ["CHISIM AKHANANG"]}, "CHISIMAPAL": {"CHISIMAPAL": ["CHISIM APAL"]}, "CHISIMARI": {"CHISIMARI": ["CHISMARI"]}, "CHITUKDADRAM": {"CHITUKDADRAM": ["DOGRU GITTIM", "NEW CHISIM APAL"]}, "CHITUKONA GARO": {"CHITUKONA GARO": ["CHITUKONA GARO"]}, "CHITUKONA RABHA": {"CHITUKONA RABHA": ["CHITUKONA RABHA"]}, "CHOREPAHAR": {"CHOREPAHAR": ["CHOREPAHAR"]}, "CHOTO MIAPARA": {"CHOTO MIAPARA": ["CHOTO MIAPARA"]}, "DAINADUBI": {"DAINADUBI": ["DAINA DUBI"]}, "DAJONGPARA": {"DAJONGPARA": ["DAJONGPARA"]}, "DAJONHWARIGRE": {"DAJONHWARIGRE": ["DAJONG WARIGRE"]}, "DALBINGGRE": {"DALBINGGRE": ["DALBINGGRE"]}, "DALBINGPA": {"DALBINGPA": ["DALBINGPA"]}, "DALMANGGRE": {"DALMANGGRE": ["DALMANGGRE"]}, "DAMAS": {"DAMAS": ["DAMAS I"]}, "DAMASH II": {"DAMASH II": ["DAMASH II"]}, "DAME APAL (GINDAPASARI)": {"DAME APAL (GINDAPASARI)": ["DAME APAL"]}, "DAMITAGA (MATCHAKOL)": {"DAMITAGA (MATCHAKOL)": ["DAGAL ARRINGGA"]}, "DAMRINGGRE": {"DAMRINGGRE": ["DAMRINGGRE"]}, "DANDAKOL": {"DANDAKOL": ["DANDAKOL"]}, "DANGGRA SONGMA": {"DANGGRA SONGMA": ["DANGRA SONGMA"]}, "DANGORBITA": {"DANGORBITA": ["DANGORPITA"]}, "DANGRA SONGGITAL": {"DANGRA SONGGITAL": ["DANGRA SONGGITAL"]}, "DANGSI BOKDA": {"DANGSI BOKDA": ["BANGSI BAKADA"]}, "DARAKONA": {"DARAKONA": ["DARAKONA"]}, "DENGGANGGRE": {"DENGGANGGRE": ["DENGNANGGRE"]}, "DIGISINGRE": {"DIGISINGRE": ["DIGISINGGRE"]}, "DILMA SONGGITAL": {"DILMA SONGGITAL": ["DILMA SONGGITAL"]}, "DILMAAGA (DONAL)": {"DILMAAGA (DONAL)": ["DILMA AGA"]}, "DIMBIL ADING": {"DIMBIL ADING": ["DIMBIL ADING"]}, "DOBAKKOL": {"DOBAKKOL": ["DOBAKKOL"]}, "DOKAMCHENG": {"DOKAMCHENG": ["DOKAMCHENG"]}, "DOKASARAM": {"DOKASARAM": ["DOKA SARAM"]}, "DOLDAM": {"DOLDAM": ["DOLDAM"]}, "DOME ANTI": {"DOME ANTI": ["DOME ANTI", "HORINKATA BAKRA GARO"]}, "DORATCHA": {"DORATCHA": ["DORATCHA"]}, "DUJONGGRE": {"DUJONGGRE": ["DUJONGGRE"]}, "EGUGRE": {"EGUGRE": ["EGUAGRE"]}, "GALWANGSA": {"GALWANGSA": ["GALWANGSA"]}, "GAMBIL AGA": {"GAMBIL AGA": ["WAKSO CHIRONGBAN"]}, "GAMBIL APAL": {"GAMBIL APAL": ["WAKSO RADANG"]}, "GENANG": {"GENANG": ["GENANG"]}, "GETAPARA": {"GETAPARA": ["GETAPARA"]}, "GOKULGRE": {"GOKULGRE": ["GOKULGRE I"]}, "GOKULGRE II": {"GOKULGRE II": ["GOKULGRE II"]}, "GOSINGPITA SONGMA": {"GOSINGPITA SONGMA": ["GOSINGPITA SONGMA"]}, "GOSINGPITABAKRA": {"GOSINGPITABAKRA": ["GOSINGPITA BAKRA"]}, "GURESIMRAM": {"GURESIMRAM": ["GURESIMRAM"]}, "HARINKATA BAKRA": {"HARINKATA BAKRA": ["HARINKATA BAKRA"]}, "HARINKATA RABHA": {"HARINKATA RABHA": ["HARINKATA RABHA"]}, "HATIBASA": {"HATIBASA": ["HATIBASA"]}, "JAMGAONDAGRE": {"JAMGAONDAGRE": ["JAMGONDAGRE"]}, "JAMGAONGDA NOKAT": {"JAMGAONGDA NOKAT": ["JAMGONDA NOKATGRE"]}, "JAMPARA": {"JAMPARA": ["BALNANGGRE"]}, "JETDOBA LANGAPARA": {"JETDOBA LANGAPARA": ["JETDOBA LANGAPARA"]}, "JETDOBA NAYAPARA": {"JETDOBA NAYAPARA": ["JETDOBA NAYAPARA"]}, "JETDOBA SONGGITCHAM": {"JETDOBA SONGGITCHAM": ["JETDOBA SONGGITCHAM"]}, "JOLDING": {"JOLDING": ["JOLDING"]}, "JONGDONGGRE": {"JONGDONGGRE": ["JONGDONGGRE"]}, "KAGRAKGRE": {"KAGRAKGRE": ["KAGRAKGRE"]}, "KAKKUNANGGRE": {"KAKKUNANGGRE": ["KAKUNANGGRE"]}, "KALDANG AGITOK": {"KALDANG AGITOK": ["KALDANG AGITOK"]}, "KANTARAGRE": {"KANTARAGRE": ["KANTARAGRE"]}, "KASH DEORIPARA": {"KASH DEORIPARA": ["DAGAL CHIMRAN"]}, "KASH RANGSI": {"KASH RANGSI": ["DAGAL SAMITY"]}, "KASHKONA": {"KASHKONA": ["SANEMA"]}, "KAWAK": {"KAWAK": ["KAWAK"]}, "KERAGALRAM": {"KERAGALRAM": ["KERAGALRAM"]}, "KIMBALDAM": {"KIMBALDAM": ["KIMBALDAM"]}, "KIMDEGRE": {"KIMDEGRE": ["KIMDEGRE"]}, "KIMSRI": {"KIMSRI": ["KIMSIRI"]}, "KITMADAMGRE": {"KITMADAMGRE": ["KITMADAMGRE"]}, "KONAPARA": {"KONAPARA": ["KONAPARA"]}, "KOREPARA": {"KOREPARA": ["KOREPARA"]}, "KOSICHORA": {"KOSICHORA": ["KOSICHORA"]}, "LINE ADING": {"LINE ADING": ["LINE ADING"]}, "LOWER MANIKGANJ": {"LOWER MANIKGANJ": ["LOWER MANIKGANJ"]}, "LOWER SUALMARI": {"LOWER SUALMARI": ["LOWER SUALMARI"]}, "MALCHAPARA": {"MALCHAPARA": ["MALCHAPARA"]}, "MANDALANGGRE": {"MANDALANGGRE": ["MANDALANGGRE"]}, "MANDALPANG B": {"MANDALPANG B": ["MANDALPANG B"]}, "MANSINGGRE": {"MANSINGGRE": ["MANSINGGRE", "MANSINGGRE SONGITTAL"]}, "MAODAMGRE": {"MAODAMGRE": ["MAODAMGRE"]}, "MAORIPARA": {"MAORIPARA": ["MAORIPARA", "RANGAGORA NALSA"]}, "MATCHAMELARAM": {"MATCHAMELARAM": ["MATCHA MELLARAM"]}, "MATCHUKI": {"MATCHUKI": ["BANDAMGIRI", "DIMAKPARA", "MATCHUKI"]}, "MEBOKDAM": {"MEBOKDAM": ["MEBOKDAM"]}, "MENDUDAM": {"MENDUDAM": ["MENDUDAM"]}, "MERONGDIK": {"MERONGDIK": ["MERONGDIK"]}, "MIKKA SIMDAM": {"MIKKA SIMDAM": ["MIKKA SAMDAM"]}, "MOAMARI": {"MOAMARI": ["MOAMARI"]}, "MONGPANGRO": {"MONGPANGRO": ["MONGPANGRO"]}, "MOTCHOLPARA": {"MOTCHOLPARA": ["MOTCHOLPARA"]}, "NAMIL APAL": {"NAMIL APAL": ["WAKSO TODAM"]}, "NARONGKOL": {"NARONGKOL": ["NARONGKOL"]}, "NENGGITCHAKGRE": {"NENGGITCHAKGRE": ["NENGGITCHAKGRE"]}, "NENGSA NARONGKOL": {"NENGSA NARONGKOL": ["NENGSA NARONKOL"]}, "NEW KATOLGURI (DOBAKKOL)": {"NEW KATOLGURI (DOBAKKOL)": ["NEW KANTOLGURI"]}, "NEW MIAPARA": {"NEW MIAPARA": ["NEW MIAPARA"]}, "NEW PUTHIMARY": {"NEW PUTHIMARY": ["NEW PUTIMARI"]}, "NIBARI RANGAGORA": {"NIBARI RANGAGORA": ["NIBARI RANGAGORA"]}, "NISHANGRAM BABUPARA": {"NISHANGRAM BABUPARA": ["NISHANGRAM BABUPARA"]}, "NOGOLPARA": {"NOGOLPARA": ["LOWER NOGOLPARA", "NOGOL PARA"]}, "NOKATGRE": {"NOKATGRE": ["NOKATGRE"]}, "NOKWAL ADING": {"NOKWAL ADING": ["NOKWAL ADING"]}, "NOKWALGRE": {"NOKWALGRE": ["NOKWALGRE"]}, "NOLBARI": {"NOLBARI": ["NOLBARI"]}, "OKBIMA": {"OKBIMA": ["OKBIMA"]}, "OMARPUR": {"OMARPUR": ["OMORPUR"]}, "PAKMARE": {"PAKMARE": ["PAKMARE"]}, "PANGSUDAM": {"PANGSUDAM": ["PANGSUDAM"]}, "RADING": {"RADING": ["RADING"]}, "RAGOLGRE": {"RAGOLGRE": ["RAGOLGRE"]}, "RAJINGGRE": {"RAJINGGRE": ["RAJINGGRE"]}, "RAKSA GALIMA": {"RAKSA GALIMA": ["RAKSAM GALIMA"]}, "RAKSAM SOMAGRE": {"RAKSAM SOMAGRE": ["RAKSAM SOMAGRE"]}, "RAKSAM SONGMA": {"RAKSAM SONGMA": ["RAKSAM SONGMA"]}, "RAKSANG GENANG": {"RAKSANG GENANG": ["RAKSANG GENANG"]}, "RAKSINGRE": {"RAKSINGRE": ["RAKSINGRE"]}, "RANGAGORA": {"RANGAGORA": ["RANGAGORA"]}, "RANGSEL": {"RANGSEL": ["RANGSEL"]}, "RANGSELGRE": {"RANGSELGRE": ["BOLBOK SONGGITAL", "CHOREBOLBOK"]}, "RANGSEP": {"RANGSEP": ["HARINKATA BAKRA RAVA", "RANGSEP"]}, "ROMPA": {"ROMPA": ["ROMPA"]}, "RONGDAMA": {"RONGDAMA": ["RONG DAMA"]}, "RONGDAN": {"RONGDAN": ["RONG DAM"]}, "RONGGE": {"RONGGE": ["WAKSO SONGGITAL"]}, "RONGGOPGRE": {"RONGGOPGRE": ["RONGGOPGRE I"]}, "RONGGOPGRE II": {"RONGGOPGRE II": ["RONGGOPGRE II"]}, "RONGJALENG NOKAT": {"RONGJALENG NOKAT": ["RONGIALLENG NOKAT"]}, "RONGJALENGGRE": {"RONGJALENGGRE": ["RONGJALLENGGRE"]}, "RONGKAMINCHI": {"RONGKAMINCHI": ["RONGKAMINCHI"]}, "RONGKAMINCHIAGA": {"RONGKAMINCHIAGA": ["RONGKAMINCHI AGA"]}, "RONGMAKLONG": {"RONGMAKLONG": ["DANING APAL"]}, "RONGMATCHA": {"RONGMATCHA": ["RONGMATCHA"]}, "RONGPETCHI": {"RONGPETCHI": ["RONGPETCHI(BAJENGDOBA)"]}, "RONGSEPGRE": {"RONGSEPGRE": ["RANGSEPGRE"]}, "RONGSOL (BIKSEL)": {"RONGSOL (BIKSEL)": ["RONGSOL"]}, "RONGSOL (DAMIT AKONG)": {"RONGSOL (DAMIT AKONG)": ["ILLAGRE"]}, "RONGTHU": {"RONGTHU": ["RONGTU"]}, "SALLINGGIRI": {"SALLINGGIRI": ["SALLINGGRE"]}, "SAMKALAKGRE": {"SAMKALAKGRE": ["SAMKALAKGRE", "SAMKALAKGRE SONGITAL"]}, "SARONGKOL": {"SARONGKOL": ["SARONGKOL"]}, "SEPIKOL": {"SEPIKOL": ["SEPIKOL"]}, "SILDUBI": {"SILDUBI": ["SILDUBI"]}, "SOENANG AGA": {"SOENANG AGA": ["SOENANG AGA"]}, "SOENANG APAL": {"SOENANG APAL": ["SOENANG APAL"]}, "SOENANG PAHARTULI": {"SOENANG PAHARTULI": ["SOENANG PAHATULI"]}, "SONACHIRING": {"SONACHIRING": ["SONA CHIRING"]}, "SONGMEGAP": {"SONGMEGAP": ["BOLMA ALDA", "PEKINCHAKGRE"]}, "SONGNARU DOKAMCHENG": {"SONGNARU DOKAMCHENG": ["DOKAMCHENG SONGNARU", "WAKPOT APAL"]}, "SUALMARI RABHA": {"SUALMARI RABHA": ["SUALMARI RABHA"]}, "TASIL APAL": {"TASIL APAL": ["TASIL APAL"]}, "TATOLGRE": {"TATOLGRE": ["TATOLGRE"]}, "TEKAGRE": {"TEKAGRE": ["TEKAGRE"]}, "TETULGURI": {"TETULGURI": ["TETLUGURI"]}, "THAPA AGITCHAK": {"THAPA AGITCHAK": ["THAPA AGITCHAK"]}, "THAPA BAZAAR": {"THAPA BAZAAR": ["THAPA BAZAR"]}, "THAPA DAJONG GATE": {"THAPA DAJONG GATE": ["THAPA DAJONGGATE"]}, "THAPA DAJONGGRE": {"THAPA DAJONGGRE": ["THAPA DAJONGGRE"]}, "THAPA DANGRE": {"THAPA DANGRE": ["THAPA DANGRI"]}, "THAPA DARANGCHI": {"THAPA DARANGCHI": ["THAPA DARENCHI"]}, "THAPA KHANTOLGURI": {"THAPA KHANTOLGURI": ["THAPA KANTOLGURI"]}, "THAPA MATRONGGRE": {"THAPA MATRONGGRE": ["THAPA MATRONGGRE"]}, "THAPA RONGDENG": {"THAPA RONGDENG": ["THAPA RONGDENG"]}, "THORIKA KONA GARO": {"THORIKA KONA GARO": ["TONIKKAKONA GARO"]}, "THORIKONA RABHA": {"THORIKONA RABHA": ["TORIKKAKONA RABHA"]}, "TORIKA KUNTABARI": {"TORIKA KUNTABARI": ["TORIKKA KANTABARI"]}, "UPPER MANIKGANJ": {"UPPER MANIKGANJ": ["UPPER MANIKGANJ"]}, "UPPER NIABOLI": {"UPPER NIABOLI": ["DAME BIBRA"]}, "UPPER SUALMARI": {"UPPER SUALMARI": ["UPPER SUALMARI"]}, "WAKSO ACHUGRE": {"WAKSO ACHUGRE": ["WAKSO ACHUGRE"]}, "WAKSO ASIMGRE": {"WAKSO ASIMGRE": ["WAKSO ASSIMGRE SONGGITAL"]}, "WAKSO NENGSA": {"WAKSO NENGSA": ["BOKMA APALGRE", "WAKSO NENGSA APAL"]}, "WAKSO RADANG": {"WAKSO RADANG": ["WAKSO RADANG APAL"]}, "WAKSO SONGGITAL": {"WAKSO SONGGITAL": ["WAKSO SONGGITAL"]}, "WAKSO TODAMGIRI": {"WAKSO TODAMGIRI": ["NEW WAKSO TODAM"]}, "WAKSOCHIRONGBAN": {"WAKSOCHIRONGBAN": ["WAKSO CHIRONGBAN"]}, "WARAMGRE": {"WARAMGRE": ["WARAMGRE"]}, "WARIGRE": {"WARIGRE": ["WARIGRE"]}, "WASIM DAJONG": {"WASIM DAJONG": ["WASIM DAJONGPARA"]}}, "SAMANDA": {"AKELGRE": {"AKELGRE": ["AKELGRE", "AKELGRE B", "AKELGRE SONGGITAL"]}, "AMPANGGRE1,2,3": {"AMPANGGRE": ["AMPANGGRE", "AMPANGGRE SONGGITAL", "BAJONG AMPHANG"]}, "AMPANGGRE4": {"AMPANGGRE": ["AMPANGGRE"]}, "ASHA BIBRA": {"ASHA BIBRA": ["ASHA BIBRA"]}, "ASIMGRE": {"ASIMGRE": ["ASIMGRE"]}, "ASIRAGRE": {"ASIRAGRE": ["ASIRAGRE", "RABANGGITTIM", "SRANGGITTIM"]}, "BANDIGRE": {"BANDIGRE": ["BANDI AKONG", "BANDIGRE"]}, "BANGGONGGRE": {"BANGGONGGRE": ["BALADINGGITTIM", "BANGONGGRE"]}, "BANGONGSING WAGRE": {"BANGONGSING WAGRE": ["BANGONG SINGWEGRE"]}, "BANSAM AWE": {"BANSAM AWE": ["BANSAM AWE", "KAKWA ADU"]}, "BANSAM BIBRAGRE": {"BANSAM BIBRAGRE": ["BANSAM  BIBRAGRE"]}, "BANSAMGRE": {"BANSAMGRE": ["BANSAM BOLLONG", "BANSAMGRE", "BANSUM ATIMBO"]}, "BANSINGGRE": {"BANSINGGRE": ["BANSINGGRE", "BANSINGGRE SONGGITAL"]}, "BAWE DURAGRE": {"BAWE DURAGRE": ["BAWE DURAGRE"]}, "BAWEGRE": {"BAWEGRE": ["BAWEGRE", "BAWEGRE SONGITAL"]}, "BOLKINGGRE": {"BOLKINGGRE": ["BOLKINGGRE", "SINGBATGRE"]}, "CHACHAT JANGKIGRE": {"CHACHAT JANGKIGRE": ["CHACHAT JANGKIGRE"]}, "CHACHAT KARUBRA": {"CHACHAT KARUBRA": ["CHACHAT KARUBRA"]}, "CHACHATGRE": {"CHACHATGRE": ["CHACHATGRE"]}, "CHEKWEBIBRA": {"CHEKWEBIBRA": ["CHEKWEBIBRA"]}, "CHERANGRE": {"CHERANGRE": ["CHERANGRE", "CHERANGRE SONGGITAL"]}, "CHIBOLGRE": {"CHIBOLGRE": ["CHIBOLGRE", "CHIBOLGRE SONGGITAL"]}, "CHIMA DACHITGITTIM": {"CHIMA DACHITGITTIM": ["CHIMA DACHITGITTIM", "DAOPIT"]}, "CHIMAGRE SONGGITAL": {"CHIMAGRE SONGGITAL": ["CHIMAGRE SONGGITAL"]}, "CHIMIMINGGRE": {"CHIMIMINGGRE": ["CHIMINMINGRE"]}, "CHINEMGRE": {"CHINEMGRE": ["CHIKALGRE", "SAMANDA CHINEMGRE"]}, "CHIOKGRE": {"CHIOKGRE": ["CHIOKGRE", "NEW CHIOKGRE"]}, "CHISOBIBRA": {"CHISOBIBRA": ["CHISO RESERVEGITTIM", "CHISOBIBRA"]}, "CHONGGEGRE": {"CHONGGEGRE": ["CHONGGIGRE"]}, "DAMBEGRE": {"DAMBEGRE": ["DOMBEGRE"]}, "DARIBOKGRE": {"DARIBOKGRE": ["ALDAGIRI", "DARIBOKGRE"]}, "DARIMGRE AND RUKALGRE": {"DARIMGRE AND RUKALGRE": ["DARIMGRE & RUKALGRE"]}, "DAWA GITTINGGRE": {"DAWA GITTINGGRE": ["DAWA GITINGGRE", "TERESGITTIM"]}, "DAWA KOSIGITTIM": {"DAWA KOSIGITTIM": ["DAWA KOSIGITTIM"]}, "DAWA MATCHAKOLGRE": {"DAWA MATCHAKOLGRE": ["DAWA MATCHAKOLGRE"]}, "DAWA NENGJATA": {"DAWA NENGJATA": ["DAWA NENGJATAGRE", "NEW DENGGAGRE"]}, "DAWA NENGKATOK": {"DAWA NENGKATOK": ["COMPOUNDGITTIM", "DAWA NENGKATOK"]}, "DAWA SONGGITAL": {"DAWA SONGGITAL": ["DAWA SONGGITAL", "DAWA SONGGITAL B"]}, "DENGAGRE SONGGITAL": {"DENGAGRE SONGGITAL": ["DENGGAGRE SONGGITAL", "MRONGGITTIM"]}, "DENGGAGRE": {"DENGGAGRE": ["DENGGAGRE"]}, "DILMA DEBRAK": {"DILMA DEBRAK": ["DILMA DEBRAK"]}, "DILMA DILSEKGRE": {"DILMA DILSEKGRE": ["DILMA DILSEKGRE"]}, "DILMA KAWAK": {"DILMA KAWAK": ["CHIADING", "DILMA KAWAK"]}, "DILMA MATCHOK AKAWE": {"DILMA MATCHOK AKAWE": ["DILMA MATCHOK AKAWE"]}, "DILMA RIMTONGGRE": {"DILMA RIMTONGGRE": ["DILMA RIMTONGGRE", "GANDINANGGIRI", "RIMTONGGIRI"]}, "DILMA SONGGITCHAM": {"DILMA SONGGITCHAM": ["DILMA SONGGITCHAM"]}, "DILMA SONGMA": {"DILMA SONGMA": ["DILMA SONGMA"]}, "DIMOGRE": {"DIMOGRE": ["DEMOGRE", "DEMOGRE SONGGITAL"]}, "DINAJEKGRE": {"DINAJEKGRE": ["DINAJEKGRE", "DINAJEKGRE SONGGITAL"]}, "DINAMINGGRE": {"DINAMINGGRE": ["DINAM AGITOK", "DINAMINGRE"]}, "DOKTILGRE": {"DOKTILGRE": ["SAMANDA DOKTILGRE"]}, "DOLWARIGRE1,2,3": {"DOLWARIGRE": ["GRENANGGRE", "KARSINAGRE", "SAMANDA DOLWARIGRE"]}, "DOLWARIGRE4,5": {"DOLWARIGRE": ["DOLWARIGRE", "GALDIM AWE"]}, "DORAKGRE": {"DORAKGRE": ["DORAK SONGGITAL", "DORAK SONGKAMA", "DORAKGRE"]}, "DORENGKIGRE": {"DORENGKIGRE": ["DORENGKIGRE", "WALMAGITTIM", "WENEGRE"]}, "ENGGOKGRE": {"ENGGOKGRE": ["ENGGOKGRE"]}, "GANINGBIBRA": {"GANINGBIBRA": ["GANINGAWE", "GANINGBIBRA"]}, "GANINGGRE": {"GANINGGRE": ["GANINGGRE"]}, "GITOKGRE": {"GITOKGRE": ["GITOKGRE", "GITOKGRE AKAWE", "GITOKGRE SONGGITAL"]}, "GONGGNAGRE": {"GONGGNAGRE": ["GONGGNAGRE", "MERONG RANGGRE"]}, "GONGMAGRE": {"GONGMAGRE": ["GONGMAGRE"]}, "GOONGGRE": {"GOONGGRE": ["BILIGIPGRE", "GONGGRE", "GONGGRE SONGGITAL"]}, "GRADEKGITTIM": {"GRADEKGITTIM": ["GRADEKGITTIM", "RIMRANG JAREK"]}, "IMSOKGRE": {"IMSOKGRE": ["IMSOK SINGWIL", "IMSOK SONGGITAL", "IMSOKGRE"]}, "JAKOPGRE": {"JAKOPGRE": ["JAKOP ADING", "JAKOPGRE"]}, "JALJENGGRE": {"JALJENGGRE": ["JALJENGGRE"]}, "JINGAMGRE": {"JINGAMGRE": ["JINGAMGRE"]}, "JONGMEGRE": {"JONGMEGRE": ["JONGMEGRE", "JONGMEGRE SONGGITAL"]}, "KAKWA BAWEGRE": {"KAKWA BAWEGRE": ["KAKWA BAWEGRE"]}, "KAKWA DURAGRE": {"KAKWA DURAGRE": ["KAKWA DURAGRE"]}, "KAKWA RONGBOKGRE": {"KAKWA RONGBOKGRE": ["KAKWA RONGBOKGRE"]}, "KAKWA SONGMA": {"KAKWA SONGMA": ["KAKWA SONGGITAL", "KAKWA SONGGITCHAM"]}, "KALAK DOREK": {"KALAK DOREK": ["KALAK DOREK", "KALAK DOREK B"]}, "KALAK SONGGITAL": {"KALAK SONGGITAL": ["KALAK SONGGITAL", "KALAK SONGGITAL B"]}, "KALAK SONGGITCHAM": {"KALAK SONGGITCHAM": ["KALAK SONGGITCHAM"]}, "MANDALGIPE": {"MANDALGIPE": ["CHIADING", "MANDALGIPI"]}, "MANDALGRE": {"MANDALGRE": ["MANDAL AKONG", "MANDAL CHIJONGGITTIM", "MANDALGRE", "NEW BOKSARI"]}, "MANGRUGRE": {"MANGRUGRE": ["MANGRUGRE", "MANGRUGRE SONGGITAL"]}, "MEGAGRE SONGGITAL": {"MEGAGRE SONGGITAL": ["MEGAGRE B", "MEGAGRE SONGGITAL"]}, "MEGAPGRE": {"MEGAPGRE": ["SAMANDA MEGAPGRE"]}, "MEJALIGRE": {"MEJALIGRE": ["MAJALIGRE", "MAJALIGRE SONGGITAL"]}, "MERONGGRE": {"MERONGGRE": ["MERONGGRE"]}, "MIGAGRE SONGITCHAM": {"MIGAGRE SONGITCHAM": ["MEGAGRE SONGGITCHAM"]}, "NABOKGRE": {"NABOKGRE": ["NABOKGIRI SONGGITAL", "NABOKGRE", "NAJONG NABOKGRE", "WATRE CHIMAGRE"]}, "NENGKRA": {"NENGKRA": ["MEGAPGRE", "NENGKHRA"]}, "NENGKRA AWE": {"NENGKRA AWE": ["NENGKHRA ASRAGITTIM", "NENGKHRA AWE-I", "NENGKHRA CHIDITGITTIM", "NENGKHRA CHIPITGITTIM", "NENGKHRA MEGADOPGRE"]}, "NENGKRA AWE -II": {"NENGKRA AWE -II": ["NENGKHRA AWE-II", "NENGKHRA NENGRINGGITTIM", "NENGKHRA SONGGITAL"]}, "NENGKRA BOLSALGRE": {"NENGKRA BOLSALGRE": ["NENGKHRA BOLSALGITTIM", "NENGKHRA BOLSALGRE SONGITAL", "NENGKHRA WATREGRE"]}, "NENGKRA WATEGRE": {"NENGKRA WATEGRE": ["NENGKHRA WATREGRE", "NENGKHRA WATREGRE SONGGITAL"]}, "NENGMANDALGRE": {"NENGMANDALGRE": ["CHACHATGRE SONGGITAL", "NENGMADAL II", "NENGMANDALGRE"]}, "NENGSITGRE": {"NENGSITGRE": ["NENGSITGRE"]}, "NENGSRANG ADUGRE (SONGGITCHAM)": {"NENGSRANG ADUGRE (SONGGITCHAM)": ["NENGSRANG ADUGRE (SONGGITCHAM)"]}, "NENGSRANG PATALGRE (SONGGITAL)": {"NENGSRANG PATALGRE (SONGGITAL)": ["NENGSRANG PATALGRE (SONGGITAL)"]}, "NEREGRE": {"NEREGRE": ["APALGITTIM", "NARAGRE", "NARIGRE", "RONGREGRE", "RONGRIM AWE"]}, "NEW CHIDGRE": {"NEW CHIDGRE": ["NEW CHIDEKGRE"]}, "PAKWAKGRE": {"PAKWAKGRE": ["PAKWAKGRE"]}, "PATRANGGRE": {"PATRANGGRE": ["SAMANDA PATRANGGRE"]}, "PILGONGGRE": {"PILGONGGRE": ["PILPONGGRE"]}, "PRAPGRE": {"PRAPGRE": ["SAMANDA PRAPGRE"]}, "RAGITIKGRE": {"RAGITIKGRE": ["RAGITIKGRE"]}, "RAMBOGRE": {"RAMBOGRE": ["RAMBOGRE"]}, "RANGMALGRE": {"RANGMALGRE": ["MARAGITTIM", "RABALGITTIM", "RANGMALGRE"]}, "RANGMALGRE SONGGITAL": {"RANGMALGRE SONGGITAL": ["ASIMGRE", "RANGMAL ADING", "RANGMALGRE SONGGITAL", "WAROGITTIM"]}, "RAPDIKGRE": {"RAPDIKGRE": ["AKINGGRE", "BOLDAKGRE", "RAPDIKGRE", "RAPDIKGRE SONGGITAL", "SINDICHIRINGGRE"]}, "RENGREGRE": {"RENGREGRE": ["APALGITTIM", "RINGREGRE"]}, "RETENGGRE": {"RETENGGRE": ["RETENGGRE", "RETENGGRE SONGGITAL"]}, "RIKWARENGGRE": {"RIKWARENGGRE": ["SAMANDA RIKWARENGGRE"]}, "RIMRIMGRE": {"RIMRIMGRE": ["RIMRINGGRE"]}, "RONGAKGRE": {"RONGAKGRE": ["RONGAK AWAL", "RONGAKGRE"]}, "RONGALGRE": {"RONGALGRE": ["RONGAL KAMAGRE", "RONGALGRE", "SENGGALGITIM"]}, "RONGBING APOT": {"RONGBING APOT": ["ASIMGITTIM", "RONGBING APOT"]}, "RONGBING BOLDAK": {"RONGBING BOLDAK": ["RONGBING BOLDAK", "RONGMACHARE"]}, "RONGBING DALBOT": {"RONGBING DALBOT": ["RONGBING DALBOT", "SIMINAGIRI"]}, "RONGBINGGRE": {"RONGBINGGRE": ["RONGBINGGRE", "RONGBINGGRE SONGGITAL"]}, "RONGCHEK CHAMBUGONG": {"RONGCHEK CHAMBUGONG": ["RONGCHEK CHAMBUGONG"]}, "RONGCHEK MANDA": {"RONGCHEK MANDA": ["MANDA SONGGITAL", "RONGCHEK MANDA"]}, "RONGGATAGRE": {"RONGGATAGRE": ["RONGATAGRE", "WATENANGGRE"]}, "RONGKINGGRE": {"RONGKINGGRE": ["RONGKINGGRE", "RONGKINGGRE SONGGITAL"]}, "RONGONGRE": {"RONGONGRE": ["RONGON APAL", "RONGONGRE", "RONGONGRE SONGGITAL"]}, "RONGREKGRE": {"RONGREKGRE": ["RONGREKGRE"]}, "RONGRENG BAIZA  (WEST)": {"RONGRENG BAIZA  (WEST)": ["RONGRENG BAIZA (WEST)"]}, "RONGRENG BAIZA (EAST)": {"RONGRENG BAIZA (EAST)": ["RONGRENG BAIZA (EAST)"]}, "RONGRIBO AMALGRE": {"RONGRIBO AMALGRE": ["AMALGRE SONGGITAL", "RONGRIBO AMALGRE"]}, "RONGRIBO WATREGRE": {"RONGRIBO WATREGRE": ["RONGREBO APALGIRI", "RONGREBO WATREGRE"]}, "RONGRIGRE": {"RONGRIGRE": ["RONGREGRE"]}, "RONGSAK BAZAR": {"RONGSAK BAZAR": ["BAPRAGRE", "RONGSAK BAZAR", "RONGSAK GREEN HILLS"]}, "RONGSAK SONGGITAL": {"RONGSAK SONGGITAL": ["RONGSAK SONGGITAL"]}, "RONGSAKGRE": {"RONGSAKGRE": ["ALDANGGITTIM", "KALAGRE", "RONGSAKGRE"]}, "RUKALGRE": {"RUKALGRE": ["RUKALGRE"]}, "SAMANDA GONGGRE": {"SAMANDA GONGGRE": ["GONGRRE SONGGITAL", "SAMANDA DOLWAGITTIM"]}, "SAMANDA WAGETGRE": {"SAMANDA WAGETGRE": ["SAMANDA WAGETGRE"]}, "SAMPALGRE": {"SAMPALGRE": ["SAMPALGRE", "SAMPLAGRE SONGGITAL"]}, "SAWILGRE": {"SAWILGRE": ["MATEKPUGITTIM", "SAWILGRE"]}, "SOBOKGRE": {"SOBOKGRE": ["CHAMBUGONGGITTIM", "SOBOKGIRI SONGGITAL", "SOBOKGRE"]}, "SONGMA ADINGGRE": {"SONGMA ADINGGRE": ["SONGMA ADINGGRE"]}, "SONGMAGRE": {"SONGMAGRE": ["SONGMAGRE"]}, "SUCHILGRE": {"SUCHILGRE": ["GRENANGGRE", "KOKDOKGIRI", "SUCHILGRE"]}, "TONGBOL SONGGITAL": {"TONGBOL SONGGITAL": ["TONGBOL SONGGITAL"]}, "TONGBOL SONGGITCHAM": {"TONGBOL SONGGITCHAM": ["TONGBOL APALGRE", "TONGBOL KAMAGRE", "TONGBOL SONGGITCHAM"]}, "UDUGRE": {"UDUGRE": ["TENGGITUGITTIM", "UDUGRE"]}, "WANANGGRE": {"WANANGGRE": ["WANANGGRE"]}}, "SONGSAK": {"ABERAM": {"ABERAM": ["A.BERAM"]}, "AKAROK SONGGITCHAM": {"AKAROK SONGGITCHAM": ["AKHARAK SONGGITCHAN"]}, "AKCHARAK SONGGITAL": {"AKCHARAK SONGGITAL": ["AKCHARAK SONGGITAL"]}, "AKCHAROK AKHIMGRE": {"AKCHAROK AKHIMGRE": ["AKCHAROK AKHIMGRE"]}, "ASIL CHIRING": {"ASIL CHIRING": ["ASIL  CHIRING"]}, "ASIL MINDIL": {"ASIL MINDIL": ["ASIL MINDIL"]}, "ASIL SONGGITAL": {"ASIL SONGGITAL": ["ASANGDANGGRE", "ASIL DIKAGITIM", "ASIL SONGGITAL", "DIKA SONGGITAL"]}, "BALMORAM ADAP": {"BALMORAM ADAP": ["BOLMORAM ADAPGRE", "RONGBARIKGITTIM", "RONGCHASAMGITTIM"]}, "BALMORAM ADING": {"BALMORAM ADING": ["BOLMORAM ADINGGRE", "BOLMORAM RONGTANGRE", "RONGBALGRE"]}, "BALMORAM MISICHIKGRE": {"BALMORAM MISICHIKGRE": ["BOLMORAM MESECHIKGRE", "RONGBRETGITTIM"]}, "BALSRIGITTIM": {"BALSRIGITTIM": ["BALSRIGITTIM"]}, "BANSINGGRE": {"BANSINGGRE": ["BANGSINGIRI SONGGITAL"]}, "BANSINGGRE B": {"BANSINGGRE B": ["BANSINGGRE (B)"]}, "BARIKGRE": {"BARIKGRE": ["BARIK NOKMAGITTIM", "BARIK RONGCHIGITTIM", "BARIK SONGGITAL", "BARIKGRE"]}, "BIGASIH SONMA": {"BIGASIH SONMA": ["BIGASIH SONMA"]}, "BIJASIK CHISIM APAL": {"BIJASIK CHISIM APAL": ["BIJASIK CHIRIM APAL"]}, "BIJASIK MATWA": {"BIJASIK MATWA": ["BIJASIK MATWA"]}, "BIJASIK WAGE - APAL": {"BIJASIK WAGE - APAL": ["BIJASIK WAIGE APAL"]}, "BOLLONGGRE": {"BOLLONGGRE": ["AGA BOLLONGGIRI", "BOLLONGGRE"]}, "BOLLONGGRE REFUGEE": {"BOLLONGGRE REFUGEE": ["BOLLONG REFUGEE"]}, "BOLMORAM AGALGRE": {"BOLMORAM AGALGRE": ["BOLMORAM AGALGRE", "MENDUGITTIM"]}, "BOLMORAM ANGKEKOL": {"BOLMORAM ANGKEKOL": ["BOLMORAM ANGKEKOL", "DOSING SARAM", "NENGSURA APAL"]}, "BOLMORAM DOCHOK": {"BOLMORAM DOCHOK": ["BOLMORAM DOCHOKGRE", "DOCHOK SONGGITAL"]}, "BOLSONGCHOK": {"BOLSONGCHOK": ["BOLSONG CHOK (SONGMEGAP)"]}, "BONE CHIDEKGRE": {"BONE CHIDEKGRE": ["BONE CHIDEKGRE"]}, "BONE CHIJANGGRE": {"BONE CHIJANGGRE": ["BONE CHIJANGGRE", "BONE CHIJANGGRE SONGGITAL"]}, "BONE CHISO": {"BONE CHISO": ["BONE CHISO"]}, "BONE MEGAPGRE": {"BONE MEGAPGRE": ["BONE MEGAPGRE"]}, "BONE SONGGITCHAM": {"BONE SONGGITCHAM": ["BONE SONGGITCHAM"]}, "BONE WATRE": {"BONE WATRE": ["BONE WATREGRE"]}, "CHERAN BOWEGRE": {"CHERAN BOWEGRE": ["CHERAN BONEGRE"]}, "CHIDARET SONGGITAL": {"CHIDARET SONGGITAL": ["CHIDARET SONGGITAL"]}, "CHIDIMIT NAMESA": {"CHIDIMIT NAMESA": ["CHIDIMIT NAMESA"]}, "CHIDIMIT NENGSAT": {"CHIDIMIT NENGSAT": ["CHIDIMIT NENGSAT", "DANINGGITTIM"]}, "CHIDIMIT SARIDAM": {"CHIDIMIT SARIDAM": ["CHIDIMIT SARIDAM"]}, "CHINABAT": {"CHINABAT": ["CHINABAT"]}, "DAGAL AGA": {"DAGAL AGA": ["DOGAL AGA"]}, "DAGAL APAL": {"DAGAL APAL": ["DAGAL APAL"]}, "DAGAL ARINGGA": {"DAGAL ARINGGA": ["DAGAL ARINGA", "GRAGRE"]}, "DAGAL CHIMRAN": {"DAGAL CHIMRAN": ["DAGAL CHIMRAM"]}, "DAGAL CHIWATE": {"DAGAL CHIWATE": ["DAGAL CHIWATE"]}, "DAGAL SAMITY": {"DAGAL SAMITY": ["DAGAL SENITY"]}, "DALBOT BANGBOL": {"DALBOT BANGBOL": ["DALBOT BONGBOL"]}, "DALBOT CHIWATE": {"DALBOT CHIWATE": ["DAL POT CHIWEATE"]}, "DALBOT DALLONGGRE": {"DALBOT DALLONGGRE": ["DALBOT BOLLONGGRE"]}, "DALBOT KONGKIL": {"DALBOT KONGKIL": ["DOLBOT KONGKIL"]}, "DALBOT MATRANG": {"DALBOT MATRANG": ["DALBOT MATRANG"]}, "DALBOT NOKAT": {"DALBOT NOKAT": ["DALBOT NOKAT (UPPER HAMLET)"]}, "DALBOT RONGBOK": {"DALBOT RONGBOK": ["DALPOT RONGBOH"]}, "DAME ABANDA": {"DAME ABANDA": ["DAME ABANDA"]}, "DAME APAL": {"DAME APAL": ["DAME APAL"]}, "DAME BIBRA": {"DAME BIBRA": ["DAM BIBRA"]}, "DANAL DASIK": {"DANAL DASIK": ["DANAL DASIK"]}, "DANG HONG DANGTARY": {"DANG HONG DANGTARY": ["DANG HONG DANGTARY"]}, "DANGKONG CHITOREGRE": {"DANGKONG CHITOREGRE": ["DANG HONG CHITOREGRE"]}, "DANGKONG DORAGRE": {"DANGKONG DORAGRE": ["DONG HONG DAREGRE (TASIKGARE)"]}, "DANGKONG GILMATDAM": {"DANGKONG GILMATDAM": ["DONG HONG GILMATDAM"]}, "DANGKONG SONGGITAL": {"DANGKONG SONGGITAL": ["DANG HONG SONGGITA"]}, "DANGKONG TASEKGRE": {"DANGKONG TASEKGRE": ["DANG KONG TASIGARE"]}, "DANING APAL1,2": {"DANING APAL": ["DARING APAL", "NENGSATOKGITTIM"]}, "DANING APAL3": {"DANING APAL": ["DANING APAL"]}, "DARING-APAL": {"DARING-APAL": ["DARING APAL", "NENGSATOKGITTIM"]}, "DIJOGRE": {"DIJOGRE": ["DORAGRE"]}, "DIMBIL BONEGRE": {"DIMBIL BONEGRE": ["DIMBIL APAL", "DIMBIL BOLDAK", "DIMBIL BONEGRE", "DIMBIL CHERANGRE"]}, "DIMIT": {"DIMIT": ["CHONGCHENGCHENGBARIGRE", "DIMIT", "NONGTALGITTIM", "WADROGITTIM", "WATRESACHITALGITTIM"]}, "DIMIT ONGTAGITTIM": {"DIMIT ONGTAGITTIM": ["DIMIT ONGKATGITTIM"]}, "DIMIT WARIKACHI": {"DIMIT WARIKACHI": ["DIMIT WARIKATCHI"]}, "DINGREPA": {"DINGREPA": ["DINGREPA"]}, "DOBA APAL": {"DOBA APAL": ["DOBA APAL"]}, "DOBU ACHAKPEK": {"DOBU ACHAKPEK": ["ACHAKPEKGITTIM", "ACHUNGLEK", "BANDIRAMGITTIM", "DOBU ACHAKPEK", "TANGKAMA BALAIGITTIM"]}, "DOBU AGALGRE": {"DOBU AGALGRE": ["DOBU AGALGRE"]}, "DOBU ANCHENGBOK": {"DOBU ANCHENGBOK": ["DOBU ANCHENGBOK"]}, "DOBU BAWARANGGITTIM": {"DOBU BAWARANGGITTIM": ["DOBU BAWARANGGITTIM"]}, "DOBU BOLSALGITTIM": {"DOBU BOLSALGITTIM": ["DOBU BOLSALGITTIM"]}, "DOBU CHITIMBING": {"DOBU CHITIMBING": ["DOBU CHITIMBING", "DOBU DIKAGITTIM"]}, "DOBU RIMDING": {"DOBU RIMDING": ["DOBU RIMDING"]}, "DOBU RONGMU": {"DOBU RONGMU": ["DOBU BAZAR", "DOBU RONGMU", "RIMDING APAL", "RIMDING DIKAGITTIM", "RONGCHU SONGGITAL", "RONGMU APAL"]}, "DOKI": {"DOKI": ["DOKI"]}, "DOKRUGRE": {"DOKRUGRE": ["DOKRUGRE"]}, "DORAGRE": {"DORAGRE": ["DORAGRE"]}, "ELATCHI AGA": {"ELATCHI AGA": ["ELATCHI AGA"]}, "ELATCHI APAL": {"ELATCHI APAL": ["ELATCHI APAL"]}, "GABIL SONGGITCHAM": {"GABIL SONGGITCHAM": ["GABIL SONGGITCHAM"]}, "GALMAHPA": {"GALMAHPA": ["GALMAHPA"]}, "GAMBALGONG": {"GAMBALGONG": ["GAM BALGONG"]}, "GERU APAL": {"GERU APAL": ["GERU APAL"]}, "GONGRANG": {"GONGRANG": ["GONGRANG"]}, "GRA SONGITCHAM": {"GRA SONGITCHAM": ["GRA SONGGITCHOM"]}, "HEDU APAL": {"HEDU APAL": ["MEDU APAL"]}, "JAMGE (A)": {"JAMGE (A)": ["JAMGE A", "MANDALGITTIM", "NENGSITGITTIM", "UPPER JAMGE"]}, "JAMGE B": {"JAMGE B": ["JAMGE B", "JAMGE SONGGITAL", "KANGKARIGITTIM", "RONGRE APAL", "TANGKAMA SONGGITAL", "WARIGITTIM"]}, "JOGOGRE": {"JOGOGRE": ["JOGOGRE"]}, "KAKWA BONEGRE": {"KAKWA BONEGRE": ["KAKWA BONEGRE"]}, "KANTRA": {"KANTRA": ["KENTRA"]}, "KOKNAL IMMONG": {"KOKNAL IMMONG": ["KOKNAL IMONG", "KOKNAL NOKAT"]}, "KOKSI NENGSAT": {"KOKSI NENGSAT": ["KOKSI NENGSAT", "RAIJVPUR"]}, "KOKSI RONGKONG": {"KOKSI RONGKONG": ["KOKSO RONG RONG"]}, "KOKSI SONGMA": {"KOKSI SONGMA": ["KOKSI SONGGITAL", "NANGAPA"]}, "KONCHIKOL": {"KONCHIKOL": ["KONCHIKOL"]}, "MANDA CHACHATGRE": {"MANDA CHACHATGRE": ["MANDA"]}, "MANDA CHOCHALGRE": {"MANDA CHOCHALGRE": ["MANDA CHOCHALGRE"]}, "MANDALONG AKOKSI": {"MANDALONG AKOKSI": ["MANDALONG AKOKSI"]}, "MENDAL": {"MENDAL": ["MENDAL", "NEW MENDAL"]}, "MONGNALGRE": {"MONGNALGRE": ["MONGOLGRE"]}, "MORANODI": {"MORANODI": ["MARA NADI"]}, "NAPAK BOLCHUGRE": {"NAPAK BOLCHUGRE": ["NAPAK BOLCHUGRE", "SURE APAL"]}, "NAPAK DOGRUGRE": {"NAPAK DOGRUGRE": ["BANDIRAMGITTIM", "NAPAK DOGRUGRE"]}, "NAPAK SONGMA": {"NAPAK SONGMA": ["NAPAK SONGGITAL", "NAPAK SONGMA"]}, "NAPAK TANGKAMA": {"NAPAK TANGKAMA": ["NAPAK TANGKAMA", "RINGRI APAL", "RONGRIGITTIM", "TANGKAMA SONGGITAL", "WARIGITTIM"]}, "NAPAK TASEK": {"NAPAK TASEK": ["NAPAK TASEK"]}, "NENGSA  APAL": {"NENGSA  APAL": ["NEAGSA APAL"]}, "NIRANGMA": {"NIRANGMA": ["NIRANGMA"]}, "NOREK DALDOT": {"NOREK DALDOT": ["MATCHU JAGITGRE", "NOREK DALBOT"]}, "NOREK MEGAPGRE": {"NOREK MEGAPGRE": ["NOREK MEGAPGRE", "NOREK SODOLGRE"]}, "NOREK NENGJRENG": {"NOREK NENGJRENG": ["NOREK NENGJRENG"]}, "NOREK NENGSAMGRE": {"NOREK NENGSAMGRE": ["NENGSAMGRE SONGGITAL", "NOREK NENGSAMGRE", "RONGBRAKGITTIM"]}, "RAJA APAL": {"RAJA APAL": ["RAJA APAL", "RAJA APAL SONGITAL"]}, "REM-KATONGRI": {"REM-KATONGRI": ["REM KOTONGGRE", "REM SONGGITCHAM"]}, "REM MATCHAKOLGRE": {"REM MATCHAKOLGRE": ["REM MATCHAKOLGRE", "REM NOKMAGITTIM"]}, "REM SONGGITCHAM": {"REM SONGGITCHAM": ["REM SONGGITCHAM"]}, "RESAGRE": {"RESAGRE": ["RESAGRE"]}, "RIMRANG BONEGRE": {"RIMRANG BONEGRE": ["RIMRANG BONEGRE", "RIMRANG KAMAGITTIM", "RIMRANG SONGGITAL"]}, "RONGAP ASIMGRE": {"RONGAP ASIMGRE": ["RONGAP ASIMGRE"]}, "RONGAP MIKILSIMGRE": {"RONGAP MIKILSIMGRE": ["RONGAP MIKILSINGGRE"]}, "RONGAP MRINGGRE": {"RONGAP MRINGGRE": ["RONGAP MRINGGRE"]}, "RONGAP SONGGITAL": {"RONGAP SONGGITAL": ["RONGAP BARIKGRE", "RONGAP BAZAR", "RONGAP SONGGITAL"]}, "RONGAP SONGGITCHAM": {"RONGAP SONGGITCHAM": ["KHERA RONGAP", "RONGAP BARIKGRE", "RONGAP MERAMBOK", "RONGAP SONGGITCHAM"]}, "RONGBALU (A)": {"RONGBALU (A)": ["RONGBALU"]}, "RONGBALU SONGGITAL": {"RONGBALU SONGGITAL": ["RONG BALU SONGITTAL (B)"]}, "RONGCHEK SONGGITAL": {"RONGCHEK SONGGITAL": ["RONGCHEK SONGGITAL"]}, "RONGCHEK SONGGITCHAM": {"RONGCHEK SONGGITCHAM": ["RONGCHEK SONGGITCHAM"]}, "RONGDOLGRE": {"RONGDOLGRE": ["RONGDOLGRE", "RONGDOLGRE SONGGITAL"]}, "RONGRE BAZAR": {"RONGRE BAZAR": ["RONGRE BAZAR"]}, "RONGRENG NOKAT": {"RONGRENG NOKAT": ["RONGRENG NOKAT"]}, "RONGRONG APAL": {"RONGRONG APAL": ["RONG NONG APAL"]}, "RONGRONG KANCHIMIKGRE": {"RONGRONG KANCHIMIKGRE": ["RONG RONG KANCHIMIT"]}, "RONGRONG SONGGITCHAM": {"RONGRONG SONGGITCHAM": ["RONG RONG SONGGITCHAM"]}, "SANEMA": {"SANEMA": ["RONGBOK"]}, "SAWEGRE": {"SAWEGRE": ["SAWEGRE"]}, "SILKOL": {"SILKOL": ["SILKOL"]}, "SKERA - APAL": {"SKERA - APAL": ["SKENA APAL"]}, "SNAL BOLLONG": {"SNAL BOLLONG": ["LADONG", "LARAMGITCHAK", "NENGGARU", "NENGGURI", "RONGBALGRE", "SAMURA", "SNAL BOLLONG", "WACHONGGITTIM"]}, "SNAL DAJRENG": {"SNAL DAJRENG": ["BANCHINGGRE SONGGITAL", "SNAL  DAJRENG", "SNAL APALGRE"]}, "SODAKAM RONGKABOK": {"SODAKAM RONGKABOK": ["CHISOGRE SONGGITAL", "SOKADAM RONGKABOK"]}, "SOK MITEGRE": {"SOK MITEGRE": ["SOK MITEGRE"]}, "SOKADAM AGALGRE": {"SOKADAM AGALGRE": ["SOKADAM AGALGRE", "SOKADAM SONGGITAL", "SOKADAM WARIGITTIM"]}, "SOKADAM ARUAKGRE": {"SOKADAM ARUAKGRE": ["SOKADAM ARUAKGRE"]}, "SOKADAM BALADING": {"SOKADAM BALADING": ["SOKADAM BALADING"]}, "SOKADAM BANGGNA": {"SOKADAM BANGGNA": ["SOKADAM BANGGNA", "UPPER SOKADAM BANGGNA"]}, "SONGSAK - AGALGRE": {"SONGSAK - AGALGRE": ["SONGSAK AGALGRE", "SONGSAK AGALGRE SONGGITAL"]}, "SONGSAK  AGITOK": {"SONGSAK  AGITOK": ["SONGSAK AGITOKGRE", "SONGSAK BAZAR", "SONGSAK CHIDIMIT", "SONGSAK DIKAGITTIM", "SONGSAK GATE"]}, "SONGSAK BOLCHUGRE": {"SONGSAK BOLCHUGRE": ["SONGSAK BOLCHUGRE", "UPPER SONGSAK BOLCHUGRE"]}, "SONGSAK JAREPA": {"SONGSAK JAREPA": ["SONGSAK JAREPAK"]}, "SONGSAK MEGAPGRE": {"SONGSAK MEGAPGRE": ["SONGSAK MEGAPGRE"]}, "TARASIM": {"TARASIM": ["TARASIN"]}, "TEBIL BONEGRE (A)": {"TEBIL BONEGRE (A)": ["TEBIL BONEGRE A"]}, "TEBIL BONEGRE (B)": {"TEBIL BONEGRE (B)": ["NEW TEBIL BONEGRE", "TEBIL BONEGRE B", "TEBIL CHIRING", "TEBIL RONGRIM"]}, "WAGOPGRE": {"WAGOPGRE": ["WAGOPGRE"]}, "WAKPAT APAL": {"WAKPAT APAL": ["WAKPAT APAL"]}, "WATENANGGRE": {"WATENANGGRE": ["WATENANGGRE"]}}}